{
	"start":	{
		"connected":	[{
				"socket":	6,
				"local_host":	"10.0.0.2",
				"local_port":	58638,
				"remote_host":	"10.0.0.1",
				"remote_port":	5001
			}],
		"version":	"iperf 3.12",
		"system_info":	"Linux cs244c-vm 6.1.0-43-cloud-amd64 #1 SMP PREEMPT_DYNAMIC Debian 6.1.162-1 (2026-02-08) x86_64",
		"timestamp":	{
			"time":	"Sat, 07 Mar 2026 23:45:16 GMT",
			"timesecs":	1772927116
		},
		"connecting_to":	{
			"host":	"10.0.0.1",
			"port":	5001
		},
		"cookie":	"73bfypqqalm5ypikh57mr2r7qwpv572z3dji",
		"tcp_mss_default":	1448,
		"target_bitrate":	0,
		"sock_bufsize":	0,
		"sndbuf_actual":	87380,
		"rcvbuf_actual":	87380,
		"test_start":	{
			"protocol":	"TCP",
			"num_streams":	1,
			"blksize":	131072,
			"omit":	0,
			"duration":	15,
			"bytes":	0,
			"blocks":	0,
			"reverse":	0,
			"tos":	0,
			"target_bitrate":	0
		}
	},
	"intervals":	[{
			"streams":	[{
					"socket":	6,
					"start":	0,
					"end":	0.100159,
					"seconds":	0.10015899688005447,
					"bytes":	414128,
					"bits_per_second":	33077647.572364528,
					"retransmits":	0,
					"snd_cwnd":	97016,
					"snd_wnd":	173056,
					"rtt":	30197,
					"rttvar":	7074,
					"pmtu":	1500,
					"omitted":	false,
					"sender":	true
				}],
			"sum":	{
				"start":	0,
				"end":	0.100159,
				"seconds":	0.10015899688005447,
				"bytes":	414128,
				"bits_per_second":	33077647.572364528,
				"retransmits":	0,
				"omitted":	false,
				"sender":	true
			}
		}, {
			"streams":	[{
					"socket":	6,
					"start":	0.100159,
					"end":	0.200153,
					"seconds":	0.099993996322155,
					"bytes":	141904,
					"bits_per_second":	11353001.59764166,
					"retransmits":	0,
					"snd_cwnd":	102808,
					"snd_wnd":	270336,
					"rtt":	65616,
					"rttvar":	19544,
					"pmtu":	1500,
					"omitted":	false,
					"sender":	true
				}],
			"sum":	{
				"start":	0.100159,
				"end":	0.200153,
				"seconds":	0.099993996322155,
				"bytes":	141904,
				"bits_per_second":	11353001.59764166,
				"retransmits":	0,
				"omitted":	false,
				"sender":	true
			}
		}, {
			"streams":	[{
					"socket":	6,
					"start":	0.200153,
					"end":	0.300147,
					"seconds":	0.099993996322155,
					"bytes":	130320,
					"bits_per_second":	10426225.957017852,
					"retransmits":	0,
					"snd_cwnd":	108600,
					"snd_wnd":	278016,
					"rtt":	80697,
					"rttvar":	7255,
					"pmtu":	1500,
					"omitted":	false,
					"sender":	true
				}],
			"sum":	{
				"start":	0.200153,
				"end":	0.300147,
				"seconds":	0.099993996322155,
				"bytes":	130320,
				"bits_per_second":	10426225.957017852,
				"retransmits":	0,
				"omitted":	false,
				"sender":	true
			}
		}, {
			"streams":	[{
					"socket":	6,
					"start":	0.300147,
					"end":	0.400149,
					"seconds":	0.10000199824571609,
					"bytes":	130320,
					"bits_per_second":	10425391.675057467,
					"retransmits":	0,
					"snd_cwnd":	114392,
					"snd_wnd":	327168,
					"rtt":	89557,
					"rttvar":	3442,
					"pmtu":	1500,
					"omitted":	false,
					"sender":	true
				}],
			"sum":	{
				"start":	0.300147,
				"end":	0.400149,
				"seconds":	0.10000199824571609,
				"bytes":	130320,
				"bits_per_second":	10425391.675057467,
				"retransmits":	0,
				"omitted":	false,
				"sender":	true
			}
		}, {
			"streams":	[{
					"socket":	6,
					"start":	0.400149,
					"end":	0.500143,
					"seconds":	0.099993996322155,
					"bytes":	130320,
					"bits_per_second":	10426225.957017852,
					"retransmits":	0,
					"snd_cwnd":	121632,
					"snd_wnd":	321024,
					"rtt":	94315,
					"rttvar":	2094,
					"pmtu":	1500,
					"omitted":	false,
					"sender":	true
				}],
			"sum":	{
				"start":	0.400149,
				"end":	0.500143,
				"seconds":	0.099993996322155,
				"bytes":	130320,
				"bits_per_second":	10426225.957017852,
				"retransmits":	0,
				"omitted":	false,
				"sender":	true
			}
		}, {
			"streams":	[{
					"socket":	6,
					"start":	0.500143,
					"end":	0.600136,
					"seconds":	0.099992997944355,
					"bytes":	195480,
					"bits_per_second":	15639495.086148527,
					"retransmits":	0,
					"snd_cwnd":	127424,
					"snd_wnd":	320000,
					"rtt":	99345,
					"rttvar":	2086,
					"pmtu":	1500,
					"omitted":	false,
					"sender":	true
				}],
			"sum":	{
				"start":	0.500143,
				"end":	0.600136,
				"seconds":	0.099992997944355,
				"bytes":	195480,
				"bits_per_second":	15639495.086148527,
				"retransmits":	0,
				"omitted":	false,
				"sender":	true
			}
		}, {
			"streams":	[{
					"socket":	6,
					"start":	0.600136,
					"end":	0.700211,
					"seconds":	0.10007499903440475,
					"bytes":	0,
					"bits_per_second":	0,
					"retransmits":	0,
					"snd_cwnd":	133216,
					"snd_wnd":	324608,
					"rtt":	104206,
					"rttvar":	1857,
					"pmtu":	1500,
					"omitted":	false,
					"sender":	true
				}],
			"sum":	{
				"start":	0.600136,
				"end":	0.700211,
				"seconds":	0.10007499903440475,
				"bytes":	0,
				"bits_per_second":	0,
				"retransmits":	0,
				"omitted":	false,
				"sender":	true
			}
		}, {
			"streams":	[{
					"socket":	6,
					"start":	0.700211,
					"end":	0.80016,
					"seconds":	0.099949002265930176,
					"bytes":	195480,
					"bits_per_second":	15646379.298906412,
					"retransmits":	0,
					"snd_cwnd":	139008,
					"snd_wnd":	324608,
					"rtt":	107831,
					"rttvar":	1403,
					"pmtu":	1500,
					"omitted":	false,
					"sender":	true
				}],
			"sum":	{
				"start":	0.700211,
				"end":	0.80016,
				"seconds":	0.099949002265930176,
				"bytes":	195480,
				"bits_per_second":	15646379.298906412,
				"retransmits":	0,
				"omitted":	false,
				"sender":	true
			}
		}, {
			"streams":	[{
					"socket":	6,
					"start":	0.80016,
					"end":	0.900169,
					"seconds":	0.1000090017914772,
					"bytes":	195480,
					"bits_per_second":	15636992.390551696,
					"retransmits":	0,
					"snd_cwnd":	144800,
					"snd_wnd":	322560,
					"rtt":	113448,
					"rttvar":	2764,
					"pmtu":	1500,
					"omitted":	false,
					"sender":	true
				}],
			"sum":	{
				"start":	0.80016,
				"end":	0.900169,
				"seconds":	0.1000090017914772,
				"bytes":	195480,
				"bits_per_second":	15636992.390551696,
				"retransmits":	0,
				"omitted":	false,
				"sender":	true
			}
		}, {
			"streams":	[{
					"socket":	6,
					"start":	0.900169,
					"end":	1.000175,
					"seconds":	0.10000599920749664,
					"bytes":	0,
					"bits_per_second":	0,
					"retransmits":	0,
					"snd_cwnd":	150592,
					"snd_wnd":	335360,
					"rtt":	118030,
					"rttvar":	1827,
					"pmtu":	1500,
					"omitted":	false,
					"sender":	true
				}],
			"sum":	{
				"start":	0.900169,
				"end":	1.000175,
				"seconds":	0.10000599920749664,
				"bytes":	0,
				"bits_per_second":	0,
				"retransmits":	0,
				"omitted":	false,
				"sender":	true
			}
		}, {
			"streams":	[{
					"socket":	6,
					"start":	1.000175,
					"end":	1.100159,
					"seconds":	0.099983997642993927,
					"bytes":	195480,
					"bits_per_second":	15640902.913123131,
					"retransmits":	0,
					"snd_cwnd":	156384,
					"snd_wnd":	336384,
					"rtt":	122879,
					"rttvar":	1969,
					"pmtu":	1500,
					"omitted":	false,
					"sender":	true
				}],
			"sum":	{
				"start":	1.000175,
				"end":	1.100159,
				"seconds":	0.099983997642993927,
				"bytes":	195480,
				"bits_per_second":	15640902.913123131,
				"retransmits":	0,
				"omitted":	false,
				"sender":	true
			}
		}, {
			"streams":	[{
					"socket":	6,
					"start":	1.100159,
					"end":	1.20014,
					"seconds":	0.099981002509593964,
					"bytes":	195480,
					"bits_per_second":	15641371.468044015,
					"retransmits":	0,
					"snd_cwnd":	162176,
					"snd_wnd":	355840,
					"rtt":	127927,
					"rttvar":	2199,
					"pmtu":	1500,
					"omitted":	false,
					"sender":	true
				}],
			"sum":	{
				"start":	1.100159,
				"end":	1.20014,
				"seconds":	0.099981002509593964,
				"bytes":	195480,
				"bits_per_second":	15641371.468044015,
				"retransmits":	0,
				"omitted":	false,
				"sender":	true
			}
		}, {
			"streams":	[{
					"socket":	6,
					"start":	1.20014,
					"end":	1.300363,
					"seconds":	0.10022299736738205,
					"bytes":	0,
					"bits_per_second":	0,
					"retransmits":	0,
					"snd_cwnd":	167968,
					"snd_wnd":	356864,
					"rtt":	132502,
					"rttvar":	1430,
					"pmtu":	1500,
					"omitted":	false,
					"sender":	true
				}],
			"sum":	{
				"start":	1.20014,
				"end":	1.300363,
				"seconds":	0.10022299736738205,
				"bytes":	0,
				"bits_per_second":	0,
				"retransmits":	0,
				"omitted":	false,
				"sender":	true
			}
		}, {
			"streams":	[{
					"socket":	6,
					"start":	1.300363,
					"end":	1.400196,
					"seconds":	0.099832996726036072,
					"bytes":	195480,
					"bits_per_second":	15664560.328600818,
					"retransmits":	0,
					"snd_cwnd":	175208,
					"snd_wnd":	386560,
					"rtt":	136681,
					"rttvar":	1494,
					"pmtu":	1500,
					"omitted":	false,
					"sender":	true
				}],
			"sum":	{
				"start":	1.300363,
				"end":	1.400196,
				"seconds":	0.099832996726036072,
				"bytes":	195480,
				"bits_per_second":	15664560.328600818,
				"retransmits":	0,
				"omitted":	false,
				"sender":	true
			}
		}, {
			"streams":	[{
					"socket":	6,
					"start":	1.400196,
					"end":	1.500152,
					"seconds":	0.0999559983611107,
					"bytes":	195480,
					"bits_per_second":	15645284.181448728,
					"retransmits":	0,
					"snd_cwnd":	181000,
					"snd_wnd":	388608,
					"rtt":	142325,
					"rttvar":	1172,
					"pmtu":	1500,
					"omitted":	false,
					"sender":	true
				}],
			"sum":	{
				"start":	1.400196,
				"end":	1.500152,
				"seconds":	0.0999559983611107,
				"bytes":	195480,
				"bits_per_second":	15645284.181448728,
				"retransmits":	0,
				"omitted":	false,
				"sender":	true
			}
		}, {
			"streams":	[{
					"socket":	6,
					"start":	1.500152,
					"end":	1.600213,
					"seconds":	0.10006099939346313,
					"bytes":	0,
					"bits_per_second":	0,
					"retransmits":	0,
					"snd_cwnd":	186792,
					"snd_wnd":	397312,
					"rtt":	145896,
					"rttvar":	1481,
					"pmtu":	1500,
					"omitted":	false,
					"sender":	true
				}],
			"sum":	{
				"start":	1.500152,
				"end":	1.600213,
				"seconds":	0.10006099939346313,
				"bytes":	0,
				"bits_per_second":	0,
				"retransmits":	0,
				"omitted":	false,
				"sender":	true
			}
		}, {
			"streams":	[{
					"socket":	6,
					"start":	1.600213,
					"end":	1.700166,
					"seconds":	0.099953003227710724,
					"bytes":	260640,
					"bits_per_second":	20861003.998546455,
					"retransmits":	0,
					"snd_cwnd":	192584,
					"snd_wnd":	417280,
					"rtt":	151603,
					"rttvar":	2275,
					"pmtu":	1500,
					"omitted":	false,
					"sender":	true
				}],
			"sum":	{
				"start":	1.600213,
				"end":	1.700166,
				"seconds":	0.099953003227710724,
				"bytes":	260640,
				"bits_per_second":	20861003.998546455,
				"retransmits":	0,
				"omitted":	false,
				"sender":	true
			}
		}, {
			"streams":	[{
					"socket":	6,
					"start":	1.700166,
					"end":	1.800197,
					"seconds":	0.10003100335597992,
					"bytes":	0,
					"bits_per_second":	0,
					"retransmits":	0,
					"snd_cwnd":	198376,
					"snd_wnd":	417792,
					"rtt":	156334,
					"rttvar":	1798,
					"pmtu":	1500,
					"omitted":	false,
					"sender":	true
				}],
			"sum":	{
				"start":	1.700166,
				"end":	1.800197,
				"seconds":	0.10003100335597992,
				"bytes":	0,
				"bits_per_second":	0,
				"retransmits":	0,
				"omitted":	false,
				"sender":	true
			}
		}, {
			"streams":	[{
					"socket":	6,
					"start":	1.800197,
					"end":	1.900181,
					"seconds":	0.099983997642993927,
					"bytes":	260640,
					"bits_per_second":	20854537.217497509,
					"retransmits":	0,
					"snd_cwnd":	204168,
					"snd_wnd":	417280,
					"rtt":	161151,
					"rttvar":	1798,
					"pmtu":	1500,
					"omitted":	false,
					"sender":	true
				}],
			"sum":	{
				"start":	1.800197,
				"end":	1.900181,
				"seconds":	0.099983997642993927,
				"bytes":	260640,
				"bits_per_second":	20854537.217497509,
				"retransmits":	0,
				"omitted":	false,
				"sender":	true
			}
		}, {
			"streams":	[{
					"socket":	6,
					"start":	1.900181,
					"end":	2.000173,
					"seconds":	0.099991999566555023,
					"bytes":	0,
					"bits_per_second":	0,
					"retransmits":	0,
					"snd_cwnd":	211408,
					"snd_wnd":	417280,
					"rtt":	165273,
					"rttvar":	1686,
					"pmtu":	1500,
					"omitted":	false,
					"sender":	true
				}],
			"sum":	{
				"start":	1.900181,
				"end":	2.000173,
				"seconds":	0.099991999566555023,
				"bytes":	0,
				"bits_per_second":	0,
				"retransmits":	0,
				"omitted":	false,
				"sender":	true
			}
		}, {
			"streams":	[{
					"socket":	6,
					"start":	2.000173,
					"end":	2.100151,
					"seconds":	0.0999779999256134,
					"bytes":	260640,
					"bits_per_second":	20855788.288937476,
					"retransmits":	0,
					"snd_cwnd":	215752,
					"snd_wnd":	639488,
					"rtt":	170291,
					"rttvar":	2217,
					"pmtu":	1500,
					"omitted":	false,
					"sender":	true
				}],
			"sum":	{
				"start":	2.000173,
				"end":	2.100151,
				"seconds":	0.0999779999256134,
				"bytes":	260640,
				"bits_per_second":	20855788.288937476,
				"retransmits":	0,
				"omitted":	false,
				"sender":	true
			}
		}, {
			"streams":	[{
					"socket":	6,
					"start":	2.100151,
					"end":	2.200188,
					"seconds":	0.10003700107336044,
					"bytes":	0,
					"bits_per_second":	0,
					"retransmits":	0,
					"snd_cwnd":	222992,
					"snd_wnd":	636416,
					"rtt":	175791,
					"rttvar":	2181,
					"pmtu":	1500,
					"omitted":	false,
					"sender":	true
				}],
			"sum":	{
				"start":	2.100151,
				"end":	2.200188,
				"seconds":	0.10003700107336044,
				"bytes":	0,
				"bits_per_second":	0,
				"retransmits":	0,
				"omitted":	false,
				"sender":	true
			}
		}, {
			"streams":	[{
					"socket":	6,
					"start":	2.200188,
					"end":	2.300154,
					"seconds":	0.099965997040271759,
					"bytes":	260640,
					"bits_per_second":	20858292.436777275,
					"retransmits":	0,
					"snd_cwnd":	228784,
					"snd_wnd":	642048,
					"rtt":	180459,
					"rttvar":	1890,
					"pmtu":	1500,
					"omitted":	false,
					"sender":	true
				}],
			"sum":	{
				"start":	2.200188,
				"end":	2.300154,
				"seconds":	0.099965997040271759,
				"bytes":	260640,
				"bits_per_second":	20858292.436777275,
				"retransmits":	0,
				"omitted":	false,
				"sender":	true
			}
		}, {
			"streams":	[{
					"socket":	6,
					"start":	2.300154,
					"end":	2.400214,
					"seconds":	0.10006000101566315,
					"bytes":	0,
					"bits_per_second":	0,
					"retransmits":	0,
					"snd_cwnd":	234576,
					"snd_wnd":	642048,
					"rtt":	185593,
					"rttvar":	2162,
					"pmtu":	1500,
					"omitted":	false,
					"sender":	true
				}],
			"sum":	{
				"start":	2.300154,
				"end":	2.400214,
				"seconds":	0.10006000101566315,
				"bytes":	0,
				"bits_per_second":	0,
				"retransmits":	0,
				"omitted":	false,
				"sender":	true
			}
		}, {
			"streams":	[{
					"socket":	6,
					"start":	2.400214,
					"end":	2.500181,
					"seconds":	0.099967002868652344,
					"bytes":	260640,
					"bits_per_second":	20858082.568901863,
					"retransmits":	0,
					"snd_cwnd":	240368,
					"snd_wnd":	642048,
					"rtt":	189945,
					"rttvar":	1965,
					"pmtu":	1500,
					"omitted":	false,
					"sender":	true
				}],
			"sum":	{
				"start":	2.400214,
				"end":	2.500181,
				"seconds":	0.099967002868652344,
				"bytes":	260640,
				"bits_per_second":	20858082.568901863,
				"retransmits":	0,
				"omitted":	false,
				"sender":	true
			}
		}, {
			"streams":	[{
					"socket":	6,
					"start":	2.500181,
					"end":	2.600196,
					"seconds":	0.10001499950885773,
					"bytes":	0,
					"bits_per_second":	0,
					"retransmits":	0,
					"snd_cwnd":	246160,
					"snd_wnd":	642048,
					"rtt":	195420,
					"rttvar":	1959,
					"pmtu":	1500,
					"omitted":	false,
					"sender":	true
				}],
			"sum":	{
				"start":	2.500181,
				"end":	2.600196,
				"seconds":	0.10001499950885773,
				"bytes":	0,
				"bits_per_second":	0,
				"retransmits":	0,
				"omitted":	false,
				"sender":	true
			}
		}, {
			"streams":	[{
					"socket":	6,
					"start":	2.600196,
					"end":	2.700186,
					"seconds":	0.099990002810955048,
					"bytes":	325800,
					"bits_per_second":	26066605.927872211,
					"retransmits":	0,
					"snd_cwnd":	251952,
					"snd_wnd":	642048,
					"rtt":	199993,
					"rttvar":	1676,
					"pmtu":	1500,
					"omitted":	false,
					"sender":	true
				}],
			"sum":	{
				"start":	2.600196,
				"end":	2.700186,
				"seconds":	0.099990002810955048,
				"bytes":	325800,
				"bits_per_second":	26066605.927872211,
				"retransmits":	0,
				"omitted":	false,
				"sender":	true
			}
		}, {
			"streams":	[{
					"socket":	6,
					"start":	2.700186,
					"end":	2.800163,
					"seconds":	0.0999770015478134,
					"bytes":	0,
					"bits_per_second":	0,
					"retransmits":	0,
					"snd_cwnd":	257744,
					"snd_wnd":	643584,
					"rtt":	204269,
					"rttvar":	1213,
					"pmtu":	1500,
					"omitted":	false,
					"sender":	true
				}],
			"sum":	{
				"start":	2.700186,
				"end":	2.800163,
				"seconds":	0.0999770015478134,
				"bytes":	0,
				"bits_per_second":	0,
				"retransmits":	0,
				"omitted":	false,
				"sender":	true
			}
		}, {
			"streams":	[{
					"socket":	6,
					"start":	2.800163,
					"end":	2.900098,
					"seconds":	0.099935002624988556,
					"bytes":	325800,
					"bits_per_second":	26080951.934135184,
					"retransmits":	0,
					"snd_cwnd":	263536,
					"snd_wnd":	643584,
					"rtt":	208878,
					"rttvar":	1735,
					"pmtu":	1500,
					"omitted":	false,
					"sender":	true
				}],
			"sum":	{
				"start":	2.800163,
				"end":	2.900098,
				"seconds":	0.099935002624988556,
				"bytes":	325800,
				"bits_per_second":	26080951.934135184,
				"retransmits":	0,
				"omitted":	false,
				"sender":	true
			}
		}, {
			"streams":	[{
					"socket":	6,
					"start":	2.900098,
					"end":	3.000148,
					"seconds":	0.10005000233650208,
					"bytes":	0,
					"bits_per_second":	0,
					"retransmits":	0,
					"snd_cwnd":	270776,
					"snd_wnd":	636416,
					"rtt":	213210,
					"rttvar":	1483,
					"pmtu":	1500,
					"omitted":	false,
					"sender":	true
				}],
			"sum":	{
				"start":	2.900098,
				"end":	3.000148,
				"seconds":	0.10005000233650208,
				"bytes":	0,
				"bits_per_second":	0,
				"retransmits":	0,
				"omitted":	false,
				"sender":	true
			}
		}, {
			"streams":	[{
					"socket":	6,
					"start":	3.000148,
					"end":	3.100186,
					"seconds":	0.10003799945116043,
					"bytes":	0,
					"bits_per_second":	0,
					"retransmits":	0,
					"snd_cwnd":	276568,
					"snd_wnd":	636416,
					"rtt":	218633,
					"rttvar":	1746,
					"pmtu":	1500,
					"omitted":	false,
					"sender":	true
				}],
			"sum":	{
				"start":	3.000148,
				"end":	3.100186,
				"seconds":	0.10003799945116043,
				"bytes":	0,
				"bits_per_second":	0,
				"retransmits":	0,
				"omitted":	false,
				"sender":	true
			}
		}, {
			"streams":	[{
					"socket":	6,
					"start":	3.100186,
					"end":	3.200178,
					"seconds":	0.099991999566555023,
					"bytes":	325800,
					"bits_per_second":	26066085.399814121,
					"retransmits":	0,
					"snd_cwnd":	282360,
					"snd_wnd":	637440,
					"rtt":	223551,
					"rttvar":	1540,
					"pmtu":	1500,
					"omitted":	false,
					"sender":	true
				}],
			"sum":	{
				"start":	3.100186,
				"end":	3.200178,
				"seconds":	0.099991999566555023,
				"bytes":	325800,
				"bits_per_second":	26066085.399814121,
				"retransmits":	0,
				"omitted":	false,
				"sender":	true
			}
		}, {
			"streams":	[{
					"socket":	6,
					"start":	3.200178,
					"end":	3.300199,
					"seconds":	0.10002099722623825,
					"bytes":	0,
					"bits_per_second":	0,
					"retransmits":	0,
					"snd_cwnd":	285256,
					"snd_wnd":	640512,
					"rtt":	250494,
					"rttvar":	19261,
					"pmtu":	1500,
					"omitted":	false,
					"sender":	true
				}],
			"sum":	{
				"start":	3.200178,
				"end":	3.300199,
				"seconds":	0.10002099722623825,
				"bytes":	0,
				"bits_per_second":	0,
				"retransmits":	0,
				"omitted":	false,
				"sender":	true
			}
		}, {
			"streams":	[{
					"socket":	6,
					"start":	3.300199,
					"end":	3.400219,
					"seconds":	0.10001999884843826,
					"bytes":	0,
					"bits_per_second":	0,
					"retransmits":	0,
					"snd_cwnd":	292496,
					"snd_wnd":	642048,
					"rtt":	266353,
					"rttvar":	3938,
					"pmtu":	1500,
					"omitted":	false,
					"sender":	true
				}],
			"sum":	{
				"start":	3.300199,
				"end":	3.400219,
				"seconds":	0.10001999884843826,
				"bytes":	0,
				"bits_per_second":	0,
				"retransmits":	0,
				"omitted":	false,
				"sender":	true
			}
		}, {
			"streams":	[{
					"socket":	6,
					"start":	3.400219,
					"end":	3.500182,
					"seconds":	0.0999630019068718,
					"bytes":	325800,
					"bits_per_second":	26073646.752107263,
					"retransmits":	0,
					"snd_cwnd":	298288,
					"snd_wnd":	638976,
					"rtt":	271432,
					"rttvar":	1895,
					"pmtu":	1500,
					"omitted":	false,
					"sender":	true
				}],
			"sum":	{
				"start":	3.400219,
				"end":	3.500182,
				"seconds":	0.0999630019068718,
				"bytes":	325800,
				"bits_per_second":	26073646.752107263,
				"retransmits":	0,
				"omitted":	false,
				"sender":	true
			}
		}, {
			"streams":	[{
					"socket":	6,
					"start":	3.500182,
					"end":	3.600191,
					"seconds":	0.1000090017914772,
					"bytes":	0,
					"bits_per_second":	0,
					"retransmits":	0,
					"snd_cwnd":	301184,
					"snd_wnd":	638464,
					"rtt":	268171,
					"rttvar":	4260,
					"pmtu":	1500,
					"omitted":	false,
					"sender":	true
				}],
			"sum":	{
				"start":	3.500182,
				"end":	3.600191,
				"seconds":	0.1000090017914772,
				"bytes":	0,
				"bits_per_second":	0,
				"retransmits":	0,
				"omitted":	false,
				"sender":	true
			}
		}, {
			"streams":	[{
					"socket":	6,
					"start":	3.600191,
					"end":	3.700181,
					"seconds":	0.099990002810955048,
					"bytes":	0,
					"bits_per_second":	0,
					"retransmits":	0,
					"snd_cwnd":	305528,
					"snd_wnd":	641536,
					"rtt":	291570,
					"rttvar":	23306,
					"pmtu":	1500,
					"omitted":	false,
					"sender":	true
				}],
			"sum":	{
				"start":	3.600191,
				"end":	3.700181,
				"seconds":	0.099990002810955048,
				"bytes":	0,
				"bits_per_second":	0,
				"retransmits":	0,
				"omitted":	false,
				"sender":	true
			}
		}, {
			"streams":	[{
					"socket":	6,
					"start":	3.700181,
					"end":	3.800167,
					"seconds":	0.0999860018491745,
					"bytes":	325800,
					"bits_per_second":	26067648.988822117,
					"retransmits":	0,
					"snd_cwnd":	311320,
					"snd_wnd":	665600,
					"rtt":	316866,
					"rttvar":	5359,
					"pmtu":	1500,
					"omitted":	false,
					"sender":	true
				}],
			"sum":	{
				"start":	3.700181,
				"end":	3.800167,
				"seconds":	0.0999860018491745,
				"bytes":	325800,
				"bits_per_second":	26067648.988822117,
				"retransmits":	0,
				"omitted":	false,
				"sender":	true
			}
		}, {
			"streams":	[{
					"socket":	6,
					"start":	3.800167,
					"end":	3.900151,
					"seconds":	0.099983997642993927,
					"bytes":	0,
					"bits_per_second":	0,
					"retransmits":	0,
					"snd_cwnd":	314216,
					"snd_wnd":	671232,
					"rtt":	324964,
					"rttvar":	8144,
					"pmtu":	1500,
					"omitted":	false,
					"sender":	true
				}],
			"sum":	{
				"start":	3.800167,
				"end":	3.900151,
				"seconds":	0.099983997642993927,
				"bytes":	0,
				"bits_per_second":	0,
				"retransmits":	0,
				"omitted":	false,
				"sender":	true
			}
		}, {
			"streams":	[{
					"socket":	6,
					"start":	3.900151,
					"end":	4.000166,
					"seconds":	0.10001499950885773,
					"bytes":	0,
					"bits_per_second":	0,
					"retransmits":	0,
					"snd_cwnd":	318560,
					"snd_wnd":	667136,
					"rtt":	338108,
					"rttvar":	16413,
					"pmtu":	1500,
					"omitted":	false,
					"sender":	true
				}],
			"sum":	{
				"start":	3.900151,
				"end":	4.000166,
				"seconds":	0.10001499950885773,
				"bytes":	0,
				"bits_per_second":	0,
				"retransmits":	0,
				"omitted":	false,
				"sender":	true
			}
		}, {
			"streams":	[{
					"socket":	6,
					"start":	4.000166,
					"end":	4.100136,
					"seconds":	0.0999699980020523,
					"bytes":	390960,
					"bits_per_second":	31286186.481025949,
					"retransmits":	0,
					"snd_cwnd":	322904,
					"snd_wnd":	664064,
					"rtt":	353019,
					"rttvar":	9452,
					"pmtu":	1500,
					"omitted":	false,
					"sender":	true
				}],
			"sum":	{
				"start":	4.000166,
				"end":	4.100136,
				"seconds":	0.0999699980020523,
				"bytes":	390960,
				"bits_per_second":	31286186.481025949,
				"retransmits":	0,
				"omitted":	false,
				"sender":	true
			}
		}, {
			"streams":	[{
					"socket":	6,
					"start":	4.100136,
					"end":	4.200206,
					"seconds":	0.10006999969482422,
					"bytes":	0,
					"bits_per_second":	0,
					"retransmits":	0,
					"snd_cwnd":	328696,
					"snd_wnd":	722944,
					"rtt":	358664,
					"rttvar":	4311,
					"pmtu":	1500,
					"omitted":	false,
					"sender":	true
				}],
			"sum":	{
				"start":	4.100136,
				"end":	4.200206,
				"seconds":	0.10006999969482422,
				"bytes":	0,
				"bits_per_second":	0,
				"retransmits":	0,
				"omitted":	false,
				"sender":	true
			}
		}, {
			"streams":	[{
					"socket":	6,
					"start":	4.200206,
					"end":	4.300193,
					"seconds":	0.0999870002269745,
					"bytes":	0,
					"bits_per_second":	0,
					"retransmits":	0,
					"snd_cwnd":	331592,
					"snd_wnd":	717824,
					"rtt":	363326,
					"rttvar":	3757,
					"pmtu":	1500,
					"omitted":	false,
					"sender":	true
				}],
			"sum":	{
				"start":	4.200206,
				"end":	4.300193,
				"seconds":	0.0999870002269745,
				"bytes":	0,
				"bits_per_second":	0,
				"retransmits":	0,
				"omitted":	false,
				"sender":	true
			}
		}, {
			"streams":	[{
					"socket":	6,
					"start":	4.300193,
					"end":	4.400227,
					"seconds":	0.10003399848937988,
					"bytes":	0,
					"bits_per_second":	0,
					"retransmits":	0,
					"snd_cwnd":	334488,
					"snd_wnd":	717824,
					"rtt":	367420,
					"rttvar":	5236,
					"pmtu":	1500,
					"omitted":	false,
					"sender":	true
				}],
			"sum":	{
				"start":	4.300193,
				"end":	4.400227,
				"seconds":	0.10003399848937988,
				"bytes":	0,
				"bits_per_second":	0,
				"retransmits":	0,
				"omitted":	false,
				"sender":	true
			}
		}, {
			"streams":	[{
					"socket":	6,
					"start":	4.400227,
					"end":	4.500129,
					"seconds":	0.0999019965529442,
					"bytes":	390960,
					"bits_per_second":	31307482.4119501,
					"retransmits":	0,
					"snd_cwnd":	340280,
					"snd_wnd":	717824,
					"rtt":	382229,
					"rttvar":	14347,
					"pmtu":	1500,
					"omitted":	false,
					"sender":	true
				}],
			"sum":	{
				"start":	4.400227,
				"end":	4.500129,
				"seconds":	0.0999019965529442,
				"bytes":	390960,
				"bits_per_second":	31307482.4119501,
				"retransmits":	0,
				"omitted":	false,
				"sender":	true
			}
		}, {
			"streams":	[{
					"socket":	6,
					"start":	4.500129,
					"end":	4.600189,
					"seconds":	0.10006000101566315,
					"bytes":	0,
					"bits_per_second":	0,
					"retransmits":	0,
					"snd_cwnd":	344624,
					"snd_wnd":	717824,
					"rtt":	389184,
					"rttvar":	3708,
					"pmtu":	1500,
					"omitted":	false,
					"sender":	true
				}],
			"sum":	{
				"start":	4.500129,
				"end":	4.600189,
				"seconds":	0.10006000101566315,
				"bytes":	0,
				"bits_per_second":	0,
				"retransmits":	0,
				"omitted":	false,
				"sender":	true
			}
		}, {
			"streams":	[{
					"socket":	6,
					"start":	4.600189,
					"end":	4.700215,
					"seconds":	0.10002599656581879,
					"bytes":	0,
					"bits_per_second":	0,
					"retransmits":	0,
					"snd_cwnd":	348968,
					"snd_wnd":	717824,
					"rtt":	399226,
					"rttvar":	4445,
					"pmtu":	1500,
					"omitted":	false,
					"sender":	true
				}],
			"sum":	{
				"start":	4.600189,
				"end":	4.700215,
				"seconds":	0.10002599656581879,
				"bytes":	0,
				"bits_per_second":	0,
				"retransmits":	0,
				"omitted":	false,
				"sender":	true
			}
		}, {
			"streams":	[{
					"socket":	6,
					"start":	4.700215,
					"end":	4.800192,
					"seconds":	0.0999770015478134,
					"bytes":	0,
					"bits_per_second":	0,
					"retransmits":	0,
					"snd_cwnd":	351864,
					"snd_wnd":	717824,
					"rtt":	401437,
					"rttvar":	2257,
					"pmtu":	1500,
					"omitted":	false,
					"sender":	true
				}],
			"sum":	{
				"start":	4.700215,
				"end":	4.800192,
				"seconds":	0.0999770015478134,
				"bytes":	0,
				"bits_per_second":	0,
				"retransmits":	0,
				"omitted":	false,
				"sender":	true
			}
		}, {
			"streams":	[{
					"socket":	6,
					"start":	4.800192,
					"end":	4.900192,
					"seconds":	0.10000000149011612,
					"bytes":	0,
					"bits_per_second":	0,
					"retransmits":	0,
					"snd_cwnd":	356208,
					"snd_wnd":	718848,
					"rtt":	406710,
					"rttvar":	6993,
					"pmtu":	1500,
					"omitted":	false,
					"sender":	true
				}],
			"sum":	{
				"start":	4.800192,
				"end":	4.900192,
				"seconds":	0.10000000149011612,
				"bytes":	0,
				"bits_per_second":	0,
				"retransmits":	0,
				"omitted":	false,
				"sender":	true
			}
		}, {
			"streams":	[{
					"socket":	6,
					"start":	4.900192,
					"end":	5.000192,
					"seconds":	0.10000000149011612,
					"bytes":	0,
					"bits_per_second":	0,
					"retransmits":	15,
					"snd_cwnd":	309872,
					"snd_wnd":	718848,
					"rtt":	405742,
					"rttvar":	2830,
					"pmtu":	1500,
					"omitted":	false,
					"sender":	true
				}],
			"sum":	{
				"start":	4.900192,
				"end":	5.000192,
				"seconds":	0.10000000149011612,
				"bytes":	0,
				"bits_per_second":	0,
				"retransmits":	15,
				"omitted":	false,
				"sender":	true
			}
		}, {
			"streams":	[{
					"socket":	6,
					"start":	5.000192,
					"end":	5.100192,
					"seconds":	0.10000000149011612,
					"bytes":	0,
					"bits_per_second":	0,
					"retransmits":	0,
					"snd_cwnd":	291048,
					"snd_wnd":	718848,
					"rtt":	405739,
					"rttvar":	1111,
					"pmtu":	1500,
					"omitted":	false,
					"sender":	true
				}],
			"sum":	{
				"start":	5.000192,
				"end":	5.100192,
				"seconds":	0.10000000149011612,
				"bytes":	0,
				"bits_per_second":	0,
				"retransmits":	0,
				"omitted":	false,
				"sender":	true
			}
		}, {
			"streams":	[{
					"socket":	6,
					"start":	5.100192,
					"end":	5.200339,
					"seconds":	0.10014700144529343,
					"bytes":	0,
					"bits_per_second":	0,
					"retransmits":	2,
					"snd_cwnd":	262088,
					"snd_wnd":	718848,
					"rtt":	404463,
					"rttvar":	1411,
					"pmtu":	1500,
					"omitted":	false,
					"sender":	true
				}],
			"sum":	{
				"start":	5.100192,
				"end":	5.200339,
				"seconds":	0.10014700144529343,
				"bytes":	0,
				"bits_per_second":	0,
				"retransmits":	2,
				"omitted":	false,
				"sender":	true
			}
		}, {
			"streams":	[{
					"socket":	6,
					"start":	5.200339,
					"end":	5.300196,
					"seconds":	0.09985700249671936,
					"bytes":	0,
					"bits_per_second":	0,
					"retransmits":	1,
					"snd_cwnd":	249056,
					"snd_wnd":	718848,
					"rtt":	401784,
					"rttvar":	2754,
					"pmtu":	1500,
					"omitted":	false,
					"sender":	true
				}],
			"sum":	{
				"start":	5.200339,
				"end":	5.300196,
				"seconds":	0.09985700249671936,
				"bytes":	0,
				"bits_per_second":	0,
				"retransmits":	1,
				"omitted":	false,
				"sender":	true
			}
		}, {
			"streams":	[{
					"socket":	6,
					"start":	5.300196,
					"end":	5.400169,
					"seconds":	0.099973000586032867,
					"bytes":	456120,
					"bits_per_second":	36499454.6388537,
					"retransmits":	6,
					"snd_cwnd":	249056,
					"snd_wnd":	623616,
					"rtt":	383821,
					"rttvar":	5222,
					"pmtu":	1500,
					"omitted":	false,
					"sender":	true
				}],
			"sum":	{
				"start":	5.300196,
				"end":	5.400169,
				"seconds":	0.099973000586032867,
				"bytes":	456120,
				"bits_per_second":	36499454.6388537,
				"retransmits":	6,
				"omitted":	false,
				"sender":	true
			}
		}, {
			"streams":	[{
					"socket":	6,
					"start":	5.400169,
					"end":	5.500183,
					"seconds":	0.10001400113105774,
					"bytes":	0,
					"bits_per_second":	0,
					"retransmits":	4,
					"snd_cwnd":	249056,
					"snd_wnd":	642560,
					"rtt":	348927,
					"rttvar":	10427,
					"pmtu":	1500,
					"omitted":	false,
					"sender":	true
				}],
			"sum":	{
				"start":	5.400169,
				"end":	5.500183,
				"seconds":	0.10001400113105774,
				"bytes":	0,
				"bits_per_second":	0,
				"retransmits":	4,
				"omitted":	false,
				"sender":	true
			}
		}, {
			"streams":	[{
					"socket":	6,
					"start":	5.500183,
					"end":	5.60019,
					"seconds":	0.10000699758529663,
					"bytes":	0,
					"bits_per_second":	0,
					"retransmits":	0,
					"snd_cwnd":	237472,
					"snd_wnd":	651776,
					"rtt":	313830,
					"rttvar":	14076,
					"pmtu":	1500,
					"omitted":	false,
					"sender":	true
				}],
			"sum":	{
				"start":	5.500183,
				"end":	5.60019,
				"seconds":	0.10000699758529663,
				"bytes":	0,
				"bits_per_second":	0,
				"retransmits":	0,
				"omitted":	false,
				"sender":	true
			}
		}, {
			"streams":	[{
					"socket":	6,
					"start":	5.60019,
					"end":	5.700352,
					"seconds":	0.10016199946403503,
					"bytes":	0,
					"bits_per_second":	0,
					"retransmits":	5,
					"snd_cwnd":	201272,
					"snd_wnd":	828928,
					"rtt":	303625,
					"rttvar":	4242,
					"pmtu":	1500,
					"omitted":	false,
					"sender":	true
				}],
			"sum":	{
				"start":	5.60019,
				"end":	5.700352,
				"seconds":	0.10016199946403503,
				"bytes":	0,
				"bits_per_second":	0,
				"retransmits":	5,
				"omitted":	false,
				"sender":	true
			}
		}, {
			"streams":	[{
					"socket":	6,
					"start":	5.700352,
					"end":	5.800159,
					"seconds":	0.0998070016503334,
					"bytes":	521280,
					"bits_per_second":	41783040.578757524,
					"retransmits":	2,
					"snd_cwnd":	173760,
					"snd_wnd":	859648,
					"rtt":	294765,
					"rttvar":	2447,
					"pmtu":	1500,
					"omitted":	false,
					"sender":	true
				}],
			"sum":	{
				"start":	5.700352,
				"end":	5.800159,
				"seconds":	0.0998070016503334,
				"bytes":	521280,
				"bits_per_second":	41783040.578757524,
				"retransmits":	2,
				"omitted":	false,
				"sender":	true
			}
		}, {
			"streams":	[{
					"socket":	6,
					"start":	5.800159,
					"end":	5.90021,
					"seconds":	0.10005100071430206,
					"bytes":	0,
					"bits_per_second":	0,
					"retransmits":	0,
					"snd_cwnd":	173760,
					"snd_wnd":	859648,
					"rtt":	285306,
					"rttvar":	3643,
					"pmtu":	1500,
					"omitted":	false,
					"sender":	true
				}],
			"sum":	{
				"start":	5.800159,
				"end":	5.90021,
				"seconds":	0.10005100071430206,
				"bytes":	0,
				"bits_per_second":	0,
				"retransmits":	0,
				"omitted":	false,
				"sender":	true
			}
		}, {
			"streams":	[{
					"socket":	6,
					"start":	5.90021,
					"end":	6.000207,
					"seconds":	0.099996998906135559,
					"bytes":	0,
					"bits_per_second":	0,
					"retransmits":	4,
					"snd_cwnd":	166520,
					"snd_wnd":	896512,
					"rtt":	246617,
					"rttvar":	8543,
					"pmtu":	1500,
					"omitted":	false,
					"sender":	true
				}],
			"sum":	{
				"start":	5.90021,
				"end":	6.000207,
				"seconds":	0.099996998906135559,
				"bytes":	0,
				"bits_per_second":	0,
				"retransmits":	4,
				"omitted":	false,
				"sender":	true
			}
		}, {
			"streams":	[{
					"socket":	6,
					"start":	6.000207,
					"end":	6.100184,
					"seconds":	0.0999770015478134,
					"bytes":	0,
					"bits_per_second":	0,
					"retransmits":	0,
					"snd_cwnd":	144800,
					"snd_wnd":	896512,
					"rtt":	227239,
					"rttvar":	6010,
					"pmtu":	1500,
					"omitted":	false,
					"sender":	true
				}],
			"sum":	{
				"start":	6.000207,
				"end":	6.100184,
				"seconds":	0.0999770015478134,
				"bytes":	0,
				"bits_per_second":	0,
				"retransmits":	0,
				"omitted":	false,
				"sender":	true
			}
		}, {
			"streams":	[{
					"socket":	6,
					"start":	6.100184,
					"end":	6.200144,
					"seconds":	0.099959999322891235,
					"bytes":	390960,
					"bits_per_second":	31289315.938238,
					"retransmits":	0,
					"snd_cwnd":	121632,
					"snd_wnd":	923136,
					"rtt":	222102,
					"rttvar":	1579,
					"pmtu":	1500,
					"omitted":	false,
					"sender":	true
				}],
			"sum":	{
				"start":	6.100184,
				"end":	6.200144,
				"seconds":	0.099959999322891235,
				"bytes":	390960,
				"bits_per_second":	31289315.938238,
				"retransmits":	0,
				"omitted":	false,
				"sender":	true
			}
		}, {
			"streams":	[{
					"socket":	6,
					"start":	6.200144,
					"end":	6.300203,
					"seconds":	0.10005900263786316,
					"bytes":	0,
					"bits_per_second":	0,
					"retransmits":	0,
					"snd_cwnd":	123080,
					"snd_wnd":	920064,
					"rtt":	198013,
					"rttvar":	5315,
					"pmtu":	1500,
					"omitted":	false,
					"sender":	true
				}],
			"sum":	{
				"start":	6.200144,
				"end":	6.300203,
				"seconds":	0.10005900263786316,
				"bytes":	0,
				"bits_per_second":	0,
				"retransmits":	0,
				"omitted":	false,
				"sender":	true
			}
		}, {
			"streams":	[{
					"socket":	6,
					"start":	6.300203,
					"end":	6.400211,
					"seconds":	0.10000800341367722,
					"bytes":	0,
					"bits_per_second":	0,
					"retransmits":	0,
					"snd_cwnd":	124528,
					"snd_wnd":	921600,
					"rtt":	170862,
					"rttvar":	3024,
					"pmtu":	1500,
					"omitted":	false,
					"sender":	true
				}],
			"sum":	{
				"start":	6.300203,
				"end":	6.400211,
				"seconds":	0.10000800341367722,
				"bytes":	0,
				"bits_per_second":	0,
				"retransmits":	0,
				"omitted":	false,
				"sender":	true
			}
		}, {
			"streams":	[{
					"socket":	6,
					"start":	6.400211,
					"end":	6.500208,
					"seconds":	0.099996998906135559,
					"bytes":	0,
					"bits_per_second":	0,
					"retransmits":	0,
					"snd_cwnd":	125976,
					"snd_wnd":	923136,
					"rtt":	167607,
					"rttvar":	802,
					"pmtu":	1500,
					"omitted":	false,
					"sender":	true
				}],
			"sum":	{
				"start":	6.400211,
				"end":	6.500208,
				"seconds":	0.099996998906135559,
				"bytes":	0,
				"bits_per_second":	0,
				"retransmits":	0,
				"omitted":	false,
				"sender":	true
			}
		}, {
			"streams":	[{
					"socket":	6,
					"start":	6.500208,
					"end":	6.600206,
					"seconds":	0.099997997283935547,
					"bytes":	0,
					"bits_per_second":	0,
					"retransmits":	0,
					"snd_cwnd":	127424,
					"snd_wnd":	921088,
					"rtt":	175768,
					"rttvar":	3286,
					"pmtu":	1500,
					"omitted":	false,
					"sender":	true
				}],
			"sum":	{
				"start":	6.500208,
				"end":	6.600206,
				"seconds":	0.099997997283935547,
				"bytes":	0,
				"bits_per_second":	0,
				"retransmits":	0,
				"omitted":	false,
				"sender":	true
			}
		}, {
			"streams":	[{
					"socket":	6,
					"start":	6.600206,
					"end":	6.700193,
					"seconds":	0.0999870002269745,
					"bytes":	0,
					"bits_per_second":	0,
					"retransmits":	0,
					"snd_cwnd":	128872,
					"snd_wnd":	921600,
					"rtt":	182706,
					"rttvar":	1495,
					"pmtu":	1500,
					"omitted":	false,
					"sender":	true
				}],
			"sum":	{
				"start":	6.600206,
				"end":	6.700193,
				"seconds":	0.0999870002269745,
				"bytes":	0,
				"bits_per_second":	0,
				"retransmits":	0,
				"omitted":	false,
				"sender":	true
			}
		}, {
			"streams":	[{
					"socket":	6,
					"start":	6.700193,
					"end":	6.800172,
					"seconds":	0.0999789983034134,
					"bytes":	390960,
					"bits_per_second":	31283370.038457543,
					"retransmits":	0,
					"snd_cwnd":	130320,
					"snd_wnd":	923136,
					"rtt":	185463,
					"rttvar":	1527,
					"pmtu":	1500,
					"omitted":	false,
					"sender":	true
				}],
			"sum":	{
				"start":	6.700193,
				"end":	6.800172,
				"seconds":	0.0999789983034134,
				"bytes":	390960,
				"bits_per_second":	31283370.038457543,
				"retransmits":	0,
				"omitted":	false,
				"sender":	true
			}
		}, {
			"streams":	[{
					"socket":	6,
					"start":	6.800172,
					"end":	6.900185,
					"seconds":	0.10001300275325775,
					"bytes":	0,
					"bits_per_second":	0,
					"retransmits":	0,
					"snd_cwnd":	131768,
					"snd_wnd":	923136,
					"rtt":	188811,
					"rttvar":	1108,
					"pmtu":	1500,
					"omitted":	false,
					"sender":	true
				}],
			"sum":	{
				"start":	6.800172,
				"end":	6.900185,
				"seconds":	0.10001300275325775,
				"bytes":	0,
				"bits_per_second":	0,
				"retransmits":	0,
				"omitted":	false,
				"sender":	true
			}
		}, {
			"streams":	[{
					"socket":	6,
					"start":	6.900185,
					"end":	7.000178,
					"seconds":	0.099992997944355,
					"bytes":	0,
					"bits_per_second":	0,
					"retransmits":	0,
					"snd_cwnd":	133216,
					"snd_wnd":	923136,
					"rtt":	191425,
					"rttvar":	877,
					"pmtu":	1500,
					"omitted":	false,
					"sender":	true
				}],
			"sum":	{
				"start":	6.900185,
				"end":	7.000178,
				"seconds":	0.099992997944355,
				"bytes":	0,
				"bits_per_second":	0,
				"retransmits":	0,
				"omitted":	false,
				"sender":	true
			}
		}, {
			"streams":	[{
					"socket":	6,
					"start":	7.000178,
					"end":	7.100216,
					"seconds":	0.10003799945116043,
					"bytes":	0,
					"bits_per_second":	0,
					"retransmits":	0,
					"snd_cwnd":	136112,
					"snd_wnd":	919552,
					"rtt":	194375,
					"rttvar":	762,
					"pmtu":	1500,
					"omitted":	false,
					"sender":	true
				}],
			"sum":	{
				"start":	7.000178,
				"end":	7.100216,
				"seconds":	0.10003799945116043,
				"bytes":	0,
				"bits_per_second":	0,
				"retransmits":	0,
				"omitted":	false,
				"sender":	true
			}
		}, {
			"streams":	[{
					"socket":	6,
					"start":	7.100216,
					"end":	7.200205,
					"seconds":	0.099988996982574463,
					"bytes":	0,
					"bits_per_second":	0,
					"retransmits":	0,
					"snd_cwnd":	137560,
					"snd_wnd":	916480,
					"rtt":	195458,
					"rttvar":	524,
					"pmtu":	1500,
					"omitted":	false,
					"sender":	true
				}],
			"sum":	{
				"start":	7.100216,
				"end":	7.200205,
				"seconds":	0.099988996982574463,
				"bytes":	0,
				"bits_per_second":	0,
				"retransmits":	0,
				"omitted":	false,
				"sender":	true
			}
		}, {
			"streams":	[{
					"socket":	6,
					"start":	7.200205,
					"end":	7.300207,
					"seconds":	0.10000199824571609,
					"bytes":	0,
					"bits_per_second":	0,
					"retransmits":	0,
					"snd_cwnd":	139008,
					"snd_wnd":	918528,
					"rtt":	196838,
					"rttvar":	675,
					"pmtu":	1500,
					"omitted":	false,
					"sender":	true
				}],
			"sum":	{
				"start":	7.200205,
				"end":	7.300207,
				"seconds":	0.10000199824571609,
				"bytes":	0,
				"bits_per_second":	0,
				"retransmits":	0,
				"omitted":	false,
				"sender":	true
			}
		}, {
			"streams":	[{
					"socket":	6,
					"start":	7.300207,
					"end":	7.400213,
					"seconds":	0.10000599920749664,
					"bytes":	390960,
					"bits_per_second":	31274923.752429675,
					"retransmits":	0,
					"snd_cwnd":	139008,
					"snd_wnd":	915968,
					"rtt":	198070,
					"rttvar":	650,
					"pmtu":	1500,
					"omitted":	false,
					"sender":	true
				}],
			"sum":	{
				"start":	7.300207,
				"end":	7.400213,
				"seconds":	0.10000599920749664,
				"bytes":	390960,
				"bits_per_second":	31274923.752429675,
				"retransmits":	0,
				"omitted":	false,
				"sender":	true
			}
		}, {
			"streams":	[{
					"socket":	6,
					"start":	7.400213,
					"end":	7.500211,
					"seconds":	0.099997997283935547,
					"bytes":	0,
					"bits_per_second":	0,
					"retransmits":	0,
					"snd_cwnd":	140456,
					"snd_wnd":	918016,
					"rtt":	199190,
					"rttvar":	685,
					"pmtu":	1500,
					"omitted":	false,
					"sender":	true
				}],
			"sum":	{
				"start":	7.400213,
				"end":	7.500211,
				"seconds":	0.099997997283935547,
				"bytes":	0,
				"bits_per_second":	0,
				"retransmits":	0,
				"omitted":	false,
				"sender":	true
			}
		}, {
			"streams":	[{
					"socket":	6,
					"start":	7.500211,
					"end":	7.600218,
					"seconds":	0.10000699758529663,
					"bytes":	0,
					"bits_per_second":	0,
					"retransmits":	0,
					"snd_cwnd":	141904,
					"snd_wnd":	915968,
					"rtt":	200554,
					"rttvar":	547,
					"pmtu":	1500,
					"omitted":	false,
					"sender":	true
				}],
			"sum":	{
				"start":	7.500211,
				"end":	7.600218,
				"seconds":	0.10000699758529663,
				"bytes":	0,
				"bits_per_second":	0,
				"retransmits":	0,
				"omitted":	false,
				"sender":	true
			}
		}, {
			"streams":	[{
					"socket":	6,
					"start":	7.600218,
					"end":	7.700217,
					"seconds":	0.099999003112316132,
					"bytes":	0,
					"bits_per_second":	0,
					"retransmits":	0,
					"snd_cwnd":	141904,
					"snd_wnd":	918016,
					"rtt":	201684,
					"rttvar":	696,
					"pmtu":	1500,
					"omitted":	false,
					"sender":	true
				}],
			"sum":	{
				"start":	7.600218,
				"end":	7.700217,
				"seconds":	0.099999003112316132,
				"bytes":	0,
				"bits_per_second":	0,
				"retransmits":	0,
				"omitted":	false,
				"sender":	true
			}
		}, {
			"streams":	[{
					"socket":	6,
					"start":	7.700217,
					"end":	7.800183,
					"seconds":	0.099965997040271759,
					"bytes":	0,
					"bits_per_second":	0,
					"retransmits":	0,
					"snd_cwnd":	143352,
					"snd_wnd":	915968,
					"rtt":	202266,
					"rttvar":	57,
					"pmtu":	1500,
					"omitted":	false,
					"sender":	true
				}],
			"sum":	{
				"start":	7.700217,
				"end":	7.800183,
				"seconds":	0.099965997040271759,
				"bytes":	0,
				"bits_per_second":	0,
				"retransmits":	0,
				"omitted":	false,
				"sender":	true
			}
		}, {
			"streams":	[{
					"socket":	6,
					"start":	7.800183,
					"end":	7.900204,
					"seconds":	0.10002099722623825,
					"bytes":	390960,
					"bits_per_second":	31270234.118196972,
					"retransmits":	0,
					"snd_cwnd":	143352,
					"snd_wnd":	918016,
					"rtt":	202707,
					"rttvar":	632,
					"pmtu":	1500,
					"omitted":	false,
					"sender":	true
				}],
			"sum":	{
				"start":	7.800183,
				"end":	7.900204,
				"seconds":	0.10002099722623825,
				"bytes":	390960,
				"bits_per_second":	31270234.118196972,
				"retransmits":	0,
				"omitted":	false,
				"sender":	true
			}
		}, {
			"streams":	[{
					"socket":	6,
					"start":	7.900204,
					"end":	8.000207,
					"seconds":	0.10000299662351608,
					"bytes":	0,
					"bits_per_second":	0,
					"retransmits":	0,
					"snd_cwnd":	144800,
					"snd_wnd":	921600,
					"rtt":	203813,
					"rttvar":	752,
					"pmtu":	1500,
					"omitted":	false,
					"sender":	true
				}],
			"sum":	{
				"start":	7.900204,
				"end":	8.000207,
				"seconds":	0.10000299662351608,
				"bytes":	0,
				"bits_per_second":	0,
				"retransmits":	0,
				"omitted":	false,
				"sender":	true
			}
		}, {
			"streams":	[{
					"socket":	6,
					"start":	8.000207,
					"end":	8.10019,
					"seconds":	0.099982999265193939,
					"bytes":	0,
					"bits_per_second":	0,
					"retransmits":	0,
					"snd_cwnd":	144800,
					"snd_wnd":	923136,
					"rtt":	204005,
					"rttvar":	334,
					"pmtu":	1500,
					"omitted":	false,
					"sender":	true
				}],
			"sum":	{
				"start":	8.000207,
				"end":	8.10019,
				"seconds":	0.099982999265193939,
				"bytes":	0,
				"bits_per_second":	0,
				"retransmits":	0,
				"omitted":	false,
				"sender":	true
			}
		}, {
			"streams":	[{
					"socket":	6,
					"start":	8.10019,
					"end":	8.200186,
					"seconds":	0.099996000528335571,
					"bytes":	0,
					"bits_per_second":	0,
					"retransmits":	0,
					"snd_cwnd":	146248,
					"snd_wnd":	922112,
					"rtt":	205702,
					"rttvar":	856,
					"pmtu":	1500,
					"omitted":	false,
					"sender":	true
				}],
			"sum":	{
				"start":	8.10019,
				"end":	8.200186,
				"seconds":	0.099996000528335571,
				"bytes":	0,
				"bits_per_second":	0,
				"retransmits":	0,
				"omitted":	false,
				"sender":	true
			}
		}, {
			"streams":	[{
					"socket":	6,
					"start":	8.200186,
					"end":	8.300193,
					"seconds":	0.10000699758529663,
					"bytes":	0,
					"bits_per_second":	0,
					"retransmits":	0,
					"snd_cwnd":	146248,
					"snd_wnd":	921088,
					"rtt":	208628,
					"rttvar":	832,
					"pmtu":	1500,
					"omitted":	false,
					"sender":	true
				}],
			"sum":	{
				"start":	8.200186,
				"end":	8.300193,
				"seconds":	0.10000699758529663,
				"bytes":	0,
				"bits_per_second":	0,
				"retransmits":	0,
				"omitted":	false,
				"sender":	true
			}
		}, {
			"streams":	[{
					"socket":	6,
					"start":	8.300193,
					"end":	8.400202,
					"seconds":	0.1000090017914772,
					"bytes":	0,
					"bits_per_second":	0,
					"retransmits":	0,
					"snd_cwnd":	147696,
					"snd_wnd":	921088,
					"rtt":	209445,
					"rttvar":	130,
					"pmtu":	1500,
					"omitted":	false,
					"sender":	true
				}],
			"sum":	{
				"start":	8.300193,
				"end":	8.400202,
				"seconds":	0.1000090017914772,
				"bytes":	0,
				"bits_per_second":	0,
				"retransmits":	0,
				"omitted":	false,
				"sender":	true
			}
		}, {
			"streams":	[{
					"socket":	6,
					"start":	8.400202,
					"end":	8.500143,
					"seconds":	0.0999410003423691,
					"bytes":	390960,
					"bits_per_second":	31295264.098672908,
					"retransmits":	0,
					"snd_cwnd":	147696,
					"snd_wnd":	923136,
					"rtt":	210554,
					"rttvar":	342,
					"pmtu":	1500,
					"omitted":	false,
					"sender":	true
				}],
			"sum":	{
				"start":	8.400202,
				"end":	8.500143,
				"seconds":	0.0999410003423691,
				"bytes":	390960,
				"bits_per_second":	31295264.098672908,
				"retransmits":	0,
				"omitted":	false,
				"sender":	true
			}
		}, {
			"streams":	[{
					"socket":	6,
					"start":	8.500143,
					"end":	8.600174,
					"seconds":	0.10003100335597992,
					"bytes":	0,
					"bits_per_second":	0,
					"retransmits":	0,
					"snd_cwnd":	147696,
					"snd_wnd":	923136,
					"rtt":	211558,
					"rttvar":	582,
					"pmtu":	1500,
					"omitted":	false,
					"sender":	true
				}],
			"sum":	{
				"start":	8.500143,
				"end":	8.600174,
				"seconds":	0.10003100335597992,
				"bytes":	0,
				"bits_per_second":	0,
				"retransmits":	0,
				"omitted":	false,
				"sender":	true
			}
		}, {
			"streams":	[{
					"socket":	6,
					"start":	8.600174,
					"end":	8.700212,
					"seconds":	0.10003799945116043,
					"bytes":	0,
					"bits_per_second":	0,
					"retransmits":	1,
					"snd_cwnd":	144800,
					"snd_wnd":	923136,
					"rtt":	214353,
					"rttvar":	1009,
					"pmtu":	1500,
					"omitted":	false,
					"sender":	true
				}],
			"sum":	{
				"start":	8.600174,
				"end":	8.700212,
				"seconds":	0.10003799945116043,
				"bytes":	0,
				"bits_per_second":	0,
				"retransmits":	1,
				"omitted":	false,
				"sender":	true
			}
		}, {
			"streams":	[{
					"socket":	6,
					"start":	8.700212,
					"end":	8.800179,
					"seconds":	0.099967002868652344,
					"bytes":	0,
					"bits_per_second":	0,
					"retransmits":	1,
					"snd_cwnd":	123080,
					"snd_wnd":	923136,
					"rtt":	213163,
					"rttvar":	43,
					"pmtu":	1500,
					"omitted":	false,
					"sender":	true
				}],
			"sum":	{
				"start":	8.700212,
				"end":	8.800179,
				"seconds":	0.099967002868652344,
				"bytes":	0,
				"bits_per_second":	0,
				"retransmits":	1,
				"omitted":	false,
				"sender":	true
			}
		}, {
			"streams":	[{
					"socket":	6,
					"start":	8.800179,
					"end":	8.900236,
					"seconds":	0.10005699843168259,
					"bytes":	0,
					"bits_per_second":	0,
					"retransmits":	0,
					"snd_cwnd":	102808,
					"snd_wnd":	923136,
					"rtt":	213106,
					"rttvar":	68,
					"pmtu":	1500,
					"omitted":	false,
					"sender":	true
				}],
			"sum":	{
				"start":	8.800179,
				"end":	8.900236,
				"seconds":	0.10005699843168259,
				"bytes":	0,
				"bits_per_second":	0,
				"retransmits":	0,
				"omitted":	false,
				"sender":	true
			}
		}, {
			"streams":	[{
					"socket":	6,
					"start":	8.900236,
					"end":	9.000177,
					"seconds":	0.0999410003423691,
					"bytes":	0,
					"bits_per_second":	0,
					"retransmits":	1,
					"snd_cwnd":	89776,
					"snd_wnd":	917504,
					"rtt":	199851,
					"rttvar":	2626,
					"pmtu":	1500,
					"omitted":	false,
					"sender":	true
				}],
			"sum":	{
				"start":	8.900236,
				"end":	9.000177,
				"seconds":	0.0999410003423691,
				"bytes":	0,
				"bits_per_second":	0,
				"retransmits":	1,
				"omitted":	false,
				"sender":	true
			}
		}, {
			"streams":	[{
					"socket":	6,
					"start":	9.000177,
					"end":	9.100123,
					"seconds":	0.0999459996819496,
					"bytes":	456120,
					"bits_per_second":	36509315.146297015,
					"retransmits":	0,
					"snd_cwnd":	70952,
					"snd_wnd":	923136,
					"rtt":	183350,
					"rttvar":	3719,
					"pmtu":	1500,
					"omitted":	false,
					"sender":	true
				}],
			"sum":	{
				"start":	9.000177,
				"end":	9.100123,
				"seconds":	0.0999459996819496,
				"bytes":	456120,
				"bits_per_second":	36509315.146297015,
				"retransmits":	0,
				"omitted":	false,
				"sender":	true
			}
		}, {
			"streams":	[{
					"socket":	6,
					"start":	9.100123,
					"end":	9.200206,
					"seconds":	0.10008300095796585,
					"bytes":	0,
					"bits_per_second":	0,
					"retransmits":	0,
					"snd_cwnd":	70952,
					"snd_wnd":	923136,
					"rtt":	169333,
					"rttvar":	3955,
					"pmtu":	1500,
					"omitted":	false,
					"sender":	true
				}],
			"sum":	{
				"start":	9.100123,
				"end":	9.200206,
				"seconds":	0.10008300095796585,
				"bytes":	0,
				"bits_per_second":	0,
				"retransmits":	0,
				"omitted":	false,
				"sender":	true
			}
		}, {
			"streams":	[{
					"socket":	6,
					"start":	9.200206,
					"end":	9.300312,
					"seconds":	0.10010600090026855,
					"bytes":	0,
					"bits_per_second":	0,
					"retransmits":	0,
					"snd_cwnd":	72400,
					"snd_wnd":	922112,
					"rtt":	156395,
					"rttvar":	3587,
					"pmtu":	1500,
					"omitted":	false,
					"sender":	true
				}],
			"sum":	{
				"start":	9.200206,
				"end":	9.300312,
				"seconds":	0.10010600090026855,
				"bytes":	0,
				"bits_per_second":	0,
				"retransmits":	0,
				"omitted":	false,
				"sender":	true
			}
		}, {
			"streams":	[{
					"socket":	6,
					"start":	9.300312,
					"end":	9.400221,
					"seconds":	0.0999090000987053,
					"bytes":	0,
					"bits_per_second":	0,
					"retransmits":	0,
					"snd_cwnd":	73848,
					"snd_wnd":	923136,
					"rtt":	156536,
					"rttvar":	968,
					"pmtu":	1500,
					"omitted":	false,
					"sender":	true
				}],
			"sum":	{
				"start":	9.300312,
				"end":	9.400221,
				"seconds":	0.0999090000987053,
				"bytes":	0,
				"bits_per_second":	0,
				"retransmits":	0,
				"omitted":	false,
				"sender":	true
			}
		}, {
			"streams":	[{
					"socket":	6,
					"start":	9.400221,
					"end":	9.500185,
					"seconds":	0.0999640002846718,
					"bytes":	0,
					"bits_per_second":	0,
					"retransmits":	0,
					"snd_cwnd":	75296,
					"snd_wnd":	922112,
					"rtt":	159789,
					"rttvar":	1078,
					"pmtu":	1500,
					"omitted":	false,
					"sender":	true
				}],
			"sum":	{
				"start":	9.400221,
				"end":	9.500185,
				"seconds":	0.0999640002846718,
				"bytes":	0,
				"bits_per_second":	0,
				"retransmits":	0,
				"omitted":	false,
				"sender":	true
			}
		}, {
			"streams":	[{
					"socket":	6,
					"start":	9.500185,
					"end":	9.600174,
					"seconds":	0.099988996982574463,
					"bytes":	0,
					"bits_per_second":	0,
					"retransmits":	0,
					"snd_cwnd":	76744,
					"snd_wnd":	922112,
					"rtt":	161749,
					"rttvar":	682,
					"pmtu":	1500,
					"omitted":	false,
					"sender":	true
				}],
			"sum":	{
				"start":	9.500185,
				"end":	9.600174,
				"seconds":	0.099988996982574463,
				"bytes":	0,
				"bits_per_second":	0,
				"retransmits":	0,
				"omitted":	false,
				"sender":	true
			}
		}, {
			"streams":	[{
					"socket":	6,
					"start":	9.600174,
					"end":	9.700184,
					"seconds":	0.10001000016927719,
					"bytes":	0,
					"bits_per_second":	0,
					"retransmits":	0,
					"snd_cwnd":	78192,
					"snd_wnd":	921600,
					"rtt":	165037,
					"rttvar":	1419,
					"pmtu":	1500,
					"omitted":	false,
					"sender":	true
				}],
			"sum":	{
				"start":	9.600174,
				"end":	9.700184,
				"seconds":	0.10001000016927719,
				"bytes":	0,
				"bits_per_second":	0,
				"retransmits":	0,
				"omitted":	false,
				"sender":	true
			}
		}, {
			"streams":	[{
					"socket":	6,
					"start":	9.700184,
					"end":	9.800364,
					"seconds":	0.1001800000667572,
					"bytes":	0,
					"bits_per_second":	0,
					"retransmits":	0,
					"snd_cwnd":	78192,
					"snd_wnd":	922112,
					"rtt":	166936,
					"rttvar":	358,
					"pmtu":	1500,
					"omitted":	false,
					"sender":	true
				}],
			"sum":	{
				"start":	9.700184,
				"end":	9.800364,
				"seconds":	0.1001800000667572,
				"bytes":	0,
				"bits_per_second":	0,
				"retransmits":	0,
				"omitted":	false,
				"sender":	true
			}
		}, {
			"streams":	[{
					"socket":	6,
					"start":	9.800364,
					"end":	9.900192,
					"seconds":	0.099827997386455536,
					"bytes":	0,
					"bits_per_second":	0,
					"retransmits":	0,
					"snd_cwnd":	79640,
					"snd_wnd":	923136,
					"rtt":	168229,
					"rttvar":	1309,
					"pmtu":	1500,
					"omitted":	false,
					"sender":	true
				}],
			"sum":	{
				"start":	9.800364,
				"end":	9.900192,
				"seconds":	0.099827997386455536,
				"bytes":	0,
				"bits_per_second":	0,
				"retransmits":	0,
				"omitted":	false,
				"sender":	true
			}
		}, {
			"streams":	[{
					"socket":	6,
					"start":	9.900192,
					"end":	10.000127,
					"seconds":	0.099935002624988556,
					"bytes":	390960,
					"bits_per_second":	31297142.32096222,
					"retransmits":	0,
					"snd_cwnd":	81088,
					"snd_wnd":	922112,
					"rtt":	171096,
					"rttvar":	1542,
					"pmtu":	1500,
					"omitted":	false,
					"sender":	true
				}],
			"sum":	{
				"start":	9.900192,
				"end":	10.000127,
				"seconds":	0.099935002624988556,
				"bytes":	390960,
				"bits_per_second":	31297142.32096222,
				"retransmits":	0,
				"omitted":	false,
				"sender":	true
			}
		}, {
			"streams":	[{
					"socket":	6,
					"start":	10.000127,
					"end":	10.100186,
					"seconds":	0.10005900263786316,
					"bytes":	0,
					"bits_per_second":	0,
					"retransmits":	0,
					"snd_cwnd":	81088,
					"snd_wnd":	922112,
					"rtt":	172810,
					"rttvar":	418,
					"pmtu":	1500,
					"omitted":	false,
					"sender":	true
				}],
			"sum":	{
				"start":	10.000127,
				"end":	10.100186,
				"seconds":	0.10005900263786316,
				"bytes":	0,
				"bits_per_second":	0,
				"retransmits":	0,
				"omitted":	false,
				"sender":	true
			}
		}, {
			"streams":	[{
					"socket":	6,
					"start":	10.100186,
					"end":	10.200218,
					"seconds":	0.10003200173377991,
					"bytes":	0,
					"bits_per_second":	0,
					"retransmits":	0,
					"snd_cwnd":	82536,
					"snd_wnd":	923136,
					"rtt":	173782,
					"rttvar":	890,
					"pmtu":	1500,
					"omitted":	false,
					"sender":	true
				}],
			"sum":	{
				"start":	10.100186,
				"end":	10.200218,
				"seconds":	0.10003200173377991,
				"bytes":	0,
				"bits_per_second":	0,
				"retransmits":	0,
				"omitted":	false,
				"sender":	true
			}
		}, {
			"streams":	[{
					"socket":	6,
					"start":	10.200218,
					"end":	10.300177,
					"seconds":	0.099959000945091248,
					"bytes":	0,
					"bits_per_second":	0,
					"retransmits":	0,
					"snd_cwnd":	82536,
					"snd_wnd":	921600,
					"rtt":	175753,
					"rttvar":	938,
					"pmtu":	1500,
					"omitted":	false,
					"sender":	true
				}],
			"sum":	{
				"start":	10.200218,
				"end":	10.300177,
				"seconds":	0.099959000945091248,
				"bytes":	0,
				"bits_per_second":	0,
				"retransmits":	0,
				"omitted":	false,
				"sender":	true
			}
		}, {
			"streams":	[{
					"socket":	6,
					"start":	10.300177,
					"end":	10.400185,
					"seconds":	0.10000800341367722,
					"bytes":	0,
					"bits_per_second":	0,
					"retransmits":	0,
					"snd_cwnd":	83984,
					"snd_wnd":	921600,
					"rtt":	178352,
					"rttvar":	1142,
					"pmtu":	1500,
					"omitted":	false,
					"sender":	true
				}],
			"sum":	{
				"start":	10.300177,
				"end":	10.400185,
				"seconds":	0.10000800341367722,
				"bytes":	0,
				"bits_per_second":	0,
				"retransmits":	0,
				"omitted":	false,
				"sender":	true
			}
		}, {
			"streams":	[{
					"socket":	6,
					"start":	10.400185,
					"end":	10.500189,
					"seconds":	0.10000400245189667,
					"bytes":	0,
					"bits_per_second":	0,
					"retransmits":	0,
					"snd_cwnd":	83984,
					"snd_wnd":	923136,
					"rtt":	179069,
					"rttvar":	268,
					"pmtu":	1500,
					"omitted":	false,
					"sender":	true
				}],
			"sum":	{
				"start":	10.400185,
				"end":	10.500189,
				"seconds":	0.10000400245189667,
				"bytes":	0,
				"bits_per_second":	0,
				"retransmits":	0,
				"omitted":	false,
				"sender":	true
			}
		}, {
			"streams":	[{
					"socket":	6,
					"start":	10.500189,
					"end":	10.600178,
					"seconds":	0.099988996982574463,
					"bytes":	0,
					"bits_per_second":	0,
					"retransmits":	2,
					"snd_cwnd":	73848,
					"snd_wnd":	923136,
					"rtt":	179124,
					"rttvar":	210,
					"pmtu":	1500,
					"omitted":	false,
					"sender":	true
				}],
			"sum":	{
				"start":	10.500189,
				"end":	10.600178,
				"seconds":	0.099988996982574463,
				"bytes":	0,
				"bits_per_second":	0,
				"retransmits":	2,
				"omitted":	false,
				"sender":	true
			}
		}, {
			"streams":	[{
					"socket":	6,
					"start":	10.600178,
					"end":	10.700257,
					"seconds":	0.1000789999961853,
					"bytes":	0,
					"bits_per_second":	0,
					"retransmits":	1,
					"snd_cwnd":	59368,
					"snd_wnd":	923136,
					"rtt":	180688,
					"rttvar":	543,
					"pmtu":	1500,
					"omitted":	false,
					"sender":	true
				}],
			"sum":	{
				"start":	10.600178,
				"end":	10.700257,
				"seconds":	0.1000789999961853,
				"bytes":	0,
				"bits_per_second":	0,
				"retransmits":	1,
				"omitted":	false,
				"sender":	true
			}
		}, {
			"streams":	[{
					"socket":	6,
					"start":	10.700257,
					"end":	10.800196,
					"seconds":	0.0999390035867691,
					"bytes":	0,
					"bits_per_second":	0,
					"retransmits":	0,
					"snd_cwnd":	59368,
					"snd_wnd":	912384,
					"rtt":	176310,
					"rttvar":	1430,
					"pmtu":	1500,
					"omitted":	false,
					"sender":	true
				}],
			"sum":	{
				"start":	10.700257,
				"end":	10.800196,
				"seconds":	0.0999390035867691,
				"bytes":	0,
				"bits_per_second":	0,
				"retransmits":	0,
				"omitted":	false,
				"sender":	true
			}
		}, {
			"streams":	[{
					"socket":	6,
					"start":	10.800196,
					"end":	10.900125,
					"seconds":	0.099928997457027435,
					"bytes":	390960,
					"bits_per_second":	31299023.102328222,
					"retransmits":	0,
					"snd_cwnd":	59368,
					"snd_wnd":	923136,
					"rtt":	166597,
					"rttvar":	2546,
					"pmtu":	1500,
					"omitted":	false,
					"sender":	true
				}],
			"sum":	{
				"start":	10.800196,
				"end":	10.900125,
				"seconds":	0.099928997457027435,
				"bytes":	390960,
				"bits_per_second":	31299023.102328222,
				"retransmits":	0,
				"omitted":	false,
				"sender":	true
			}
		}, {
			"streams":	[{
					"socket":	6,
					"start":	10.900125,
					"end":	11.000196,
					"seconds":	0.10007099807262421,
					"bytes":	0,
					"bits_per_second":	0,
					"retransmits":	0,
					"snd_cwnd":	60816,
					"snd_wnd":	922112,
					"rtt":	166594,
					"rttvar":	879,
					"pmtu":	1500,
					"omitted":	false,
					"sender":	true
				}],
			"sum":	{
				"start":	10.900125,
				"end":	11.000196,
				"seconds":	0.10007099807262421,
				"bytes":	0,
				"bits_per_second":	0,
				"retransmits":	0,
				"omitted":	false,
				"sender":	true
			}
		}, {
			"streams":	[{
					"socket":	6,
					"start":	11.000196,
					"end":	11.10018,
					"seconds":	0.099983997642993927,
					"bytes":	0,
					"bits_per_second":	0,
					"retransmits":	0,
					"snd_cwnd":	62264,
					"snd_wnd":	921600,
					"rtt":	165651,
					"rttvar":	948,
					"pmtu":	1500,
					"omitted":	false,
					"sender":	true
				}],
			"sum":	{
				"start":	11.000196,
				"end":	11.10018,
				"seconds":	0.099983997642993927,
				"bytes":	0,
				"bits_per_second":	0,
				"retransmits":	0,
				"omitted":	false,
				"sender":	true
			}
		}, {
			"streams":	[{
					"socket":	6,
					"start":	11.10018,
					"end":	11.200199,
					"seconds":	0.10001900047063828,
					"bytes":	0,
					"bits_per_second":	0,
					"retransmits":	0,
					"snd_cwnd":	62264,
					"snd_wnd":	921088,
					"rtt":	168139,
					"rttvar":	1469,
					"pmtu":	1500,
					"omitted":	false,
					"sender":	true
				}],
			"sum":	{
				"start":	11.10018,
				"end":	11.200199,
				"seconds":	0.10001900047063828,
				"bytes":	0,
				"bits_per_second":	0,
				"retransmits":	0,
				"omitted":	false,
				"sender":	true
			}
		}, {
			"streams":	[{
					"socket":	6,
					"start":	11.200199,
					"end":	11.300194,
					"seconds":	0.0999950021505356,
					"bytes":	0,
					"bits_per_second":	0,
					"retransmits":	0,
					"snd_cwnd":	63712,
					"snd_wnd":	923136,
					"rtt":	170552,
					"rttvar":	1611,
					"pmtu":	1500,
					"omitted":	false,
					"sender":	true
				}],
			"sum":	{
				"start":	11.200199,
				"end":	11.300194,
				"seconds":	0.0999950021505356,
				"bytes":	0,
				"bits_per_second":	0,
				"retransmits":	0,
				"omitted":	false,
				"sender":	true
			}
		}, {
			"streams":	[{
					"socket":	6,
					"start":	11.300194,
					"end":	11.400184,
					"seconds":	0.099990002810955048,
					"bytes":	0,
					"bits_per_second":	0,
					"retransmits":	0,
					"snd_cwnd":	65160,
					"snd_wnd":	922112,
					"rtt":	170738,
					"rttvar":	225,
					"pmtu":	1500,
					"omitted":	false,
					"sender":	true
				}],
			"sum":	{
				"start":	11.300194,
				"end":	11.400184,
				"seconds":	0.099990002810955048,
				"bytes":	0,
				"bits_per_second":	0,
				"retransmits":	0,
				"omitted":	false,
				"sender":	true
			}
		}, {
			"streams":	[{
					"socket":	6,
					"start":	11.400184,
					"end":	11.500232,
					"seconds":	0.1000479981303215,
					"bytes":	0,
					"bits_per_second":	0,
					"retransmits":	0,
					"snd_cwnd":	65160,
					"snd_wnd":	921600,
					"rtt":	168388,
					"rttvar":	1012,
					"pmtu":	1500,
					"omitted":	false,
					"sender":	true
				}],
			"sum":	{
				"start":	11.400184,
				"end":	11.500232,
				"seconds":	0.1000479981303215,
				"bytes":	0,
				"bits_per_second":	0,
				"retransmits":	0,
				"omitted":	false,
				"sender":	true
			}
		}, {
			"streams":	[{
					"socket":	6,
					"start":	11.500232,
					"end":	11.60023,
					"seconds":	0.099997997283935547,
					"bytes":	0,
					"bits_per_second":	0,
					"retransmits":	0,
					"snd_cwnd":	66608,
					"snd_wnd":	921600,
					"rtt":	158484,
					"rttvar":	2549,
					"pmtu":	1500,
					"omitted":	false,
					"sender":	true
				}],
			"sum":	{
				"start":	11.500232,
				"end":	11.60023,
				"seconds":	0.099997997283935547,
				"bytes":	0,
				"bits_per_second":	0,
				"retransmits":	0,
				"omitted":	false,
				"sender":	true
			}
		}, {
			"streams":	[{
					"socket":	6,
					"start":	11.60023,
					"end":	11.700175,
					"seconds":	0.099945001304149628,
					"bytes":	0,
					"bits_per_second":	0,
					"retransmits":	0,
					"snd_cwnd":	68056,
					"snd_wnd":	923136,
					"rtt":	146998,
					"rttvar":	3581,
					"pmtu":	1500,
					"omitted":	false,
					"sender":	true
				}],
			"sum":	{
				"start":	11.60023,
				"end":	11.700175,
				"seconds":	0.099945001304149628,
				"bytes":	0,
				"bits_per_second":	0,
				"retransmits":	0,
				"omitted":	false,
				"sender":	true
			}
		}, {
			"streams":	[{
					"socket":	6,
					"start":	11.700175,
					"end":	11.800186,
					"seconds":	0.10001099854707718,
					"bytes":	0,
					"bits_per_second":	0,
					"retransmits":	0,
					"snd_cwnd":	68056,
					"snd_wnd":	922112,
					"rtt":	141905,
					"rttvar":	1141,
					"pmtu":	1500,
					"omitted":	false,
					"sender":	true
				}],
			"sum":	{
				"start":	11.700175,
				"end":	11.800186,
				"seconds":	0.10001099854707718,
				"bytes":	0,
				"bits_per_second":	0,
				"retransmits":	0,
				"omitted":	false,
				"sender":	true
			}
		}, {
			"streams":	[{
					"socket":	6,
					"start":	11.800186,
					"end":	11.900122,
					"seconds":	0.099936001002788544,
					"bytes":	390960,
					"bits_per_second":	31296829.657139547,
					"retransmits":	0,
					"snd_cwnd":	69504,
					"snd_wnd":	923136,
					"rtt":	147415,
					"rttvar":	3746,
					"pmtu":	1500,
					"omitted":	false,
					"sender":	true
				}],
			"sum":	{
				"start":	11.800186,
				"end":	11.900122,
				"seconds":	0.099936001002788544,
				"bytes":	390960,
				"bits_per_second":	31296829.657139547,
				"retransmits":	0,
				"omitted":	false,
				"sender":	true
			}
		}, {
			"streams":	[{
					"socket":	6,
					"start":	11.900122,
					"end":	12.000193,
					"seconds":	0.10007099807262421,
					"bytes":	0,
					"bits_per_second":	0,
					"retransmits":	0,
					"snd_cwnd":	70952,
					"snd_wnd":	922112,
					"rtt":	153242,
					"rttvar":	2164,
					"pmtu":	1500,
					"omitted":	false,
					"sender":	true
				}],
			"sum":	{
				"start":	11.900122,
				"end":	12.000193,
				"seconds":	0.10007099807262421,
				"bytes":	0,
				"bits_per_second":	0,
				"retransmits":	0,
				"omitted":	false,
				"sender":	true
			}
		}, {
			"streams":	[{
					"socket":	6,
					"start":	12.000193,
					"end":	12.100191,
					"seconds":	0.099997997283935547,
					"bytes":	0,
					"bits_per_second":	0,
					"retransmits":	0,
					"snd_cwnd":	70952,
					"snd_wnd":	921600,
					"rtt":	158840,
					"rttvar":	1707,
					"pmtu":	1500,
					"omitted":	false,
					"sender":	true
				}],
			"sum":	{
				"start":	12.000193,
				"end":	12.100191,
				"seconds":	0.099997997283935547,
				"bytes":	0,
				"bits_per_second":	0,
				"retransmits":	0,
				"omitted":	false,
				"sender":	true
			}
		}, {
			"streams":	[{
					"socket":	6,
					"start":	12.100191,
					"end":	12.20018,
					"seconds":	0.099988996982574463,
					"bytes":	0,
					"bits_per_second":	0,
					"retransmits":	0,
					"snd_cwnd":	70952,
					"snd_wnd":	921088,
					"rtt":	161750,
					"rttvar":	2226,
					"pmtu":	1500,
					"omitted":	false,
					"sender":	true
				}],
			"sum":	{
				"start":	12.100191,
				"end":	12.20018,
				"seconds":	0.099988996982574463,
				"bytes":	0,
				"bits_per_second":	0,
				"retransmits":	0,
				"omitted":	false,
				"sender":	true
			}
		}, {
			"streams":	[{
					"socket":	6,
					"start":	12.20018,
					"end":	12.300176,
					"seconds":	0.099996000528335571,
					"bytes":	0,
					"bits_per_second":	0,
					"retransmits":	0,
					"snd_cwnd":	70952,
					"snd_wnd":	921088,
					"rtt":	164429,
					"rttvar":	514,
					"pmtu":	1500,
					"omitted":	false,
					"sender":	true
				}],
			"sum":	{
				"start":	12.20018,
				"end":	12.300176,
				"seconds":	0.099996000528335571,
				"bytes":	0,
				"bits_per_second":	0,
				"retransmits":	0,
				"omitted":	false,
				"sender":	true
			}
		}, {
			"streams":	[{
					"socket":	6,
					"start":	12.300176,
					"end":	12.400166,
					"seconds":	0.099990002810955048,
					"bytes":	0,
					"bits_per_second":	0,
					"retransmits":	0,
					"snd_cwnd":	72400,
					"snd_wnd":	923136,
					"rtt":	167646,
					"rttvar":	1212,
					"pmtu":	1500,
					"omitted":	false,
					"sender":	true
				}],
			"sum":	{
				"start":	12.300176,
				"end":	12.400166,
				"seconds":	0.099990002810955048,
				"bytes":	0,
				"bits_per_second":	0,
				"retransmits":	0,
				"omitted":	false,
				"sender":	true
			}
		}, {
			"streams":	[{
					"socket":	6,
					"start":	12.400166,
					"end":	12.500202,
					"seconds":	0.10003600269556046,
					"bytes":	0,
					"bits_per_second":	0,
					"retransmits":	0,
					"snd_cwnd":	72400,
					"snd_wnd":	921600,
					"rtt":	168926,
					"rttvar":	1257,
					"pmtu":	1500,
					"omitted":	false,
					"sender":	true
				}],
			"sum":	{
				"start":	12.400166,
				"end":	12.500202,
				"seconds":	0.10003600269556046,
				"bytes":	0,
				"bits_per_second":	0,
				"retransmits":	0,
				"omitted":	false,
				"sender":	true
			}
		}, {
			"streams":	[{
					"socket":	6,
					"start":	12.500202,
					"end":	12.600273,
					"seconds":	0.10007099807262421,
					"bytes":	0,
					"bits_per_second":	0,
					"retransmits":	0,
					"snd_cwnd":	72400,
					"snd_wnd":	923136,
					"rtt":	172821,
					"rttvar":	663,
					"pmtu":	1500,
					"omitted":	false,
					"sender":	true
				}],
			"sum":	{
				"start":	12.500202,
				"end":	12.600273,
				"seconds":	0.10007099807262421,
				"bytes":	0,
				"bits_per_second":	0,
				"retransmits":	0,
				"omitted":	false,
				"sender":	true
			}
		}, {
			"streams":	[{
					"socket":	6,
					"start":	12.600273,
					"end":	12.700172,
					"seconds":	0.0998990014195442,
					"bytes":	0,
					"bits_per_second":	0,
					"retransmits":	0,
					"snd_cwnd":	72400,
					"snd_wnd":	923136,
					"rtt":	172742,
					"rttvar":	423,
					"pmtu":	1500,
					"omitted":	false,
					"sender":	true
				}],
			"sum":	{
				"start":	12.600273,
				"end":	12.700172,
				"seconds":	0.0998990014195442,
				"bytes":	0,
				"bits_per_second":	0,
				"retransmits":	0,
				"omitted":	false,
				"sender":	true
			}
		}, {
			"streams":	[{
					"socket":	6,
					"start":	12.700172,
					"end":	12.800131,
					"seconds":	0.099959000945091248,
					"bytes":	390960,
					"bits_per_second":	31289628.45194976,
					"retransmits":	0,
					"snd_cwnd":	72400,
					"snd_wnd":	923136,
					"rtt":	173015,
					"rttvar":	243,
					"pmtu":	1500,
					"omitted":	false,
					"sender":	true
				}],
			"sum":	{
				"start":	12.700172,
				"end":	12.800131,
				"seconds":	0.099959000945091248,
				"bytes":	390960,
				"bits_per_second":	31289628.45194976,
				"retransmits":	0,
				"omitted":	false,
				"sender":	true
			}
		}, {
			"streams":	[{
					"socket":	6,
					"start":	12.800131,
					"end":	12.900177,
					"seconds":	0.10004600137472153,
					"bytes":	0,
					"bits_per_second":	0,
					"retransmits":	0,
					"snd_cwnd":	72400,
					"snd_wnd":	921600,
					"rtt":	170129,
					"rttvar":	800,
					"pmtu":	1500,
					"omitted":	false,
					"sender":	true
				}],
			"sum":	{
				"start":	12.800131,
				"end":	12.900177,
				"seconds":	0.10004600137472153,
				"bytes":	0,
				"bits_per_second":	0,
				"retransmits":	0,
				"omitted":	false,
				"sender":	true
			}
		}, {
			"streams":	[{
					"socket":	6,
					"start":	12.900177,
					"end":	13.000175,
					"seconds":	0.099997997283935547,
					"bytes":	0,
					"bits_per_second":	0,
					"retransmits":	0,
					"snd_cwnd":	72400,
					"snd_wnd":	922112,
					"rtt":	147762,
					"rttvar":	4577,
					"pmtu":	1500,
					"omitted":	false,
					"sender":	true
				}],
			"sum":	{
				"start":	12.900177,
				"end":	13.000175,
				"seconds":	0.099997997283935547,
				"bytes":	0,
				"bits_per_second":	0,
				"retransmits":	0,
				"omitted":	false,
				"sender":	true
			}
		}, {
			"streams":	[{
					"socket":	6,
					"start":	13.000175,
					"end":	13.100188,
					"seconds":	0.10001300275325775,
					"bytes":	0,
					"bits_per_second":	0,
					"retransmits":	0,
					"snd_cwnd":	72400,
					"snd_wnd":	921088,
					"rtt":	136847,
					"rttvar":	2104,
					"pmtu":	1500,
					"omitted":	false,
					"sender":	true
				}],
			"sum":	{
				"start":	13.000175,
				"end":	13.100188,
				"seconds":	0.10001300275325775,
				"bytes":	0,
				"bits_per_second":	0,
				"retransmits":	0,
				"omitted":	false,
				"sender":	true
			}
		}, {
			"streams":	[{
					"socket":	6,
					"start":	13.100188,
					"end":	13.20018,
					"seconds":	0.099991999566555023,
					"bytes":	0,
					"bits_per_second":	0,
					"retransmits":	0,
					"snd_cwnd":	72400,
					"snd_wnd":	922112,
					"rtt":	135682,
					"rttvar":	456,
					"pmtu":	1500,
					"omitted":	false,
					"sender":	true
				}],
			"sum":	{
				"start":	13.100188,
				"end":	13.20018,
				"seconds":	0.099991999566555023,
				"bytes":	0,
				"bits_per_second":	0,
				"retransmits":	0,
				"omitted":	false,
				"sender":	true
			}
		}, {
			"streams":	[{
					"socket":	6,
					"start":	13.20018,
					"end":	13.300171,
					"seconds":	0.099991001188755035,
					"bytes":	0,
					"bits_per_second":	0,
					"retransmits":	0,
					"snd_cwnd":	72400,
					"snd_wnd":	921088,
					"rtt":	138233,
					"rttvar":	1058,
					"pmtu":	1500,
					"omitted":	false,
					"sender":	true
				}],
			"sum":	{
				"start":	13.20018,
				"end":	13.300171,
				"seconds":	0.099991001188755035,
				"bytes":	0,
				"bits_per_second":	0,
				"retransmits":	0,
				"omitted":	false,
				"sender":	true
			}
		}, {
			"streams":	[{
					"socket":	6,
					"start":	13.300171,
					"end":	13.400175,
					"seconds":	0.10000400245189667,
					"bytes":	0,
					"bits_per_second":	0,
					"retransmits":	0,
					"snd_cwnd":	72400,
					"snd_wnd":	923136,
					"rtt":	141065,
					"rttvar":	1003,
					"pmtu":	1500,
					"omitted":	false,
					"sender":	true
				}],
			"sum":	{
				"start":	13.300171,
				"end":	13.400175,
				"seconds":	0.10000400245189667,
				"bytes":	0,
				"bits_per_second":	0,
				"retransmits":	0,
				"omitted":	false,
				"sender":	true
			}
		}, {
			"streams":	[{
					"socket":	6,
					"start":	13.400175,
					"end":	13.500169,
					"seconds":	0.099993996322155,
					"bytes":	0,
					"bits_per_second":	0,
					"retransmits":	0,
					"snd_cwnd":	72400,
					"snd_wnd":	922112,
					"rtt":	142796,
					"rttvar":	755,
					"pmtu":	1500,
					"omitted":	false,
					"sender":	true
				}],
			"sum":	{
				"start":	13.400175,
				"end":	13.500169,
				"seconds":	0.099993996322155,
				"bytes":	0,
				"bits_per_second":	0,
				"retransmits":	0,
				"omitted":	false,
				"sender":	true
			}
		}, {
			"streams":	[{
					"socket":	6,
					"start":	13.500169,
					"end":	13.600128,
					"seconds":	0.099959000945091248,
					"bytes":	390960,
					"bits_per_second":	31289628.45194976,
					"retransmits":	0,
					"snd_cwnd":	72400,
					"snd_wnd":	921600,
					"rtt":	145182,
					"rttvar":	339,
					"pmtu":	1500,
					"omitted":	false,
					"sender":	true
				}],
			"sum":	{
				"start":	13.500169,
				"end":	13.600128,
				"seconds":	0.099959000945091248,
				"bytes":	390960,
				"bits_per_second":	31289628.45194976,
				"retransmits":	0,
				"omitted":	false,
				"sender":	true
			}
		}, {
			"streams":	[{
					"socket":	6,
					"start":	13.600128,
					"end":	13.70018,
					"seconds":	0.10005199909210205,
					"bytes":	0,
					"bits_per_second":	0,
					"retransmits":	0,
					"snd_cwnd":	72400,
					"snd_wnd":	922112,
					"rtt":	146263,
					"rttvar":	496,
					"pmtu":	1500,
					"omitted":	false,
					"sender":	true
				}],
			"sum":	{
				"start":	13.600128,
				"end":	13.70018,
				"seconds":	0.10005199909210205,
				"bytes":	0,
				"bits_per_second":	0,
				"retransmits":	0,
				"omitted":	false,
				"sender":	true
			}
		}, {
			"streams":	[{
					"socket":	6,
					"start":	13.70018,
					"end":	13.800176,
					"seconds":	0.099996000528335571,
					"bytes":	0,
					"bits_per_second":	0,
					"retransmits":	0,
					"snd_cwnd":	72400,
					"snd_wnd":	923136,
					"rtt":	146388,
					"rttvar":	101,
					"pmtu":	1500,
					"omitted":	false,
					"sender":	true
				}],
			"sum":	{
				"start":	13.70018,
				"end":	13.800176,
				"seconds":	0.099996000528335571,
				"bytes":	0,
				"bits_per_second":	0,
				"retransmits":	0,
				"omitted":	false,
				"sender":	true
			}
		}, {
			"streams":	[{
					"socket":	6,
					"start":	13.800176,
					"end":	13.900795,
					"seconds":	0.10061900317668915,
					"bytes":	0,
					"bits_per_second":	0,
					"retransmits":	0,
					"snd_cwnd":	73848,
					"snd_wnd":	923136,
					"rtt":	148573,
					"rttvar":	609,
					"pmtu":	1500,
					"omitted":	false,
					"sender":	true
				}],
			"sum":	{
				"start":	13.800176,
				"end":	13.900795,
				"seconds":	0.10061900317668915,
				"bytes":	0,
				"bits_per_second":	0,
				"retransmits":	0,
				"omitted":	false,
				"sender":	true
			}
		}, {
			"streams":	[{
					"socket":	6,
					"start":	13.900795,
					"end":	14.000163,
					"seconds":	0.099367998540401459,
					"bytes":	0,
					"bits_per_second":	0,
					"retransmits":	0,
					"snd_cwnd":	73848,
					"snd_wnd":	922112,
					"rtt":	149539,
					"rttvar":	689,
					"pmtu":	1500,
					"omitted":	false,
					"sender":	true
				}],
			"sum":	{
				"start":	13.900795,
				"end":	14.000163,
				"seconds":	0.099367998540401459,
				"bytes":	0,
				"bits_per_second":	0,
				"retransmits":	0,
				"omitted":	false,
				"sender":	true
			}
		}, {
			"streams":	[{
					"socket":	6,
					"start":	14.000163,
					"end":	14.10017,
					"seconds":	0.10000699758529663,
					"bytes":	0,
					"bits_per_second":	0,
					"retransmits":	0,
					"snd_cwnd":	75296,
					"snd_wnd":	923136,
					"rtt":	150137,
					"rttvar":	65,
					"pmtu":	1500,
					"omitted":	false,
					"sender":	true
				}],
			"sum":	{
				"start":	14.000163,
				"end":	14.10017,
				"seconds":	0.10000699758529663,
				"bytes":	0,
				"bits_per_second":	0,
				"retransmits":	0,
				"omitted":	false,
				"sender":	true
			}
		}, {
			"streams":	[{
					"socket":	6,
					"start":	14.10017,
					"end":	14.20016,
					"seconds":	0.099990002810955048,
					"bytes":	0,
					"bits_per_second":	0,
					"retransmits":	0,
					"snd_cwnd":	75296,
					"snd_wnd":	923136,
					"rtt":	150117,
					"rttvar":	64,
					"pmtu":	1500,
					"omitted":	false,
					"sender":	true
				}],
			"sum":	{
				"start":	14.10017,
				"end":	14.20016,
				"seconds":	0.099990002810955048,
				"bytes":	0,
				"bits_per_second":	0,
				"retransmits":	0,
				"omitted":	false,
				"sender":	true
			}
		}, {
			"streams":	[{
					"socket":	6,
					"start":	14.20016,
					"end":	14.300165,
					"seconds":	0.10000500082969666,
					"bytes":	0,
					"bits_per_second":	0,
					"retransmits":	0,
					"snd_cwnd":	75296,
					"snd_wnd":	922112,
					"rtt":	151745,
					"rttvar":	1104,
					"pmtu":	1500,
					"omitted":	false,
					"sender":	true
				}],
			"sum":	{
				"start":	14.20016,
				"end":	14.300165,
				"seconds":	0.10000500082969666,
				"bytes":	0,
				"bits_per_second":	0,
				"retransmits":	0,
				"omitted":	false,
				"sender":	true
			}
		}, {
			"streams":	[{
					"socket":	6,
					"start":	14.300165,
					"end":	14.400115,
					"seconds":	0.099950000643730164,
					"bytes":	390960,
					"bits_per_second":	31292446.021571871,
					"retransmits":	0,
					"snd_cwnd":	76744,
					"snd_wnd":	922112,
					"rtt":	152554,
					"rttvar":	77,
					"pmtu":	1500,
					"omitted":	false,
					"sender":	true
				}],
			"sum":	{
				"start":	14.300165,
				"end":	14.400115,
				"seconds":	0.099950000643730164,
				"bytes":	390960,
				"bits_per_second":	31292446.021571871,
				"retransmits":	0,
				"omitted":	false,
				"sender":	true
			}
		}, {
			"streams":	[{
					"socket":	6,
					"start":	14.400115,
					"end":	14.500165,
					"seconds":	0.10005000233650208,
					"bytes":	0,
					"bits_per_second":	0,
					"retransmits":	0,
					"snd_cwnd":	76744,
					"snd_wnd":	923136,
					"rtt":	152610,
					"rttvar":	26,
					"pmtu":	1500,
					"omitted":	false,
					"sender":	true
				}],
			"sum":	{
				"start":	14.400115,
				"end":	14.500165,
				"seconds":	0.10005000233650208,
				"bytes":	0,
				"bits_per_second":	0,
				"retransmits":	0,
				"omitted":	false,
				"sender":	true
			}
		}, {
			"streams":	[{
					"socket":	6,
					"start":	14.500165,
					"end":	14.600166,
					"seconds":	0.10000099986791611,
					"bytes":	0,
					"bits_per_second":	0,
					"retransmits":	0,
					"snd_cwnd":	76744,
					"snd_wnd":	923136,
					"rtt":	153606,
					"rttvar":	527,
					"pmtu":	1500,
					"omitted":	false,
					"sender":	true
				}],
			"sum":	{
				"start":	14.500165,
				"end":	14.600166,
				"seconds":	0.10000099986791611,
				"bytes":	0,
				"bits_per_second":	0,
				"retransmits":	0,
				"omitted":	false,
				"sender":	true
			}
		}, {
			"streams":	[{
					"socket":	6,
					"start":	14.600166,
					"end":	14.70016,
					"seconds":	0.099993996322155,
					"bytes":	0,
					"bits_per_second":	0,
					"retransmits":	0,
					"snd_cwnd":	78192,
					"snd_wnd":	922112,
					"rtt":	155386,
					"rttvar":	911,
					"pmtu":	1500,
					"omitted":	false,
					"sender":	true
				}],
			"sum":	{
				"start":	14.600166,
				"end":	14.70016,
				"seconds":	0.099993996322155,
				"bytes":	0,
				"bits_per_second":	0,
				"retransmits":	0,
				"omitted":	false,
				"sender":	true
			}
		}, {
			"streams":	[{
					"socket":	6,
					"start":	14.70016,
					"end":	14.800224,
					"seconds":	0.1000640019774437,
					"bytes":	0,
					"bits_per_second":	0,
					"retransmits":	0,
					"snd_cwnd":	78192,
					"snd_wnd":	921088,
					"rtt":	157323,
					"rttvar":	215,
					"pmtu":	1500,
					"omitted":	false,
					"sender":	true
				}],
			"sum":	{
				"start":	14.70016,
				"end":	14.800224,
				"seconds":	0.1000640019774437,
				"bytes":	0,
				"bits_per_second":	0,
				"retransmits":	0,
				"omitted":	false,
				"sender":	true
			}
		}, {
			"streams":	[{
					"socket":	6,
					"start":	14.800224,
					"end":	14.900169,
					"seconds":	0.099945001304149628,
					"bytes":	0,
					"bits_per_second":	0,
					"retransmits":	1,
					"snd_cwnd":	70952,
					"snd_wnd":	923136,
					"rtt":	157555,
					"rttvar":	309,
					"pmtu":	1500,
					"omitted":	false,
					"sender":	true
				}],
			"sum":	{
				"start":	14.800224,
				"end":	14.900169,
				"seconds":	0.099945001304149628,
				"bytes":	0,
				"bits_per_second":	0,
				"retransmits":	1,
				"omitted":	false,
				"sender":	true
			}
		}, {
			"streams":	[{
					"socket":	6,
					"start":	14.900169,
					"end":	15.000158,
					"seconds":	0.099988996982574463,
					"bytes":	0,
					"bits_per_second":	0,
					"retransmits":	0,
					"snd_cwnd":	53576,
					"snd_wnd":	923136,
					"rtt":	156528,
					"rttvar":	212,
					"pmtu":	1500,
					"omitted":	false,
					"sender":	true
				}],
			"sum":	{
				"start":	14.900169,
				"end":	15.000158,
				"seconds":	0.099988996982574463,
				"bytes":	0,
				"bits_per_second":	0,
				"retransmits":	0,
				"omitted":	false,
				"sender":	true
			}
		}],
	"end":	{
		"streams":	[{
				"sender":	{
					"socket":	6,
					"start":	0,
					"end":	15.000158,
					"seconds":	15.000158,
					"bytes":	11763552,
					"bits_per_second":	6273828.3156750742,
					"retransmits":	46,
					"max_snd_cwnd":	356208,
					"max_snd_wnd":	923136,
					"max_rtt":	406710,
					"min_rtt":	30197,
					"mean_rtt":	199174,
					"sender":	true
				},
				"receiver":	{
					"socket":	6,
					"start":	0,
					"end":	15.128596,
					"seconds":	15.000158,
					"bytes":	10994664,
					"bits_per_second":	5813977.1859860625,
					"sender":	true
				}
			}],
		"sum_sent":	{
			"start":	0,
			"end":	15.000158,
			"seconds":	15.000158,
			"bytes":	11763552,
			"bits_per_second":	6273828.3156750742,
			"retransmits":	46,
			"sender":	true
		},
		"sum_received":	{
			"start":	0,
			"end":	15.128596,
			"seconds":	15.128596,
			"bytes":	10994664,
			"bits_per_second":	5813977.1859860625,
			"sender":	true
		},
		"cpu_utilization_percent":	{
			"host_total":	0.18089635606873594,
			"host_user":	0.033759413509641817,
			"host_system":	0.14713694255909412,
			"remote_total":	1.009490220724605,
			"remote_user":	0.51422382971196456,
			"remote_system":	0.49526639101264053
		},
		"sender_tcp_congestion":	"cubic",
		"receiver_tcp_congestion":	"cubic"
	}
}
