{
	"start":	{
		"connected":	[{
				"socket":	6,
				"local_host":	"10.0.0.2",
				"local_port":	43264,
				"remote_host":	"10.0.0.1",
				"remote_port":	5001
			}],
		"version":	"iperf 3.12",
		"system_info":	"Linux cs244c-vm 6.1.0-43-cloud-amd64 #1 SMP PREEMPT_DYNAMIC Debian 6.1.162-1 (2026-02-08) x86_64",
		"timestamp":	{
			"time":	"Fri, 13 Mar 2026 17:58:24 GMT",
			"timesecs":	1773424704
		},
		"connecting_to":	{
			"host":	"10.0.0.1",
			"port":	5001
		},
		"cookie":	"w4ylfjxxymg6wqoj64jj7xnhiphqikvo7bek",
		"tcp_mss_default":	1448,
		"target_bitrate":	0,
		"sock_bufsize":	0,
		"sndbuf_actual":	87380,
		"rcvbuf_actual":	87380,
		"test_start":	{
			"protocol":	"TCP",
			"num_streams":	1,
			"blksize":	131072,
			"omit":	0,
			"duration":	15,
			"bytes":	0,
			"blocks":	0,
			"reverse":	0,
			"tos":	0,
			"target_bitrate":	0
		}
	},
	"intervals":	[{
			"streams":	[{
					"socket":	6,
					"start":	0,
					"end":	0.100096,
					"seconds":	0.10009600222110748,
					"bytes":	842736,
					"bits_per_second":	67354218.4542743,
					"retransmits":	0,
					"snd_cwnd":	231680,
					"snd_wnd":	407552,
					"rtt":	20092,
					"rttvar":	25,
					"pmtu":	1500,
					"omitted":	false,
					"sender":	true
				}],
			"sum":	{
				"start":	0,
				"end":	0.100096,
				"seconds":	0.10009600222110748,
				"bytes":	842736,
				"bits_per_second":	67354218.4542743,
				"retransmits":	0,
				"omitted":	false,
				"sender":	true
			}
		}, {
			"streams":	[{
					"socket":	6,
					"start":	0.100096,
					"end":	0.200109,
					"seconds":	0.10001300275325775,
					"bytes":	16458768,
					"bits_per_second":	1316530254.8194022,
					"retransmits":	0,
					"snd_cwnd":	5874536,
					"snd_wnd":	8355840,
					"rtt":	26410,
					"rttvar":	2028,
					"pmtu":	1500,
					"omitted":	false,
					"sender":	true
				}],
			"sum":	{
				"start":	0.100096,
				"end":	0.200109,
				"seconds":	0.10001300275325775,
				"bytes":	16458768,
				"bits_per_second":	1316530254.8194022,
				"retransmits":	0,
				"omitted":	false,
				"sender":	true
			}
		}, {
			"streams":	[{
					"socket":	6,
					"start":	0.200109,
					"end":	0.300139,
					"seconds":	0.10002999752759933,
					"bytes":	11796480,
					"bits_per_second":	943435392.7076906,
					"retransmits":	0,
					"snd_cwnd":	6646320,
					"snd_wnd":	8355840,
					"rtt":	53632,
					"rttvar":	350,
					"pmtu":	1500,
					"omitted":	false,
					"sender":	true
				}],
			"sum":	{
				"start":	0.200109,
				"end":	0.300139,
				"seconds":	0.10002999752759933,
				"bytes":	11796480,
				"bits_per_second":	943435392.7076906,
				"retransmits":	0,
				"omitted":	false,
				"sender":	true
			}
		}, {
			"streams":	[{
					"socket":	6,
					"start":	0.300139,
					"end":	0.400117,
					"seconds":	0.0999779999256134,
					"bytes":	11796480,
					"bits_per_second":	943926064.43633044,
					"retransmits":	0,
					"snd_cwnd":	7229864,
					"snd_wnd":	8355840,
					"rtt":	58499,
					"rttvar":	187,
					"pmtu":	1500,
					"omitted":	false,
					"sender":	true
				}],
			"sum":	{
				"start":	0.300139,
				"end":	0.400117,
				"seconds":	0.0999779999256134,
				"bytes":	11796480,
				"bits_per_second":	943926064.43633044,
				"retransmits":	0,
				"omitted":	false,
				"sender":	true
			}
		}, {
			"streams":	[{
					"socket":	6,
					"start":	0.400117,
					"end":	0.500099,
					"seconds":	0.099982000887393951,
					"bytes":	11796480,
					"bits_per_second":	943888291.51646531,
					"retransmits":	0,
					"snd_cwnd":	7811960,
					"snd_wnd":	8355840,
					"rtt":	63094,
					"rttvar":	318,
					"pmtu":	1500,
					"omitted":	false,
					"sender":	true
				}],
			"sum":	{
				"start":	0.400117,
				"end":	0.500099,
				"seconds":	0.099982000887393951,
				"bytes":	11796480,
				"bits_per_second":	943888291.51646531,
				"retransmits":	0,
				"omitted":	false,
				"sender":	true
			}
		}, {
			"streams":	[{
					"socket":	6,
					"start":	0.500099,
					"end":	0.600102,
					"seconds":	0.10000299662351608,
					"bytes":	11796480,
					"bits_per_second":	943690121.15991032,
					"retransmits":	0,
					"snd_cwnd":	8395504,
					"snd_wnd":	8355840,
					"rtt":	68219,
					"rttvar":	112,
					"pmtu":	1500,
					"omitted":	false,
					"sender":	true
				}],
			"sum":	{
				"start":	0.500099,
				"end":	0.600102,
				"seconds":	0.10000299662351608,
				"bytes":	11796480,
				"bits_per_second":	943690121.15991032,
				"retransmits":	0,
				"omitted":	false,
				"sender":	true
			}
		}, {
			"streams":	[{
					"socket":	6,
					"start":	0.600102,
					"end":	0.700155,
					"seconds":	0.10005299746990204,
					"bytes":	11796480,
					"bits_per_second":	943218518.049786,
					"retransmits":	0,
					"snd_cwnd":	8770536,
					"snd_wnd":	8355840,
					"rtt":	71721,
					"rttvar":	37,
					"pmtu":	1500,
					"omitted":	false,
					"sender":	true
				}],
			"sum":	{
				"start":	0.600102,
				"end":	0.700155,
				"seconds":	0.10005299746990204,
				"bytes":	11796480,
				"bits_per_second":	943218518.049786,
				"retransmits":	0,
				"omitted":	false,
				"sender":	true
			}
		}, {
			"streams":	[{
					"socket":	6,
					"start":	0.700155,
					"end":	0.800138,
					"seconds":	0.099982999265193939,
					"bytes":	11796480,
					"bits_per_second":	943878866.34295738,
					"retransmits":	0,
					"snd_cwnd":	8770536,
					"snd_wnd":	8355840,
					"rtt":	71513,
					"rttvar":	35,
					"pmtu":	1500,
					"omitted":	false,
					"sender":	true
				}],
			"sum":	{
				"start":	0.700155,
				"end":	0.800138,
				"seconds":	0.099982999265193939,
				"bytes":	11796480,
				"bits_per_second":	943878866.34295738,
				"retransmits":	0,
				"omitted":	false,
				"sender":	true
			}
		}, {
			"streams":	[{
					"socket":	6,
					"start":	0.800138,
					"end":	0.90011,
					"seconds":	0.0999720022082329,
					"bytes":	10485760,
					"bits_per_second":	839095728.274729,
					"retransmits":	0,
					"snd_cwnd":	8770536,
					"snd_wnd":	8355840,
					"rtt":	71591,
					"rttvar":	32,
					"pmtu":	1500,
					"omitted":	false,
					"sender":	true
				}],
			"sum":	{
				"start":	0.800138,
				"end":	0.90011,
				"seconds":	0.0999720022082329,
				"bytes":	10485760,
				"bits_per_second":	839095728.274729,
				"retransmits":	0,
				"omitted":	false,
				"sender":	true
			}
		}, {
			"streams":	[{
					"socket":	6,
					"start":	0.90011,
					"end":	1.000135,
					"seconds":	0.1000249981880188,
					"bytes":	11796480,
					"bits_per_second":	943482546.45911157,
					"retransmits":	0,
					"snd_cwnd":	8770536,
					"snd_wnd":	8355840,
					"rtt":	71485,
					"rttvar":	29,
					"pmtu":	1500,
					"omitted":	false,
					"sender":	true
				}],
			"sum":	{
				"start":	0.90011,
				"end":	1.000135,
				"seconds":	0.1000249981880188,
				"bytes":	11796480,
				"bits_per_second":	943482546.45911157,
				"retransmits":	0,
				"omitted":	false,
				"sender":	true
			}
		}, {
			"streams":	[{
					"socket":	6,
					"start":	1.000135,
					"end":	1.100102,
					"seconds":	0.099967002868652344,
					"bytes":	11796480,
					"bits_per_second":	944029902.78698373,
					"retransmits":	0,
					"snd_cwnd":	8770536,
					"snd_wnd":	8355840,
					"rtt":	71099,
					"rttvar":	13,
					"pmtu":	1500,
					"omitted":	false,
					"sender":	true
				}],
			"sum":	{
				"start":	1.000135,
				"end":	1.100102,
				"seconds":	0.099967002868652344,
				"bytes":	11796480,
				"bits_per_second":	944029902.78698373,
				"retransmits":	0,
				"omitted":	false,
				"sender":	true
			}
		}, {
			"streams":	[{
					"socket":	6,
					"start":	1.100102,
					"end":	1.200137,
					"seconds":	0.10003499686717987,
					"bytes":	11796480,
					"bits_per_second":	943388243.66937256,
					"retransmits":	0,
					"snd_cwnd":	8770536,
					"snd_wnd":	8355840,
					"rtt":	71537,
					"rttvar":	29,
					"pmtu":	1500,
					"omitted":	false,
					"sender":	true
				}],
			"sum":	{
				"start":	1.100102,
				"end":	1.200137,
				"seconds":	0.10003499686717987,
				"bytes":	11796480,
				"bits_per_second":	943388243.66937256,
				"retransmits":	0,
				"omitted":	false,
				"sender":	true
			}
		}, {
			"streams":	[{
					"socket":	6,
					"start":	1.200137,
					"end":	1.300104,
					"seconds":	0.099967002868652344,
					"bytes":	11796480,
					"bits_per_second":	944029902.78698373,
					"retransmits":	0,
					"snd_cwnd":	8770536,
					"snd_wnd":	8355840,
					"rtt":	71518,
					"rttvar":	25,
					"pmtu":	1500,
					"omitted":	false,
					"sender":	true
				}],
			"sum":	{
				"start":	1.200137,
				"end":	1.300104,
				"seconds":	0.099967002868652344,
				"bytes":	11796480,
				"bits_per_second":	944029902.78698373,
				"retransmits":	0,
				"omitted":	false,
				"sender":	true
			}
		}, {
			"streams":	[{
					"socket":	6,
					"start":	1.300104,
					"end":	1.400098,
					"seconds":	0.099993996322155,
					"bytes":	11796480,
					"bits_per_second":	943775061.21425676,
					"retransmits":	0,
					"snd_cwnd":	8770536,
					"snd_wnd":	8355840,
					"rtt":	71480,
					"rttvar":	27,
					"pmtu":	1500,
					"omitted":	false,
					"sender":	true
				}],
			"sum":	{
				"start":	1.300104,
				"end":	1.400098,
				"seconds":	0.099993996322155,
				"bytes":	11796480,
				"bits_per_second":	943775061.21425676,
				"retransmits":	0,
				"omitted":	false,
				"sender":	true
			}
		}, {
			"streams":	[{
					"socket":	6,
					"start":	1.400098,
					"end":	1.500095,
					"seconds":	0.099996998906135559,
					"bytes":	11796480,
					"bits_per_second":	943746722.72499156,
					"retransmits":	0,
					"snd_cwnd":	8770536,
					"snd_wnd":	8355840,
					"rtt":	70556,
					"rttvar":	12,
					"pmtu":	1500,
					"omitted":	false,
					"sender":	true
				}],
			"sum":	{
				"start":	1.400098,
				"end":	1.500095,
				"seconds":	0.099996998906135559,
				"bytes":	11796480,
				"bits_per_second":	943746722.72499156,
				"retransmits":	0,
				"omitted":	false,
				"sender":	true
			}
		}, {
			"streams":	[{
					"socket":	6,
					"start":	1.500095,
					"end":	1.600091,
					"seconds":	0.099996000528335571,
					"bytes":	11796480,
					"bits_per_second":	943756145.259611,
					"retransmits":	0,
					"snd_cwnd":	8770536,
					"snd_wnd":	8355840,
					"rtt":	71064,
					"rttvar":	18,
					"pmtu":	1500,
					"omitted":	false,
					"sender":	true
				}],
			"sum":	{
				"start":	1.500095,
				"end":	1.600091,
				"seconds":	0.099996000528335571,
				"bytes":	11796480,
				"bits_per_second":	943756145.259611,
				"retransmits":	0,
				"omitted":	false,
				"sender":	true
			}
		}, {
			"streams":	[{
					"socket":	6,
					"start":	1.600091,
					"end":	1.700129,
					"seconds":	0.10003799945116043,
					"bytes":	11796480,
					"bits_per_second":	943359928.40473878,
					"retransmits":	0,
					"snd_cwnd":	8770536,
					"snd_wnd":	8355840,
					"rtt":	71631,
					"rttvar":	22,
					"pmtu":	1500,
					"omitted":	false,
					"sender":	true
				}],
			"sum":	{
				"start":	1.600091,
				"end":	1.700129,
				"seconds":	0.10003799945116043,
				"bytes":	11796480,
				"bits_per_second":	943359928.40473878,
				"retransmits":	0,
				"omitted":	false,
				"sender":	true
			}
		}, {
			"streams":	[{
					"socket":	6,
					"start":	1.700129,
					"end":	1.800118,
					"seconds":	0.099988996982574463,
					"bytes":	11796480,
					"bits_per_second":	943822248.92651546,
					"retransmits":	0,
					"snd_cwnd":	8770536,
					"snd_wnd":	8355840,
					"rtt":	71798,
					"rttvar":	21,
					"pmtu":	1500,
					"omitted":	false,
					"sender":	true
				}],
			"sum":	{
				"start":	1.700129,
				"end":	1.800118,
				"seconds":	0.099988996982574463,
				"bytes":	11796480,
				"bits_per_second":	943822248.92651546,
				"retransmits":	0,
				"omitted":	false,
				"sender":	true
			}
		}, {
			"streams":	[{
					"socket":	6,
					"start":	1.800118,
					"end":	1.90006,
					"seconds":	0.099941998720169067,
					"bytes":	11796480,
					"bits_per_second":	944266086.41513026,
					"retransmits":	0,
					"snd_cwnd":	8770536,
					"snd_wnd":	8355840,
					"rtt":	71584,
					"rttvar":	46,
					"pmtu":	1500,
					"omitted":	false,
					"sender":	true
				}],
			"sum":	{
				"start":	1.800118,
				"end":	1.90006,
				"seconds":	0.099941998720169067,
				"bytes":	11796480,
				"bits_per_second":	944266086.41513026,
				"retransmits":	0,
				"omitted":	false,
				"sender":	true
			}
		}, {
			"streams":	[{
					"socket":	6,
					"start":	1.90006,
					"end":	2.000216,
					"seconds":	0.10015600174665451,
					"bytes":	11796480,
					"bits_per_second":	942248475.91973972,
					"retransmits":	0,
					"snd_cwnd":	8770536,
					"snd_wnd":	8355840,
					"rtt":	71321,
					"rttvar":	25,
					"pmtu":	1500,
					"omitted":	false,
					"sender":	true
				}],
			"sum":	{
				"start":	1.90006,
				"end":	2.000216,
				"seconds":	0.10015600174665451,
				"bytes":	11796480,
				"bits_per_second":	942248475.91973972,
				"retransmits":	0,
				"omitted":	false,
				"sender":	true
			}
		}, {
			"streams":	[{
					"socket":	6,
					"start":	2.000216,
					"end":	2.100115,
					"seconds":	0.0998990014195442,
					"bytes":	10485760,
					"bits_per_second":	839708894.06296456,
					"retransmits":	0,
					"snd_cwnd":	8770536,
					"snd_wnd":	8355840,
					"rtt":	71461,
					"rttvar":	93,
					"pmtu":	1500,
					"omitted":	false,
					"sender":	true
				}],
			"sum":	{
				"start":	2.000216,
				"end":	2.100115,
				"seconds":	0.0998990014195442,
				"bytes":	10485760,
				"bits_per_second":	839708894.06296456,
				"retransmits":	0,
				"omitted":	false,
				"sender":	true
			}
		}, {
			"streams":	[{
					"socket":	6,
					"start":	2.100115,
					"end":	2.20009,
					"seconds":	0.099974997341632843,
					"bytes":	11796480,
					"bits_per_second":	943954413.69719839,
					"retransmits":	0,
					"snd_cwnd":	8770536,
					"snd_wnd":	8355840,
					"rtt":	71016,
					"rttvar":	29,
					"pmtu":	1500,
					"omitted":	false,
					"sender":	true
				}],
			"sum":	{
				"start":	2.100115,
				"end":	2.20009,
				"seconds":	0.099974997341632843,
				"bytes":	11796480,
				"bits_per_second":	943954413.69719839,
				"retransmits":	0,
				"omitted":	false,
				"sender":	true
			}
		}, {
			"streams":	[{
					"socket":	6,
					"start":	2.20009,
					"end":	2.300117,
					"seconds":	0.10002700239419937,
					"bytes":	11796480,
					"bits_per_second":	943463642.22819781,
					"retransmits":	0,
					"snd_cwnd":	8770536,
					"snd_wnd":	8355840,
					"rtt":	70348,
					"rttvar":	113,
					"pmtu":	1500,
					"omitted":	false,
					"sender":	true
				}],
			"sum":	{
				"start":	2.20009,
				"end":	2.300117,
				"seconds":	0.10002700239419937,
				"bytes":	11796480,
				"bits_per_second":	943463642.22819781,
				"retransmits":	0,
				"omitted":	false,
				"sender":	true
			}
		}, {
			"streams":	[{
					"socket":	6,
					"start":	2.300117,
					"end":	2.400104,
					"seconds":	0.0999870002269745,
					"bytes":	11796480,
					"bits_per_second":	943841097.20035756,
					"retransmits":	0,
					"snd_cwnd":	8770536,
					"snd_wnd":	8355840,
					"rtt":	71063,
					"rttvar":	19,
					"pmtu":	1500,
					"omitted":	false,
					"sender":	true
				}],
			"sum":	{
				"start":	2.300117,
				"end":	2.400104,
				"seconds":	0.0999870002269745,
				"bytes":	11796480,
				"bits_per_second":	943841097.20035756,
				"retransmits":	0,
				"omitted":	false,
				"sender":	true
			}
		}, {
			"streams":	[{
					"socket":	6,
					"start":	2.400104,
					"end":	2.500121,
					"seconds":	0.1000170037150383,
					"bytes":	11796480,
					"bits_per_second":	943557960.09324455,
					"retransmits":	0,
					"snd_cwnd":	8770536,
					"snd_wnd":	8355840,
					"rtt":	71334,
					"rttvar":	56,
					"pmtu":	1500,
					"omitted":	false,
					"sender":	true
				}],
			"sum":	{
				"start":	2.400104,
				"end":	2.500121,
				"seconds":	0.1000170037150383,
				"bytes":	11796480,
				"bits_per_second":	943557960.09324455,
				"retransmits":	0,
				"omitted":	false,
				"sender":	true
			}
		}, {
			"streams":	[{
					"socket":	6,
					"start":	2.500121,
					"end":	2.600107,
					"seconds":	0.0999860018491745,
					"bytes":	11796480,
					"bits_per_second":	943850521.61958361,
					"retransmits":	0,
					"snd_cwnd":	8770536,
					"snd_wnd":	8355840,
					"rtt":	72234,
					"rttvar":	78,
					"pmtu":	1500,
					"omitted":	false,
					"sender":	true
				}],
			"sum":	{
				"start":	2.500121,
				"end":	2.600107,
				"seconds":	0.0999860018491745,
				"bytes":	11796480,
				"bits_per_second":	943850521.61958361,
				"retransmits":	0,
				"omitted":	false,
				"sender":	true
			}
		}, {
			"streams":	[{
					"socket":	6,
					"start":	2.600107,
					"end":	2.700113,
					"seconds":	0.10000599920749664,
					"bytes":	11796480,
					"bits_per_second":	943661787.771285,
					"retransmits":	0,
					"snd_cwnd":	8770536,
					"snd_wnd":	8355840,
					"rtt":	73677,
					"rttvar":	73,
					"pmtu":	1500,
					"omitted":	false,
					"sender":	true
				}],
			"sum":	{
				"start":	2.600107,
				"end":	2.700113,
				"seconds":	0.10000599920749664,
				"bytes":	11796480,
				"bits_per_second":	943661787.771285,
				"retransmits":	0,
				"omitted":	false,
				"sender":	true
			}
		}, {
			"streams":	[{
					"socket":	6,
					"start":	2.700113,
					"end":	2.800085,
					"seconds":	0.0999720022082329,
					"bytes":	10485760,
					"bits_per_second":	839095728.274729,
					"retransmits":	0,
					"snd_cwnd":	8770536,
					"snd_wnd":	8355840,
					"rtt":	76481,
					"rttvar":	348,
					"pmtu":	1500,
					"omitted":	false,
					"sender":	true
				}],
			"sum":	{
				"start":	2.700113,
				"end":	2.800085,
				"seconds":	0.0999720022082329,
				"bytes":	10485760,
				"bits_per_second":	839095728.274729,
				"retransmits":	0,
				"omitted":	false,
				"sender":	true
			}
		}, {
			"streams":	[{
					"socket":	6,
					"start":	2.800085,
					"end":	2.900088,
					"seconds":	0.10000299662351608,
					"bytes":	10485760,
					"bits_per_second":	838835663.2532537,
					"retransmits":	0,
					"snd_cwnd":	8770536,
					"snd_wnd":	8355840,
					"rtt":	83991,
					"rttvar":	748,
					"pmtu":	1500,
					"omitted":	false,
					"sender":	true
				}],
			"sum":	{
				"start":	2.800085,
				"end":	2.900088,
				"seconds":	0.10000299662351608,
				"bytes":	10485760,
				"bits_per_second":	838835663.2532537,
				"retransmits":	0,
				"omitted":	false,
				"sender":	true
			}
		}, {
			"streams":	[{
					"socket":	6,
					"start":	2.900088,
					"end":	3.000096,
					"seconds":	0.10000800341367722,
					"bytes":	7864320,
					"bits_per_second":	629095250.9046464,
					"retransmits":	0,
					"snd_cwnd":	8770536,
					"snd_wnd":	8355840,
					"rtt":	96228,
					"rttvar":	1564,
					"pmtu":	1500,
					"omitted":	false,
					"sender":	true
				}],
			"sum":	{
				"start":	2.900088,
				"end":	3.000096,
				"seconds":	0.10000800341367722,
				"bytes":	7864320,
				"bits_per_second":	629095250.9046464,
				"retransmits":	0,
				"omitted":	false,
				"sender":	true
			}
		}, {
			"streams":	[{
					"socket":	6,
					"start":	3.000096,
					"end":	3.100114,
					"seconds":	0.10001800209283829,
					"bytes":	7864320,
					"bits_per_second":	629032361.010388,
					"retransmits":	0,
					"snd_cwnd":	8770536,
					"snd_wnd":	8355840,
					"rtt":	102005,
					"rttvar":	132,
					"pmtu":	1500,
					"omitted":	false,
					"sender":	true
				}],
			"sum":	{
				"start":	3.000096,
				"end":	3.100114,
				"seconds":	0.10001800209283829,
				"bytes":	7864320,
				"bits_per_second":	629032361.010388,
				"retransmits":	0,
				"omitted":	false,
				"sender":	true
			}
		}, {
			"streams":	[{
					"socket":	6,
					"start":	3.100114,
					"end":	3.200088,
					"seconds":	0.099973998963832855,
					"bytes":	6553600,
					"bits_per_second":	524424355.76641214,
					"retransmits":	460,
					"snd_cwnd":	7001080,
					"snd_wnd":	8380928,
					"rtt":	95459,
					"rttvar":	1229,
					"pmtu":	1500,
					"omitted":	false,
					"sender":	true
				}],
			"sum":	{
				"start":	3.100114,
				"end":	3.200088,
				"seconds":	0.099973998963832855,
				"bytes":	6553600,
				"bits_per_second":	524424355.76641214,
				"retransmits":	460,
				"omitted":	false,
				"sender":	true
			}
		}, {
			"streams":	[{
					"socket":	6,
					"start":	3.200088,
					"end":	3.300119,
					"seconds":	0.10003100335597992,
					"bytes":	2621440,
					"bits_per_second":	209650201.40174681,
					"retransmits":	240,
					"snd_cwnd":	6140968,
					"snd_wnd":	5711872,
					"rtt":	67492,
					"rttvar":	5122,
					"pmtu":	1500,
					"omitted":	false,
					"sender":	true
				}],
			"sum":	{
				"start":	3.200088,
				"end":	3.300119,
				"seconds":	0.10003100335597992,
				"bytes":	2621440,
				"bits_per_second":	209650201.40174681,
				"retransmits":	240,
				"omitted":	false,
				"sender":	true
			}
		}, {
			"streams":	[{
					"socket":	6,
					"start":	3.300119,
					"end":	3.400114,
					"seconds":	0.0999950021505356,
					"bytes":	14417920,
					"bits_per_second":	1153491249.756248,
					"retransmits":	0,
					"snd_cwnd":	6178616,
					"snd_wnd":	8355840,
					"rtt":	52523,
					"rttvar":	450,
					"pmtu":	1500,
					"omitted":	false,
					"sender":	true
				}],
			"sum":	{
				"start":	3.300119,
				"end":	3.400114,
				"seconds":	0.0999950021505356,
				"bytes":	14417920,
				"bits_per_second":	1153491249.756248,
				"retransmits":	0,
				"omitted":	false,
				"sender":	true
			}
		}, {
			"streams":	[{
					"socket":	6,
					"start":	3.400114,
					"end":	3.500092,
					"seconds":	0.0999779999256134,
					"bytes":	11796480,
					"bits_per_second":	943926064.43633044,
					"retransmits":	0,
					"snd_cwnd":	6227848,
					"snd_wnd":	8355840,
					"rtt":	52784,
					"rttvar":	19,
					"pmtu":	1500,
					"omitted":	false,
					"sender":	true
				}],
			"sum":	{
				"start":	3.400114,
				"end":	3.500092,
				"seconds":	0.0999779999256134,
				"bytes":	11796480,
				"bits_per_second":	943926064.43633044,
				"retransmits":	0,
				"omitted":	false,
				"sender":	true
			}
		}, {
			"streams":	[{
					"socket":	6,
					"start":	3.500092,
					"end":	3.600088,
					"seconds":	0.099996000528335571,
					"bytes":	11796480,
					"bits_per_second":	943756145.259611,
					"retransmits":	0,
					"snd_cwnd":	6274184,
					"snd_wnd":	8355840,
					"rtt":	52907,
					"rttvar":	34,
					"pmtu":	1500,
					"omitted":	false,
					"sender":	true
				}],
			"sum":	{
				"start":	3.500092,
				"end":	3.600088,
				"seconds":	0.099996000528335571,
				"bytes":	11796480,
				"bits_per_second":	943756145.259611,
				"retransmits":	0,
				"omitted":	false,
				"sender":	true
			}
		}, {
			"streams":	[{
					"socket":	6,
					"start":	3.600088,
					"end":	3.700089,
					"seconds":	0.10000099986791611,
					"bytes":	11796480,
					"bits_per_second":	943708964.156846,
					"retransmits":	0,
					"snd_cwnd":	6319072,
					"snd_wnd":	8355840,
					"rtt":	53381,
					"rttvar":	103,
					"pmtu":	1500,
					"omitted":	false,
					"sender":	true
				}],
			"sum":	{
				"start":	3.600088,
				"end":	3.700089,
				"seconds":	0.10000099986791611,
				"bytes":	11796480,
				"bits_per_second":	943708964.156846,
				"retransmits":	0,
				"omitted":	false,
				"sender":	true
			}
		}, {
			"streams":	[{
					"socket":	6,
					"start":	3.700089,
					"end":	3.8001,
					"seconds":	0.10001099854707718,
					"bytes":	11796480,
					"bits_per_second":	943614616.102221,
					"retransmits":	0,
					"snd_cwnd":	6363960,
					"snd_wnd":	8355840,
					"rtt":	53627,
					"rttvar":	8,
					"pmtu":	1500,
					"omitted":	false,
					"sender":	true
				}],
			"sum":	{
				"start":	3.700089,
				"end":	3.8001,
				"seconds":	0.10001099854707718,
				"bytes":	11796480,
				"bits_per_second":	943614616.102221,
				"retransmits":	0,
				"omitted":	false,
				"sender":	true
			}
		}, {
			"streams":	[{
					"socket":	6,
					"start":	3.8001,
					"end":	3.900058,
					"seconds":	0.09995800256729126,
					"bytes":	11796480,
					"bits_per_second":	944114904.02150965,
					"retransmits":	0,
					"snd_cwnd":	6408848,
					"snd_wnd":	8355840,
					"rtt":	54229,
					"rttvar":	38,
					"pmtu":	1500,
					"omitted":	false,
					"sender":	true
				}],
			"sum":	{
				"start":	3.8001,
				"end":	3.900058,
				"seconds":	0.09995800256729126,
				"bytes":	11796480,
				"bits_per_second":	944114904.02150965,
				"retransmits":	0,
				"omitted":	false,
				"sender":	true
			}
		}, {
			"streams":	[{
					"socket":	6,
					"start":	3.900058,
					"end":	4.000061,
					"seconds":	0.10000299662351608,
					"bytes":	11796480,
					"bits_per_second":	943690121.15991032,
					"retransmits":	0,
					"snd_cwnd":	6453736,
					"snd_wnd":	8355840,
					"rtt":	54556,
					"rttvar":	20,
					"pmtu":	1500,
					"omitted":	false,
					"sender":	true
				}],
			"sum":	{
				"start":	3.900058,
				"end":	4.000061,
				"seconds":	0.10000299662351608,
				"bytes":	11796480,
				"bits_per_second":	943690121.15991032,
				"retransmits":	0,
				"omitted":	false,
				"sender":	true
			}
		}, {
			"streams":	[{
					"socket":	6,
					"start":	4.000061,
					"end":	4.100098,
					"seconds":	0.10003700107336044,
					"bytes":	11796480,
					"bits_per_second":	943369343.21725631,
					"retransmits":	0,
					"snd_cwnd":	6495728,
					"snd_wnd":	8355840,
					"rtt":	55107,
					"rttvar":	30,
					"pmtu":	1500,
					"omitted":	false,
					"sender":	true
				}],
			"sum":	{
				"start":	4.000061,
				"end":	4.100098,
				"seconds":	0.10003700107336044,
				"bytes":	11796480,
				"bits_per_second":	943369343.21725631,
				"retransmits":	0,
				"omitted":	false,
				"sender":	true
			}
		}, {
			"streams":	[{
					"socket":	6,
					"start":	4.100098,
					"end":	4.200135,
					"seconds":	0.10003700107336044,
					"bytes":	11796480,
					"bits_per_second":	943369343.21725631,
					"retransmits":	0,
					"snd_cwnd":	6539168,
					"snd_wnd":	8355840,
					"rtt":	55034,
					"rttvar":	185,
					"pmtu":	1500,
					"omitted":	false,
					"sender":	true
				}],
			"sum":	{
				"start":	4.100098,
				"end":	4.200135,
				"seconds":	0.10003700107336044,
				"bytes":	11796480,
				"bits_per_second":	943369343.21725631,
				"retransmits":	0,
				"omitted":	false,
				"sender":	true
			}
		}, {
			"streams":	[{
					"socket":	6,
					"start":	4.200135,
					"end":	4.300137,
					"seconds":	0.10000199824571609,
					"bytes":	11796480,
					"bits_per_second":	943699542.564318,
					"retransmits":	0,
					"snd_cwnd":	6581160,
					"snd_wnd":	8355840,
					"rtt":	56055,
					"rttvar":	61,
					"pmtu":	1500,
					"omitted":	false,
					"sender":	true
				}],
			"sum":	{
				"start":	4.200135,
				"end":	4.300137,
				"seconds":	0.10000199824571609,
				"bytes":	11796480,
				"bits_per_second":	943699542.564318,
				"retransmits":	0,
				"omitted":	false,
				"sender":	true
			}
		}, {
			"streams":	[{
					"socket":	6,
					"start":	4.300137,
					"end":	4.400109,
					"seconds":	0.0999720022082329,
					"bytes":	10485760,
					"bits_per_second":	839095728.274729,
					"retransmits":	0,
					"snd_cwnd":	6623152,
					"snd_wnd":	8355840,
					"rtt":	56753,
					"rttvar":	16,
					"pmtu":	1500,
					"omitted":	false,
					"sender":	true
				}],
			"sum":	{
				"start":	4.300137,
				"end":	4.400109,
				"seconds":	0.0999720022082329,
				"bytes":	10485760,
				"bits_per_second":	839095728.274729,
				"retransmits":	0,
				"omitted":	false,
				"sender":	true
			}
		}, {
			"streams":	[{
					"socket":	6,
					"start":	4.400109,
					"end":	4.500146,
					"seconds":	0.10003700107336044,
					"bytes":	11796480,
					"bits_per_second":	943369343.21725631,
					"retransmits":	0,
					"snd_cwnd":	6663696,
					"snd_wnd":	8355840,
					"rtt":	58393,
					"rttvar":	69,
					"pmtu":	1500,
					"omitted":	false,
					"sender":	true
				}],
			"sum":	{
				"start":	4.400109,
				"end":	4.500146,
				"seconds":	0.10003700107336044,
				"bytes":	11796480,
				"bits_per_second":	943369343.21725631,
				"retransmits":	0,
				"omitted":	false,
				"sender":	true
			}
		}, {
			"streams":	[{
					"socket":	6,
					"start":	4.500146,
					"end":	4.600116,
					"seconds":	0.0999699980020523,
					"bytes":	10485760,
					"bits_per_second":	839112550.530189,
					"retransmits":	0,
					"snd_cwnd":	6702792,
					"snd_wnd":	8355840,
					"rtt":	61778,
					"rttvar":	375,
					"pmtu":	1500,
					"omitted":	false,
					"sender":	true
				}],
			"sum":	{
				"start":	4.500146,
				"end":	4.600116,
				"seconds":	0.0999699980020523,
				"bytes":	10485760,
				"bits_per_second":	839112550.530189,
				"retransmits":	0,
				"omitted":	false,
				"sender":	true
			}
		}, {
			"streams":	[{
					"socket":	6,
					"start":	4.600116,
					"end":	4.700137,
					"seconds":	0.10002099722623825,
					"bytes":	9175040,
					"bits_per_second":	733849112.04169726,
					"retransmits":	0,
					"snd_cwnd":	6738992,
					"snd_wnd":	8355840,
					"rtt":	71843,
					"rttvar":	1293,
					"pmtu":	1500,
					"omitted":	false,
					"sender":	true
				}],
			"sum":	{
				"start":	4.600116,
				"end":	4.700137,
				"seconds":	0.10002099722623825,
				"bytes":	9175040,
				"bits_per_second":	733849112.04169726,
				"retransmits":	0,
				"omitted":	false,
				"sender":	true
			}
		}, {
			"streams":	[{
					"socket":	6,
					"start":	4.700137,
					"end":	4.80011,
					"seconds":	0.099973000586032867,
					"bytes":	9175040,
					"bits_per_second":	734201430.08346081,
					"retransmits":	0,
					"snd_cwnd":	6778088,
					"snd_wnd":	8355840,
					"rtt":	75483,
					"rttvar":	156,
					"pmtu":	1500,
					"omitted":	false,
					"sender":	true
				}],
			"sum":	{
				"start":	4.700137,
				"end":	4.80011,
				"seconds":	0.099973000586032867,
				"bytes":	9175040,
				"bits_per_second":	734201430.08346081,
				"retransmits":	0,
				"omitted":	false,
				"sender":	true
			}
		}, {
			"streams":	[{
					"socket":	6,
					"start":	4.80011,
					"end":	4.900116,
					"seconds":	0.10000599920749664,
					"bytes":	9175040,
					"bits_per_second":	733959168.266555,
					"retransmits":	0,
					"snd_cwnd":	6817184,
					"snd_wnd":	8355840,
					"rtt":	77414,
					"rttvar":	167,
					"pmtu":	1500,
					"omitted":	false,
					"sender":	true
				}],
			"sum":	{
				"start":	4.80011,
				"end":	4.900116,
				"seconds":	0.10000599920749664,
				"bytes":	9175040,
				"bits_per_second":	733959168.266555,
				"retransmits":	0,
				"omitted":	false,
				"sender":	true
			}
		}, {
			"streams":	[{
					"socket":	6,
					"start":	4.900116,
					"end":	5.000077,
					"seconds":	0.099960997700691223,
					"bytes":	9175040,
					"bits_per_second":	734289589.823616,
					"retransmits":	0,
					"snd_cwnd":	6853384,
					"snd_wnd":	8355840,
					"rtt":	78491,
					"rttvar":	235,
					"pmtu":	1500,
					"omitted":	false,
					"sender":	true
				}],
			"sum":	{
				"start":	4.900116,
				"end":	5.000077,
				"seconds":	0.099960997700691223,
				"bytes":	9175040,
				"bits_per_second":	734289589.823616,
				"retransmits":	0,
				"omitted":	false,
				"sender":	true
			}
		}, {
			"streams":	[{
					"socket":	6,
					"start":	5.000077,
					"end":	5.100097,
					"seconds":	0.10001999884843826,
					"bytes":	7864320,
					"bits_per_second":	629019803.282895,
					"retransmits":	0,
					"snd_cwnd":	6891032,
					"snd_wnd":	8355840,
					"rtt":	81078,
					"rttvar":	176,
					"pmtu":	1500,
					"omitted":	false,
					"sender":	true
				}],
			"sum":	{
				"start":	5.000077,
				"end":	5.100097,
				"seconds":	0.10001999884843826,
				"bytes":	7864320,
				"bits_per_second":	629019803.282895,
				"retransmits":	0,
				"omitted":	false,
				"sender":	true
			}
		}, {
			"streams":	[{
					"socket":	6,
					"start":	5.100097,
					"end":	5.200329,
					"seconds":	0.10023199766874313,
					"bytes":	9175040,
					"bits_per_second":	732304271.162796,
					"retransmits":	0,
					"snd_cwnd":	6930128,
					"snd_wnd":	8355840,
					"rtt":	81450,
					"rttvar":	117,
					"pmtu":	1500,
					"omitted":	false,
					"sender":	true
				}],
			"sum":	{
				"start":	5.100097,
				"end":	5.200329,
				"seconds":	0.10023199766874313,
				"bytes":	9175040,
				"bits_per_second":	732304271.162796,
				"retransmits":	0,
				"omitted":	false,
				"sender":	true
			}
		}, {
			"streams":	[{
					"socket":	6,
					"start":	5.200329,
					"end":	5.300078,
					"seconds":	0.099748998880386353,
					"bytes":	9175040,
					"bits_per_second":	735850192.22115433,
					"retransmits":	0,
					"snd_cwnd":	6972120,
					"snd_wnd":	8355840,
					"rtt":	63481,
					"rttvar":	1729,
					"pmtu":	1500,
					"omitted":	false,
					"sender":	true
				}],
			"sum":	{
				"start":	5.200329,
				"end":	5.300078,
				"seconds":	0.099748998880386353,
				"bytes":	9175040,
				"bits_per_second":	735850192.22115433,
				"retransmits":	0,
				"omitted":	false,
				"sender":	true
			}
		}, {
			"streams":	[{
					"socket":	6,
					"start":	5.300078,
					"end":	5.400141,
					"seconds":	0.10006300359964371,
					"bytes":	11796480,
					"bits_per_second":	943124197.8062712,
					"retransmits":	0,
					"snd_cwnd":	7011216,
					"snd_wnd":	8355840,
					"rtt":	59710,
					"rttvar":	25,
					"pmtu":	1500,
					"omitted":	false,
					"sender":	true
				}],
			"sum":	{
				"start":	5.300078,
				"end":	5.400141,
				"seconds":	0.10006300359964371,
				"bytes":	11796480,
				"bits_per_second":	943124197.8062712,
				"retransmits":	0,
				"omitted":	false,
				"sender":	true
			}
		}, {
			"streams":	[{
					"socket":	6,
					"start":	5.400141,
					"end":	5.500107,
					"seconds":	0.099965997040271759,
					"bytes":	11796480,
					"bits_per_second":	944039401.33745551,
					"retransmits":	0,
					"snd_cwnd":	7047416,
					"snd_wnd":	8355840,
					"rtt":	59733,
					"rttvar":	18,
					"pmtu":	1500,
					"omitted":	false,
					"sender":	true
				}],
			"sum":	{
				"start":	5.400141,
				"end":	5.500107,
				"seconds":	0.099965997040271759,
				"bytes":	11796480,
				"bits_per_second":	944039401.33745551,
				"retransmits":	0,
				"omitted":	false,
				"sender":	true
			}
		}, {
			"streams":	[{
					"socket":	6,
					"start":	5.500107,
					"end":	5.60012,
					"seconds":	0.10001300275325775,
					"bytes":	11796480,
					"bits_per_second":	943595706.5785228,
					"retransmits":	0,
					"snd_cwnd":	7083616,
					"snd_wnd":	8355840,
					"rtt":	60391,
					"rttvar":	18,
					"pmtu":	1500,
					"omitted":	false,
					"sender":	true
				}],
			"sum":	{
				"start":	5.500107,
				"end":	5.60012,
				"seconds":	0.10001300275325775,
				"bytes":	11796480,
				"bits_per_second":	943595706.5785228,
				"retransmits":	0,
				"omitted":	false,
				"sender":	true
			}
		}, {
			"streams":	[{
					"socket":	6,
					"start":	5.60012,
					"end":	5.700084,
					"seconds":	0.0999640002846718,
					"bytes":	11796480,
					"bits_per_second":	944058258.28551531,
					"retransmits":	0,
					"snd_cwnd":	7118368,
					"snd_wnd":	8355840,
					"rtt":	60557,
					"rttvar":	89,
					"pmtu":	1500,
					"omitted":	false,
					"sender":	true
				}],
			"sum":	{
				"start":	5.60012,
				"end":	5.700084,
				"seconds":	0.0999640002846718,
				"bytes":	11796480,
				"bits_per_second":	944058258.28551531,
				"retransmits":	0,
				"omitted":	false,
				"sender":	true
			}
		}, {
			"streams":	[{
					"socket":	6,
					"start":	5.700084,
					"end":	5.800132,
					"seconds":	0.1000479981303215,
					"bytes":	11796480,
					"bits_per_second":	943265650.12397552,
					"retransmits":	0,
					"snd_cwnd":	7151672,
					"snd_wnd":	8355840,
					"rtt":	60893,
					"rttvar":	24,
					"pmtu":	1500,
					"omitted":	false,
					"sender":	true
				}],
			"sum":	{
				"start":	5.700084,
				"end":	5.800132,
				"seconds":	0.1000479981303215,
				"bytes":	11796480,
				"bits_per_second":	943265650.12397552,
				"retransmits":	0,
				"omitted":	false,
				"sender":	true
			}
		}, {
			"streams":	[{
					"socket":	6,
					"start":	5.800132,
					"end":	5.900064,
					"seconds":	0.099932000041008,
					"bytes":	10485760,
					"bits_per_second":	839431613.15270972,
					"retransmits":	0,
					"snd_cwnd":	7186424,
					"snd_wnd":	8355840,
					"rtt":	60812,
					"rttvar":	20,
					"pmtu":	1500,
					"omitted":	false,
					"sender":	true
				}],
			"sum":	{
				"start":	5.800132,
				"end":	5.900064,
				"seconds":	0.099932000041008,
				"bytes":	10485760,
				"bits_per_second":	839431613.15270972,
				"retransmits":	0,
				"omitted":	false,
				"sender":	true
			}
		}, {
			"streams":	[{
					"socket":	6,
					"start":	5.900064,
					"end":	6.000116,
					"seconds":	0.10005199909210205,
					"bytes":	11796480,
					"bits_per_second":	943227930.03992629,
					"retransmits":	0,
					"snd_cwnd":	7219728,
					"snd_wnd":	8355840,
					"rtt":	61344,
					"rttvar":	15,
					"pmtu":	1500,
					"omitted":	false,
					"sender":	true
				}],
			"sum":	{
				"start":	5.900064,
				"end":	6.000116,
				"seconds":	0.10005199909210205,
				"bytes":	11796480,
				"bits_per_second":	943227930.03992629,
				"retransmits":	0,
				"omitted":	false,
				"sender":	true
			}
		}, {
			"streams":	[{
					"socket":	6,
					"start":	6.000116,
					"end":	6.100096,
					"seconds":	0.099979996681213379,
					"bytes":	11796480,
					"bits_per_second":	943907212.76882,
					"retransmits":	0,
					"snd_cwnd":	7253032,
					"snd_wnd":	8355840,
					"rtt":	61492,
					"rttvar":	275,
					"pmtu":	1500,
					"omitted":	false,
					"sender":	true
				}],
			"sum":	{
				"start":	6.000116,
				"end":	6.100096,
				"seconds":	0.099979996681213379,
				"bytes":	11796480,
				"bits_per_second":	943907212.76882,
				"retransmits":	0,
				"omitted":	false,
				"sender":	true
			}
		}, {
			"streams":	[{
					"socket":	6,
					"start":	6.100096,
					"end":	6.200097,
					"seconds":	0.10000099986791611,
					"bytes":	11796480,
					"bits_per_second":	943708964.156846,
					"retransmits":	0,
					"snd_cwnd":	7286336,
					"snd_wnd":	8355840,
					"rtt":	61570,
					"rttvar":	29,
					"pmtu":	1500,
					"omitted":	false,
					"sender":	true
				}],
			"sum":	{
				"start":	6.100096,
				"end":	6.200097,
				"seconds":	0.10000099986791611,
				"bytes":	11796480,
				"bits_per_second":	943708964.156846,
				"retransmits":	0,
				"omitted":	false,
				"sender":	true
			}
		}, {
			"streams":	[{
					"socket":	6,
					"start":	6.200097,
					"end":	6.300138,
					"seconds":	0.100041002035141,
					"bytes":	11796480,
					"bits_per_second":	943331614.83978736,
					"retransmits":	0,
					"snd_cwnd":	7318192,
					"snd_wnd":	8355840,
					"rtt":	62563,
					"rttvar":	328,
					"pmtu":	1500,
					"omitted":	false,
					"sender":	true
				}],
			"sum":	{
				"start":	6.200097,
				"end":	6.300138,
				"seconds":	0.100041002035141,
				"bytes":	11796480,
				"bits_per_second":	943331614.83978736,
				"retransmits":	0,
				"omitted":	false,
				"sender":	true
			}
		}, {
			"streams":	[{
					"socket":	6,
					"start":	6.300138,
					"end":	6.400127,
					"seconds":	0.099988996982574463,
					"bytes":	11796480,
					"bits_per_second":	943822248.92651546,
					"retransmits":	0,
					"snd_cwnd":	7350048,
					"snd_wnd":	8355840,
					"rtt":	62832,
					"rttvar":	34,
					"pmtu":	1500,
					"omitted":	false,
					"sender":	true
				}],
			"sum":	{
				"start":	6.300138,
				"end":	6.400127,
				"seconds":	0.099988996982574463,
				"bytes":	11796480,
				"bits_per_second":	943822248.92651546,
				"retransmits":	0,
				"omitted":	false,
				"sender":	true
			}
		}, {
			"streams":	[{
					"socket":	6,
					"start":	6.400127,
					"end":	6.50013,
					"seconds":	0.10000299662351608,
					"bytes":	11796480,
					"bits_per_second":	943690121.15991032,
					"retransmits":	0,
					"snd_cwnd":	7380456,
					"snd_wnd":	8355840,
					"rtt":	63531,
					"rttvar":	82,
					"pmtu":	1500,
					"omitted":	false,
					"sender":	true
				}],
			"sum":	{
				"start":	6.400127,
				"end":	6.50013,
				"seconds":	0.10000299662351608,
				"bytes":	11796480,
				"bits_per_second":	943690121.15991032,
				"retransmits":	0,
				"omitted":	false,
				"sender":	true
			}
		}, {
			"streams":	[{
					"socket":	6,
					"start":	6.50013,
					"end":	6.600114,
					"seconds":	0.099983997642993927,
					"bytes":	10485760,
					"bits_per_second":	838995058.984602,
					"retransmits":	0,
					"snd_cwnd":	7410864,
					"snd_wnd":	8355840,
					"rtt":	65760,
					"rttvar":	64,
					"pmtu":	1500,
					"omitted":	false,
					"sender":	true
				}],
			"sum":	{
				"start":	6.50013,
				"end":	6.600114,
				"seconds":	0.099983997642993927,
				"bytes":	10485760,
				"bits_per_second":	838995058.984602,
				"retransmits":	0,
				"omitted":	false,
				"sender":	true
			}
		}, {
			"streams":	[{
					"socket":	6,
					"start":	6.600114,
					"end":	6.700102,
					"seconds":	0.099987998604774475,
					"bytes":	10485760,
					"bits_per_second":	838961487.083855,
					"retransmits":	0,
					"snd_cwnd":	7439824,
					"snd_wnd":	8355840,
					"rtt":	69367,
					"rttvar":	400,
					"pmtu":	1500,
					"omitted":	false,
					"sender":	true
				}],
			"sum":	{
				"start":	6.600114,
				"end":	6.700102,
				"seconds":	0.099987998604774475,
				"bytes":	10485760,
				"bits_per_second":	838961487.083855,
				"retransmits":	0,
				"omitted":	false,
				"sender":	true
			}
		}, {
			"streams":	[{
					"socket":	6,
					"start":	6.700102,
					"end":	6.800101,
					"seconds":	0.099999003112316132,
					"bytes":	10485760,
					"bits_per_second":	838869162.58336556,
					"retransmits":	0,
					"snd_cwnd":	7468784,
					"snd_wnd":	8355840,
					"rtt":	79370,
					"rttvar":	457,
					"pmtu":	1500,
					"omitted":	false,
					"sender":	true
				}],
			"sum":	{
				"start":	6.700102,
				"end":	6.800101,
				"seconds":	0.099999003112316132,
				"bytes":	10485760,
				"bits_per_second":	838869162.58336556,
				"retransmits":	0,
				"omitted":	false,
				"sender":	true
			}
		}, {
			"streams":	[{
					"socket":	6,
					"start":	6.800101,
					"end":	6.900125,
					"seconds":	0.10002399981021881,
					"bytes":	9175040,
					"bits_per_second":	733827082.89277148,
					"retransmits":	0,
					"snd_cwnd":	7497744,
					"snd_wnd":	8355840,
					"rtt":	81446,
					"rttvar":	90,
					"pmtu":	1500,
					"omitted":	false,
					"sender":	true
				}],
			"sum":	{
				"start":	6.800101,
				"end":	6.900125,
				"seconds":	0.10002399981021881,
				"bytes":	9175040,
				"bits_per_second":	733827082.89277148,
				"retransmits":	0,
				"omitted":	false,
				"sender":	true
			}
		}, {
			"streams":	[{
					"socket":	6,
					"start":	6.900125,
					"end":	7.000156,
					"seconds":	0.10003100335597992,
					"bytes":	9175040,
					"bits_per_second":	733775704.90611374,
					"retransmits":	0,
					"snd_cwnd":	7525256,
					"snd_wnd":	8355840,
					"rtt":	83044,
					"rttvar":	69,
					"pmtu":	1500,
					"omitted":	false,
					"sender":	true
				}],
			"sum":	{
				"start":	6.900125,
				"end":	7.000156,
				"seconds":	0.10003100335597992,
				"bytes":	9175040,
				"bits_per_second":	733775704.90611374,
				"retransmits":	0,
				"omitted":	false,
				"sender":	true
			}
		}, {
			"streams":	[{
					"socket":	6,
					"start":	7.000156,
					"end":	7.100157,
					"seconds":	0.10000099986791611,
					"bytes":	7864320,
					"bits_per_second":	629139309.43789732,
					"retransmits":	0,
					"snd_cwnd":	7554216,
					"snd_wnd":	8355840,
					"rtt":	84065,
					"rttvar":	67,
					"pmtu":	1500,
					"omitted":	false,
					"sender":	true
				}],
			"sum":	{
				"start":	7.000156,
				"end":	7.100157,
				"seconds":	0.10000099986791611,
				"bytes":	7864320,
				"bits_per_second":	629139309.43789732,
				"retransmits":	0,
				"omitted":	false,
				"sender":	true
			}
		}, {
			"streams":	[{
					"socket":	6,
					"start":	7.100157,
					"end":	7.200158,
					"seconds":	0.10000099986791611,
					"bytes":	9175040,
					"bits_per_second":	733995861.01088023,
					"retransmits":	0,
					"snd_cwnd":	7581728,
					"snd_wnd":	8355840,
					"rtt":	85252,
					"rttvar":	142,
					"pmtu":	1500,
					"omitted":	false,
					"sender":	true
				}],
			"sum":	{
				"start":	7.100157,
				"end":	7.200158,
				"seconds":	0.10000099986791611,
				"bytes":	9175040,
				"bits_per_second":	733995861.01088023,
				"retransmits":	0,
				"omitted":	false,
				"sender":	true
			}
		}, {
			"streams":	[{
					"socket":	6,
					"start":	7.200158,
					"end":	7.300072,
					"seconds":	0.099913999438285828,
					"bytes":	9175040,
					"bits_per_second":	734634990.21813643,
					"retransmits":	0,
					"snd_cwnd":	7609240,
					"snd_wnd":	8375296,
					"rtt":	85696,
					"rttvar":	120,
					"pmtu":	1500,
					"omitted":	false,
					"sender":	true
				}],
			"sum":	{
				"start":	7.200158,
				"end":	7.300072,
				"seconds":	0.099913999438285828,
				"bytes":	9175040,
				"bits_per_second":	734634990.21813643,
				"retransmits":	0,
				"omitted":	false,
				"sender":	true
			}
		}, {
			"streams":	[{
					"socket":	6,
					"start":	7.300072,
					"end":	7.400407,
					"seconds":	0.10033500194549561,
					"bytes":	9175040,
					"bits_per_second":	731552484.943119,
					"retransmits":	0,
					"snd_cwnd":	7636752,
					"snd_wnd":	8355840,
					"rtt":	86502,
					"rttvar":	496,
					"pmtu":	1500,
					"omitted":	false,
					"sender":	true
				}],
			"sum":	{
				"start":	7.300072,
				"end":	7.400407,
				"seconds":	0.10033500194549561,
				"bytes":	9175040,
				"bits_per_second":	731552484.943119,
				"retransmits":	0,
				"omitted":	false,
				"sender":	true
			}
		}, {
			"streams":	[{
					"socket":	6,
					"start":	7.400407,
					"end":	7.500161,
					"seconds":	0.0997539982199669,
					"bytes":	10485760,
					"bits_per_second":	840929501.54261839,
					"retransmits":	0,
					"snd_cwnd":	7668608,
					"snd_wnd":	8355840,
					"rtt":	62636,
					"rttvar":	30,
					"pmtu":	1500,
					"omitted":	false,
					"sender":	true
				}],
			"sum":	{
				"start":	7.400407,
				"end":	7.500161,
				"seconds":	0.0997539982199669,
				"bytes":	10485760,
				"bits_per_second":	840929501.54261839,
				"retransmits":	0,
				"omitted":	false,
				"sender":	true
			}
		}, {
			"streams":	[{
					"socket":	6,
					"start":	7.500161,
					"end":	7.600151,
					"seconds":	0.099990002810955048,
					"bytes":	11796480,
					"bits_per_second":	943812754.74532223,
					"retransmits":	0,
					"snd_cwnd":	7694672,
					"snd_wnd":	8355840,
					"rtt":	65658,
					"rttvar":	41,
					"pmtu":	1500,
					"omitted":	false,
					"sender":	true
				}],
			"sum":	{
				"start":	7.500161,
				"end":	7.600151,
				"seconds":	0.099990002810955048,
				"bytes":	11796480,
				"bits_per_second":	943812754.74532223,
				"retransmits":	0,
				"omitted":	false,
				"sender":	true
			}
		}, {
			"streams":	[{
					"socket":	6,
					"start":	7.600151,
					"end":	7.700171,
					"seconds":	0.10001999884843826,
					"bytes":	11796480,
					"bits_per_second":	943529704.924342,
					"retransmits":	0,
					"snd_cwnd":	7722184,
					"snd_wnd":	8355840,
					"rtt":	66033,
					"rttvar":	31,
					"pmtu":	1500,
					"omitted":	false,
					"sender":	true
				}],
			"sum":	{
				"start":	7.600151,
				"end":	7.700171,
				"seconds":	0.10001999884843826,
				"bytes":	11796480,
				"bits_per_second":	943529704.924342,
				"retransmits":	0,
				"omitted":	false,
				"sender":	true
			}
		}, {
			"streams":	[{
					"socket":	6,
					"start":	7.700171,
					"end":	7.80013,
					"seconds":	0.099959000945091248,
					"bytes":	11796480,
					"bits_per_second":	944105474.3218137,
					"retransmits":	0,
					"snd_cwnd":	7746800,
					"snd_wnd":	8355840,
					"rtt":	65948,
					"rttvar":	12,
					"pmtu":	1500,
					"omitted":	false,
					"sender":	true
				}],
			"sum":	{
				"start":	7.700171,
				"end":	7.80013,
				"seconds":	0.099959000945091248,
				"bytes":	11796480,
				"bits_per_second":	944105474.3218137,
				"retransmits":	0,
				"omitted":	false,
				"sender":	true
			}
		}, {
			"streams":	[{
					"socket":	6,
					"start":	7.80013,
					"end":	7.900129,
					"seconds":	0.099999003112316132,
					"bytes":	11796480,
					"bits_per_second":	943727807.90628624,
					"retransmits":	0,
					"snd_cwnd":	7772864,
					"snd_wnd":	8355840,
					"rtt":	66484,
					"rttvar":	120,
					"pmtu":	1500,
					"omitted":	false,
					"sender":	true
				}],
			"sum":	{
				"start":	7.80013,
				"end":	7.900129,
				"seconds":	0.099999003112316132,
				"bytes":	11796480,
				"bits_per_second":	943727807.90628624,
				"retransmits":	0,
				"omitted":	false,
				"sender":	true
			}
		}, {
			"streams":	[{
					"socket":	6,
					"start":	7.900129,
					"end":	8.000132,
					"seconds":	0.10000299662351608,
					"bytes":	11796480,
					"bits_per_second":	943690121.15991032,
					"retransmits":	0,
					"snd_cwnd":	7797480,
					"snd_wnd":	8355840,
					"rtt":	66500,
					"rttvar":	35,
					"pmtu":	1500,
					"omitted":	false,
					"sender":	true
				}],
			"sum":	{
				"start":	7.900129,
				"end":	8.000132,
				"seconds":	0.10000299662351608,
				"bytes":	11796480,
				"bits_per_second":	943690121.15991032,
				"retransmits":	0,
				"omitted":	false,
				"sender":	true
			}
		}, {
			"streams":	[{
					"socket":	6,
					"start":	8.000132,
					"end":	8.100128,
					"seconds":	0.099996000528335571,
					"bytes":	11796480,
					"bits_per_second":	943756145.259611,
					"retransmits":	0,
					"snd_cwnd":	7820648,
					"snd_wnd":	8355840,
					"rtt":	66672,
					"rttvar":	21,
					"pmtu":	1500,
					"omitted":	false,
					"sender":	true
				}],
			"sum":	{
				"start":	8.000132,
				"end":	8.100128,
				"seconds":	0.099996000528335571,
				"bytes":	11796480,
				"bits_per_second":	943756145.259611,
				"retransmits":	0,
				"omitted":	false,
				"sender":	true
			}
		}, {
			"streams":	[{
					"socket":	6,
					"start":	8.100128,
					"end":	8.200122,
					"seconds":	0.099993996322155,
					"bytes":	11796480,
					"bits_per_second":	943775061.21425676,
					"retransmits":	0,
					"snd_cwnd":	7845264,
					"snd_wnd":	8355840,
					"rtt":	67011,
					"rttvar":	35,
					"pmtu":	1500,
					"omitted":	false,
					"sender":	true
				}],
			"sum":	{
				"start":	8.100128,
				"end":	8.200122,
				"seconds":	0.099993996322155,
				"bytes":	11796480,
				"bits_per_second":	943775061.21425676,
				"retransmits":	0,
				"omitted":	false,
				"sender":	true
			}
		}, {
			"streams":	[{
					"socket":	6,
					"start":	8.200122,
					"end":	8.300139,
					"seconds":	0.1000170037150383,
					"bytes":	10485760,
					"bits_per_second":	838718186.7495507,
					"retransmits":	0,
					"snd_cwnd":	7868432,
					"snd_wnd":	8355840,
					"rtt":	67059,
					"rttvar":	25,
					"pmtu":	1500,
					"omitted":	false,
					"sender":	true
				}],
			"sum":	{
				"start":	8.200122,
				"end":	8.300139,
				"seconds":	0.1000170037150383,
				"bytes":	10485760,
				"bits_per_second":	838718186.7495507,
				"retransmits":	0,
				"omitted":	false,
				"sender":	true
			}
		}, {
			"streams":	[{
					"socket":	6,
					"start":	8.300139,
					"end":	8.40013,
					"seconds":	0.099991001188755035,
					"bytes":	11796480,
					"bits_per_second":	943803331.08028758,
					"retransmits":	0,
					"snd_cwnd":	7891600,
					"snd_wnd":	8355840,
					"rtt":	67030,
					"rttvar":	22,
					"pmtu":	1500,
					"omitted":	false,
					"sender":	true
				}],
			"sum":	{
				"start":	8.300139,
				"end":	8.40013,
				"seconds":	0.099991001188755035,
				"bytes":	11796480,
				"bits_per_second":	943803331.08028758,
				"retransmits":	0,
				"omitted":	false,
				"sender":	true
			}
		}, {
			"streams":	[{
					"socket":	6,
					"start":	8.40013,
					"end":	8.500125,
					"seconds":	0.0999950021505356,
					"bytes":	11796480,
					"bits_per_second":	943765567.9823848,
					"retransmits":	0,
					"snd_cwnd":	7914768,
					"snd_wnd":	8355840,
					"rtt":	67553,
					"rttvar":	47,
					"pmtu":	1500,
					"omitted":	false,
					"sender":	true
				}],
			"sum":	{
				"start":	8.40013,
				"end":	8.500125,
				"seconds":	0.0999950021505356,
				"bytes":	11796480,
				"bits_per_second":	943765567.9823848,
				"retransmits":	0,
				"omitted":	false,
				"sender":	true
			}
		}, {
			"streams":	[{
					"socket":	6,
					"start":	8.500125,
					"end":	8.600116,
					"seconds":	0.099991001188755035,
					"bytes":	11796480,
					"bits_per_second":	943803331.08028758,
					"retransmits":	0,
					"snd_cwnd":	7936488,
					"snd_wnd":	8355840,
					"rtt":	67499,
					"rttvar":	36,
					"pmtu":	1500,
					"omitted":	false,
					"sender":	true
				}],
			"sum":	{
				"start":	8.500125,
				"end":	8.600116,
				"seconds":	0.099991001188755035,
				"bytes":	11796480,
				"bits_per_second":	943803331.08028758,
				"retransmits":	0,
				"omitted":	false,
				"sender":	true
			}
		}, {
			"streams":	[{
					"socket":	6,
					"start":	8.600116,
					"end":	8.70013,
					"seconds":	0.10001400113105774,
					"bytes":	11796480,
					"bits_per_second":	943586287.24727964,
					"retransmits":	0,
					"snd_cwnd":	7958208,
					"snd_wnd":	8355840,
					"rtt":	67738,
					"rttvar":	35,
					"pmtu":	1500,
					"omitted":	false,
					"sender":	true
				}],
			"sum":	{
				"start":	8.600116,
				"end":	8.70013,
				"seconds":	0.10001400113105774,
				"bytes":	11796480,
				"bits_per_second":	943586287.24727964,
				"retransmits":	0,
				"omitted":	false,
				"sender":	true
			}
		}, {
			"streams":	[{
					"socket":	6,
					"start":	8.70013,
					"end":	8.800137,
					"seconds":	0.10000699758529663,
					"bytes":	11796480,
					"bits_per_second":	943652367.120707,
					"retransmits":	0,
					"snd_cwnd":	7979928,
					"snd_wnd":	8355840,
					"rtt":	68453,
					"rttvar":	40,
					"pmtu":	1500,
					"omitted":	false,
					"sender":	true
				}],
			"sum":	{
				"start":	8.70013,
				"end":	8.800137,
				"seconds":	0.10000699758529663,
				"bytes":	11796480,
				"bits_per_second":	943652367.120707,
				"retransmits":	0,
				"omitted":	false,
				"sender":	true
			}
		}, {
			"streams":	[{
					"socket":	6,
					"start":	8.800137,
					"end":	8.900141,
					"seconds":	0.10000400245189667,
					"bytes":	11796480,
					"bits_per_second":	943680629.63674057,
					"retransmits":	0,
					"snd_cwnd":	8001648,
					"snd_wnd":	8355840,
					"rtt":	68167,
					"rttvar":	33,
					"pmtu":	1500,
					"omitted":	false,
					"sender":	true
				}],
			"sum":	{
				"start":	8.800137,
				"end":	8.900141,
				"seconds":	0.10000400245189667,
				"bytes":	11796480,
				"bits_per_second":	943680629.63674057,
				"retransmits":	0,
				"omitted":	false,
				"sender":	true
			}
		}, {
			"streams":	[{
					"socket":	6,
					"start":	8.900141,
					"end":	9.00014,
					"seconds":	0.099999003112316132,
					"bytes":	11796480,
					"bits_per_second":	943727807.90628624,
					"retransmits":	0,
					"snd_cwnd":	8021920,
					"snd_wnd":	8355840,
					"rtt":	68111,
					"rttvar":	15,
					"pmtu":	1500,
					"omitted":	false,
					"sender":	true
				}],
			"sum":	{
				"start":	8.900141,
				"end":	9.00014,
				"seconds":	0.099999003112316132,
				"bytes":	11796480,
				"bits_per_second":	943727807.90628624,
				"retransmits":	0,
				"omitted":	false,
				"sender":	true
			}
		}, {
			"streams":	[{
					"socket":	6,
					"start":	9.00014,
					"end":	9.100109,
					"seconds":	0.0999689996242523,
					"bytes":	11796480,
					"bits_per_second":	944011046.971661,
					"retransmits":	0,
					"snd_cwnd":	8042192,
					"snd_wnd":	8355840,
					"rtt":	68756,
					"rttvar":	51,
					"pmtu":	1500,
					"omitted":	false,
					"sender":	true
				}],
			"sum":	{
				"start":	9.00014,
				"end":	9.100109,
				"seconds":	0.0999689996242523,
				"bytes":	11796480,
				"bits_per_second":	944011046.971661,
				"retransmits":	0,
				"omitted":	false,
				"sender":	true
			}
		}, {
			"streams":	[{
					"socket":	6,
					"start":	9.100109,
					"end":	9.200351,
					"seconds":	0.10024199634790421,
					"bytes":	11796480,
					"bits_per_second":	941440149.2211808,
					"retransmits":	0,
					"snd_cwnd":	8062464,
					"snd_wnd":	8355840,
					"rtt":	68823,
					"rttvar":	19,
					"pmtu":	1500,
					"omitted":	false,
					"sender":	true
				}],
			"sum":	{
				"start":	9.100109,
				"end":	9.200351,
				"seconds":	0.10024199634790421,
				"bytes":	11796480,
				"bits_per_second":	941440149.2211808,
				"retransmits":	0,
				"omitted":	false,
				"sender":	true
			}
		}, {
			"streams":	[{
					"socket":	6,
					"start":	9.200351,
					"end":	9.300148,
					"seconds":	0.099797002971172333,
					"bytes":	10485760,
					"bits_per_second":	840567126.29167426,
					"retransmits":	0,
					"snd_cwnd":	8082736,
					"snd_wnd":	8355840,
					"rtt":	68778,
					"rttvar":	21,
					"pmtu":	1500,
					"omitted":	false,
					"sender":	true
				}],
			"sum":	{
				"start":	9.200351,
				"end":	9.300148,
				"seconds":	0.099797002971172333,
				"bytes":	10485760,
				"bits_per_second":	840567126.29167426,
				"retransmits":	0,
				"omitted":	false,
				"sender":	true
			}
		}, {
			"streams":	[{
					"socket":	6,
					"start":	9.300148,
					"end":	9.400145,
					"seconds":	0.099996998906135559,
					"bytes":	11796480,
					"bits_per_second":	943746722.72499156,
					"retransmits":	0,
					"snd_cwnd":	8101560,
					"snd_wnd":	8355840,
					"rtt":	69325,
					"rttvar":	31,
					"pmtu":	1500,
					"omitted":	false,
					"sender":	true
				}],
			"sum":	{
				"start":	9.300148,
				"end":	9.400145,
				"seconds":	0.099996998906135559,
				"bytes":	11796480,
				"bits_per_second":	943746722.72499156,
				"retransmits":	0,
				"omitted":	false,
				"sender":	true
			}
		}, {
			"streams":	[{
					"socket":	6,
					"start":	9.400145,
					"end":	9.500116,
					"seconds":	0.0999709963798523,
					"bytes":	11796480,
					"bits_per_second":	943992191.90956545,
					"retransmits":	0,
					"snd_cwnd":	8120384,
					"snd_wnd":	8355840,
					"rtt":	69500,
					"rttvar":	27,
					"pmtu":	1500,
					"omitted":	false,
					"sender":	true
				}],
			"sum":	{
				"start":	9.400145,
				"end":	9.500116,
				"seconds":	0.0999709963798523,
				"bytes":	11796480,
				"bits_per_second":	943992191.90956545,
				"retransmits":	0,
				"omitted":	false,
				"sender":	true
			}
		}, {
			"streams":	[{
					"socket":	6,
					"start":	9.500116,
					"end":	9.60013,
					"seconds":	0.10001400113105774,
					"bytes":	11796480,
					"bits_per_second":	943586287.24727964,
					"retransmits":	0,
					"snd_cwnd":	8139208,
					"snd_wnd":	8355840,
					"rtt":	68893,
					"rttvar":	10,
					"pmtu":	1500,
					"omitted":	false,
					"sender":	true
				}],
			"sum":	{
				"start":	9.500116,
				"end":	9.60013,
				"seconds":	0.10001400113105774,
				"bytes":	11796480,
				"bits_per_second":	943586287.24727964,
				"retransmits":	0,
				"omitted":	false,
				"sender":	true
			}
		}, {
			"streams":	[{
					"socket":	6,
					"start":	9.60013,
					"end":	9.700067,
					"seconds":	0.099936999380588531,
					"bytes":	11796480,
					"bits_per_second":	944313323.242828,
					"retransmits":	0,
					"snd_cwnd":	8156584,
					"snd_wnd":	8355840,
					"rtt":	69287,
					"rttvar":	294,
					"pmtu":	1500,
					"omitted":	false,
					"sender":	true
				}],
			"sum":	{
				"start":	9.60013,
				"end":	9.700067,
				"seconds":	0.099936999380588531,
				"bytes":	11796480,
				"bits_per_second":	944313323.242828,
				"retransmits":	0,
				"omitted":	false,
				"sender":	true
			}
		}, {
			"streams":	[{
					"socket":	6,
					"start":	9.700067,
					"end":	9.800107,
					"seconds":	0.100040003657341,
					"bytes":	11796480,
					"bits_per_second":	943341029.087167,
					"retransmits":	0,
					"snd_cwnd":	8175408,
					"snd_wnd":	8355840,
					"rtt":	69974,
					"rttvar":	41,
					"pmtu":	1500,
					"omitted":	false,
					"sender":	true
				}],
			"sum":	{
				"start":	9.700067,
				"end":	9.800107,
				"seconds":	0.100040003657341,
				"bytes":	11796480,
				"bits_per_second":	943341029.087167,
				"retransmits":	0,
				"omitted":	false,
				"sender":	true
			}
		}, {
			"streams":	[{
					"socket":	6,
					"start":	9.800107,
					"end":	9.900104,
					"seconds":	0.099996998906135559,
					"bytes":	11796480,
					"bits_per_second":	943746722.72499156,
					"retransmits":	0,
					"snd_cwnd":	8192784,
					"snd_wnd":	8355840,
					"rtt":	69920,
					"rttvar":	49,
					"pmtu":	1500,
					"omitted":	false,
					"sender":	true
				}],
			"sum":	{
				"start":	9.800107,
				"end":	9.900104,
				"seconds":	0.099996998906135559,
				"bytes":	11796480,
				"bits_per_second":	943746722.72499156,
				"retransmits":	0,
				"omitted":	false,
				"sender":	true
			}
		}, {
			"streams":	[{
					"socket":	6,
					"start":	9.900104,
					"end":	10.000099,
					"seconds":	0.0999950021505356,
					"bytes":	11796480,
					"bits_per_second":	943765567.9823848,
					"retransmits":	0,
					"snd_cwnd":	8210160,
					"snd_wnd":	8355840,
					"rtt":	69693,
					"rttvar":	24,
					"pmtu":	1500,
					"omitted":	false,
					"sender":	true
				}],
			"sum":	{
				"start":	9.900104,
				"end":	10.000099,
				"seconds":	0.0999950021505356,
				"bytes":	11796480,
				"bits_per_second":	943765567.9823848,
				"retransmits":	0,
				"omitted":	false,
				"sender":	true
			}
		}, {
			"streams":	[{
					"socket":	6,
					"start":	10.000099,
					"end":	10.100114,
					"seconds":	0.10001499950885773,
					"bytes":	11796480,
					"bits_per_second":	943576868.10408926,
					"retransmits":	0,
					"snd_cwnd":	8226088,
					"snd_wnd":	8355840,
					"rtt":	70549,
					"rttvar":	20,
					"pmtu":	1500,
					"omitted":	false,
					"sender":	true
				}],
			"sum":	{
				"start":	10.000099,
				"end":	10.100114,
				"seconds":	0.10001499950885773,
				"bytes":	11796480,
				"bits_per_second":	943576868.10408926,
				"retransmits":	0,
				"omitted":	false,
				"sender":	true
			}
		}, {
			"streams":	[{
					"socket":	6,
					"start":	10.100114,
					"end":	10.200237,
					"seconds":	0.10012300312519073,
					"bytes":	11796480,
					"bits_per_second":	942559022.94501042,
					"retransmits":	0,
					"snd_cwnd":	8243464,
					"snd_wnd":	8355840,
					"rtt":	70221,
					"rttvar":	32,
					"pmtu":	1500,
					"omitted":	false,
					"sender":	true
				}],
			"sum":	{
				"start":	10.100114,
				"end":	10.200237,
				"seconds":	0.10012300312519073,
				"bytes":	11796480,
				"bits_per_second":	942559022.94501042,
				"retransmits":	0,
				"omitted":	false,
				"sender":	true
			}
		}, {
			"streams":	[{
					"socket":	6,
					"start":	10.200237,
					"end":	10.300131,
					"seconds":	0.0998940020799637,
					"bytes":	10485760,
					"bits_per_second":	839750918.50710344,
					"retransmits":	0,
					"snd_cwnd":	8259392,
					"snd_wnd":	8355840,
					"rtt":	70372,
					"rttvar":	70,
					"pmtu":	1500,
					"omitted":	false,
					"sender":	true
				}],
			"sum":	{
				"start":	10.200237,
				"end":	10.300131,
				"seconds":	0.0998940020799637,
				"bytes":	10485760,
				"bits_per_second":	839750918.50710344,
				"retransmits":	0,
				"omitted":	false,
				"sender":	true
			}
		}, {
			"streams":	[{
					"socket":	6,
					"start":	10.300131,
					"end":	10.400106,
					"seconds":	0.099974997341632843,
					"bytes":	11796480,
					"bits_per_second":	943954413.69719839,
					"retransmits":	0,
					"snd_cwnd":	8275320,
					"snd_wnd":	8355840,
					"rtt":	70189,
					"rttvar":	15,
					"pmtu":	1500,
					"omitted":	false,
					"sender":	true
				}],
			"sum":	{
				"start":	10.300131,
				"end":	10.400106,
				"seconds":	0.099974997341632843,
				"bytes":	11796480,
				"bits_per_second":	943954413.69719839,
				"retransmits":	0,
				"omitted":	false,
				"sender":	true
			}
		}, {
			"streams":	[{
					"socket":	6,
					"start":	10.400106,
					"end":	10.500074,
					"seconds":	0.099968001246452332,
					"bytes":	11796480,
					"bits_per_second":	944020474.785166,
					"retransmits":	0,
					"snd_cwnd":	8289800,
					"snd_wnd":	8355840,
					"rtt":	70631,
					"rttvar":	24,
					"pmtu":	1500,
					"omitted":	false,
					"sender":	true
				}],
			"sum":	{
				"start":	10.400106,
				"end":	10.500074,
				"seconds":	0.099968001246452332,
				"bytes":	11796480,
				"bits_per_second":	944020474.785166,
				"retransmits":	0,
				"omitted":	false,
				"sender":	true
			}
		}, {
			"streams":	[{
					"socket":	6,
					"start":	10.500074,
					"end":	10.600099,
					"seconds":	0.1000249981880188,
					"bytes":	11796480,
					"bits_per_second":	943482546.45911157,
					"retransmits":	0,
					"snd_cwnd":	8305728,
					"snd_wnd":	8355840,
					"rtt":	70682,
					"rttvar":	43,
					"pmtu":	1500,
					"omitted":	false,
					"sender":	true
				}],
			"sum":	{
				"start":	10.500074,
				"end":	10.600099,
				"seconds":	0.1000249981880188,
				"bytes":	11796480,
				"bits_per_second":	943482546.45911157,
				"retransmits":	0,
				"omitted":	false,
				"sender":	true
			}
		}, {
			"streams":	[{
					"socket":	6,
					"start":	10.600099,
					"end":	10.700102,
					"seconds":	0.10000299662351608,
					"bytes":	11796480,
					"bits_per_second":	943690121.15991032,
					"retransmits":	0,
					"snd_cwnd":	8320208,
					"snd_wnd":	8355840,
					"rtt":	70751,
					"rttvar":	17,
					"pmtu":	1500,
					"omitted":	false,
					"sender":	true
				}],
			"sum":	{
				"start":	10.600099,
				"end":	10.700102,
				"seconds":	0.10000299662351608,
				"bytes":	11796480,
				"bits_per_second":	943690121.15991032,
				"retransmits":	0,
				"omitted":	false,
				"sender":	true
			}
		}, {
			"streams":	[{
					"socket":	6,
					"start":	10.700102,
					"end":	10.800101,
					"seconds":	0.099999003112316132,
					"bytes":	11796480,
					"bits_per_second":	943727807.90628624,
					"retransmits":	0,
					"snd_cwnd":	8334688,
					"snd_wnd":	8355840,
					"rtt":	70909,
					"rttvar":	30,
					"pmtu":	1500,
					"omitted":	false,
					"sender":	true
				}],
			"sum":	{
				"start":	10.700102,
				"end":	10.800101,
				"seconds":	0.099999003112316132,
				"bytes":	11796480,
				"bits_per_second":	943727807.90628624,
				"retransmits":	0,
				"omitted":	false,
				"sender":	true
			}
		}, {
			"streams":	[{
					"socket":	6,
					"start":	10.800101,
					"end":	10.900101,
					"seconds":	0.10000000149011612,
					"bytes":	11796480,
					"bits_per_second":	943718385.93750024,
					"retransmits":	0,
					"snd_cwnd":	8349168,
					"snd_wnd":	8355840,
					"rtt":	70786,
					"rttvar":	20,
					"pmtu":	1500,
					"omitted":	false,
					"sender":	true
				}],
			"sum":	{
				"start":	10.800101,
				"end":	10.900101,
				"seconds":	0.10000000149011612,
				"bytes":	11796480,
				"bits_per_second":	943718385.93750024,
				"retransmits":	0,
				"omitted":	false,
				"sender":	true
			}
		}, {
			"streams":	[{
					"socket":	6,
					"start":	10.900101,
					"end":	11.0001,
					"seconds":	0.099999003112316132,
					"bytes":	11796480,
					"bits_per_second":	943727807.90628624,
					"retransmits":	0,
					"snd_cwnd":	8363648,
					"snd_wnd":	8355840,
					"rtt":	71342,
					"rttvar":	26,
					"pmtu":	1500,
					"omitted":	false,
					"sender":	true
				}],
			"sum":	{
				"start":	10.900101,
				"end":	11.0001,
				"seconds":	0.099999003112316132,
				"bytes":	11796480,
				"bits_per_second":	943727807.90628624,
				"retransmits":	0,
				"omitted":	false,
				"sender":	true
			}
		}, {
			"streams":	[{
					"socket":	6,
					"start":	11.0001,
					"end":	11.100098,
					"seconds":	0.099997997283935547,
					"bytes":	11796480,
					"bits_per_second":	943737300.378521,
					"retransmits":	0,
					"snd_cwnd":	8365096,
					"snd_wnd":	8355840,
					"rtt":	71195,
					"rttvar":	75,
					"pmtu":	1500,
					"omitted":	false,
					"sender":	true
				}],
			"sum":	{
				"start":	11.0001,
				"end":	11.100098,
				"seconds":	0.099997997283935547,
				"bytes":	11796480,
				"bits_per_second":	943737300.378521,
				"retransmits":	0,
				"omitted":	false,
				"sender":	true
			}
		}, {
			"streams":	[{
					"socket":	6,
					"start":	11.100098,
					"end":	11.200115,
					"seconds":	0.1000170037150383,
					"bytes":	11796480,
					"bits_per_second":	943557960.09324455,
					"retransmits":	0,
					"snd_cwnd":	8365096,
					"snd_wnd":	8355840,
					"rtt":	71340,
					"rttvar":	49,
					"pmtu":	1500,
					"omitted":	false,
					"sender":	true
				}],
			"sum":	{
				"start":	11.100098,
				"end":	11.200115,
				"seconds":	0.1000170037150383,
				"bytes":	11796480,
				"bits_per_second":	943557960.09324455,
				"retransmits":	0,
				"omitted":	false,
				"sender":	true
			}
		}, {
			"streams":	[{
					"socket":	6,
					"start":	11.200115,
					"end":	11.300125,
					"seconds":	0.10001000016927719,
					"bytes":	11796480,
					"bits_per_second":	943624035.9990598,
					"retransmits":	0,
					"snd_cwnd":	8365096,
					"snd_wnd":	8355840,
					"rtt":	71173,
					"rttvar":	22,
					"pmtu":	1500,
					"omitted":	false,
					"sender":	true
				}],
			"sum":	{
				"start":	11.200115,
				"end":	11.300125,
				"seconds":	0.10001000016927719,
				"bytes":	11796480,
				"bits_per_second":	943624035.9990598,
				"retransmits":	0,
				"omitted":	false,
				"sender":	true
			}
		}, {
			"streams":	[{
					"socket":	6,
					"start":	11.300125,
					"end":	11.4001,
					"seconds":	0.099974997341632843,
					"bytes":	11796480,
					"bits_per_second":	943954413.69719839,
					"retransmits":	0,
					"snd_cwnd":	8365096,
					"snd_wnd":	8355840,
					"rtt":	71445,
					"rttvar":	23,
					"pmtu":	1500,
					"omitted":	false,
					"sender":	true
				}],
			"sum":	{
				"start":	11.300125,
				"end":	11.4001,
				"seconds":	0.099974997341632843,
				"bytes":	11796480,
				"bits_per_second":	943954413.69719839,
				"retransmits":	0,
				"omitted":	false,
				"sender":	true
			}
		}, {
			"streams":	[{
					"socket":	6,
					"start":	11.4001,
					"end":	11.500095,
					"seconds":	0.0999950021505356,
					"bytes":	11796480,
					"bits_per_second":	943765567.9823848,
					"retransmits":	0,
					"snd_cwnd":	8365096,
					"snd_wnd":	8355840,
					"rtt":	70981,
					"rttvar":	28,
					"pmtu":	1500,
					"omitted":	false,
					"sender":	true
				}],
			"sum":	{
				"start":	11.4001,
				"end":	11.500095,
				"seconds":	0.0999950021505356,
				"bytes":	11796480,
				"bits_per_second":	943765567.9823848,
				"retransmits":	0,
				"omitted":	false,
				"sender":	true
			}
		}, {
			"streams":	[{
					"socket":	6,
					"start":	11.500095,
					"end":	11.600099,
					"seconds":	0.10000400245189667,
					"bytes":	11796480,
					"bits_per_second":	943680629.63674057,
					"retransmits":	0,
					"snd_cwnd":	8365096,
					"snd_wnd":	8355840,
					"rtt":	70789,
					"rttvar":	19,
					"pmtu":	1500,
					"omitted":	false,
					"sender":	true
				}],
			"sum":	{
				"start":	11.500095,
				"end":	11.600099,
				"seconds":	0.10000400245189667,
				"bytes":	11796480,
				"bits_per_second":	943680629.63674057,
				"retransmits":	0,
				"omitted":	false,
				"sender":	true
			}
		}, {
			"streams":	[{
					"socket":	6,
					"start":	11.600099,
					"end":	11.700428,
					"seconds":	0.10032899677753448,
					"bytes":	11796480,
					"bits_per_second":	940623778.081389,
					"retransmits":	0,
					"snd_cwnd":	8365096,
					"snd_wnd":	8355840,
					"rtt":	70902,
					"rttvar":	10,
					"pmtu":	1500,
					"omitted":	false,
					"sender":	true
				}],
			"sum":	{
				"start":	11.600099,
				"end":	11.700428,
				"seconds":	0.10032899677753448,
				"bytes":	11796480,
				"bits_per_second":	940623778.081389,
				"retransmits":	0,
				"omitted":	false,
				"sender":	true
			}
		}, {
			"streams":	[{
					"socket":	6,
					"start":	11.700428,
					"end":	11.800135,
					"seconds":	0.0997069999575615,
					"bytes":	10485760,
					"bits_per_second":	841325885.20068419,
					"retransmits":	0,
					"snd_cwnd":	8365096,
					"snd_wnd":	8355840,
					"rtt":	71171,
					"rttvar":	19,
					"pmtu":	1500,
					"omitted":	false,
					"sender":	true
				}],
			"sum":	{
				"start":	11.700428,
				"end":	11.800135,
				"seconds":	0.0997069999575615,
				"bytes":	10485760,
				"bits_per_second":	841325885.20068419,
				"retransmits":	0,
				"omitted":	false,
				"sender":	true
			}
		}, {
			"streams":	[{
					"socket":	6,
					"start":	11.800135,
					"end":	11.900129,
					"seconds":	0.099993996322155,
					"bytes":	11796480,
					"bits_per_second":	943775061.21425676,
					"retransmits":	0,
					"snd_cwnd":	8365096,
					"snd_wnd":	8355840,
					"rtt":	71269,
					"rttvar":	25,
					"pmtu":	1500,
					"omitted":	false,
					"sender":	true
				}],
			"sum":	{
				"start":	11.800135,
				"end":	11.900129,
				"seconds":	0.099993996322155,
				"bytes":	11796480,
				"bits_per_second":	943775061.21425676,
				"retransmits":	0,
				"omitted":	false,
				"sender":	true
			}
		}, {
			"streams":	[{
					"socket":	6,
					"start":	11.900129,
					"end":	12.000129,
					"seconds":	0.10000000149011612,
					"bytes":	11796480,
					"bits_per_second":	943718385.93750024,
					"retransmits":	0,
					"snd_cwnd":	8365096,
					"snd_wnd":	8355840,
					"rtt":	71738,
					"rttvar":	43,
					"pmtu":	1500,
					"omitted":	false,
					"sender":	true
				}],
			"sum":	{
				"start":	11.900129,
				"end":	12.000129,
				"seconds":	0.10000000149011612,
				"bytes":	11796480,
				"bits_per_second":	943718385.93750024,
				"retransmits":	0,
				"omitted":	false,
				"sender":	true
			}
		}, {
			"streams":	[{
					"socket":	6,
					"start":	12.000129,
					"end":	12.100184,
					"seconds":	0.10005500167608261,
					"bytes":	11796480,
					"bits_per_second":	943199624.39777637,
					"retransmits":	0,
					"snd_cwnd":	8365096,
					"snd_wnd":	8355840,
					"rtt":	70935,
					"rttvar":	29,
					"pmtu":	1500,
					"omitted":	false,
					"sender":	true
				}],
			"sum":	{
				"start":	12.000129,
				"end":	12.100184,
				"seconds":	0.10005500167608261,
				"bytes":	11796480,
				"bits_per_second":	943199624.39777637,
				"retransmits":	0,
				"omitted":	false,
				"sender":	true
			}
		}, {
			"streams":	[{
					"socket":	6,
					"start":	12.100184,
					"end":	12.200121,
					"seconds":	0.099936999380588531,
					"bytes":	11796480,
					"bits_per_second":	944313323.242828,
					"retransmits":	0,
					"snd_cwnd":	8365096,
					"snd_wnd":	8355840,
					"rtt":	71235,
					"rttvar":	33,
					"pmtu":	1500,
					"omitted":	false,
					"sender":	true
				}],
			"sum":	{
				"start":	12.100184,
				"end":	12.200121,
				"seconds":	0.099936999380588531,
				"bytes":	11796480,
				"bits_per_second":	944313323.242828,
				"retransmits":	0,
				"omitted":	false,
				"sender":	true
			}
		}, {
			"streams":	[{
					"socket":	6,
					"start":	12.200121,
					"end":	12.300123,
					"seconds":	0.10000199824571609,
					"bytes":	11796480,
					"bits_per_second":	943699542.564318,
					"retransmits":	0,
					"snd_cwnd":	8365096,
					"snd_wnd":	8355840,
					"rtt":	71104,
					"rttvar":	14,
					"pmtu":	1500,
					"omitted":	false,
					"sender":	true
				}],
			"sum":	{
				"start":	12.200121,
				"end":	12.300123,
				"seconds":	0.10000199824571609,
				"bytes":	11796480,
				"bits_per_second":	943699542.564318,
				"retransmits":	0,
				"omitted":	false,
				"sender":	true
			}
		}, {
			"streams":	[{
					"socket":	6,
					"start":	12.300123,
					"end":	12.400135,
					"seconds":	0.10001199692487717,
					"bytes":	11796480,
					"bits_per_second":	943605196.39345169,
					"retransmits":	0,
					"snd_cwnd":	8365096,
					"snd_wnd":	8355840,
					"rtt":	71098,
					"rttvar":	20,
					"pmtu":	1500,
					"omitted":	false,
					"sender":	true
				}],
			"sum":	{
				"start":	12.300123,
				"end":	12.400135,
				"seconds":	0.10001199692487717,
				"bytes":	11796480,
				"bits_per_second":	943605196.39345169,
				"retransmits":	0,
				"omitted":	false,
				"sender":	true
			}
		}, {
			"streams":	[{
					"socket":	6,
					"start":	12.400135,
					"end":	12.500114,
					"seconds":	0.0999789983034134,
					"bytes":	11796480,
					"bits_per_second":	943916638.50845,
					"retransmits":	0,
					"snd_cwnd":	8365096,
					"snd_wnd":	8355840,
					"rtt":	70997,
					"rttvar":	45,
					"pmtu":	1500,
					"omitted":	false,
					"sender":	true
				}],
			"sum":	{
				"start":	12.400135,
				"end":	12.500114,
				"seconds":	0.0999789983034134,
				"bytes":	11796480,
				"bits_per_second":	943916638.50845,
				"retransmits":	0,
				"omitted":	false,
				"sender":	true
			}
		}, {
			"streams":	[{
					"socket":	6,
					"start":	12.500114,
					"end":	12.600142,
					"seconds":	0.10002800077199936,
					"bytes":	11796480,
					"bits_per_second":	943454225.53339,
					"retransmits":	0,
					"snd_cwnd":	8365096,
					"snd_wnd":	8355840,
					"rtt":	71216,
					"rttvar":	12,
					"pmtu":	1500,
					"omitted":	false,
					"sender":	true
				}],
			"sum":	{
				"start":	12.500114,
				"end":	12.600142,
				"seconds":	0.10002800077199936,
				"bytes":	11796480,
				"bits_per_second":	943454225.53339,
				"retransmits":	0,
				"omitted":	false,
				"sender":	true
			}
		}, {
			"streams":	[{
					"socket":	6,
					"start":	12.600142,
					"end":	12.700105,
					"seconds":	0.0999630019068718,
					"bytes":	11796480,
					"bits_per_second":	944067687.042045,
					"retransmits":	0,
					"snd_cwnd":	8365096,
					"snd_wnd":	8355840,
					"rtt":	70746,
					"rttvar":	8,
					"pmtu":	1500,
					"omitted":	false,
					"sender":	true
				}],
			"sum":	{
				"start":	12.600142,
				"end":	12.700105,
				"seconds":	0.0999630019068718,
				"bytes":	11796480,
				"bits_per_second":	944067687.042045,
				"retransmits":	0,
				"omitted":	false,
				"sender":	true
			}
		}, {
			"streams":	[{
					"socket":	6,
					"start":	12.700105,
					"end":	12.800136,
					"seconds":	0.10003100335597992,
					"bytes":	11796480,
					"bits_per_second":	943425906.30786061,
					"retransmits":	0,
					"snd_cwnd":	8365096,
					"snd_wnd":	8355840,
					"rtt":	70671,
					"rttvar":	5,
					"pmtu":	1500,
					"omitted":	false,
					"sender":	true
				}],
			"sum":	{
				"start":	12.700105,
				"end":	12.800136,
				"seconds":	0.10003100335597992,
				"bytes":	11796480,
				"bits_per_second":	943425906.30786061,
				"retransmits":	0,
				"omitted":	false,
				"sender":	true
			}
		}, {
			"streams":	[{
					"socket":	6,
					"start":	12.800136,
					"end":	12.900142,
					"seconds":	0.10000599920749664,
					"bytes":	11796480,
					"bits_per_second":	943661787.771285,
					"retransmits":	0,
					"snd_cwnd":	8365096,
					"snd_wnd":	8355840,
					"rtt":	70676,
					"rttvar":	15,
					"pmtu":	1500,
					"omitted":	false,
					"sender":	true
				}],
			"sum":	{
				"start":	12.800136,
				"end":	12.900142,
				"seconds":	0.10000599920749664,
				"bytes":	11796480,
				"bits_per_second":	943661787.771285,
				"retransmits":	0,
				"omitted":	false,
				"sender":	true
			}
		}, {
			"streams":	[{
					"socket":	6,
					"start":	12.900142,
					"end":	13.00012,
					"seconds":	0.0999779999256134,
					"bytes":	11796480,
					"bits_per_second":	943926064.43633044,
					"retransmits":	0,
					"snd_cwnd":	8365096,
					"snd_wnd":	8355840,
					"rtt":	70941,
					"rttvar":	13,
					"pmtu":	1500,
					"omitted":	false,
					"sender":	true
				}],
			"sum":	{
				"start":	12.900142,
				"end":	13.00012,
				"seconds":	0.0999779999256134,
				"bytes":	11796480,
				"bits_per_second":	943926064.43633044,
				"retransmits":	0,
				"omitted":	false,
				"sender":	true
			}
		}, {
			"streams":	[{
					"socket":	6,
					"start":	13.00012,
					"end":	13.100133,
					"seconds":	0.10001300275325775,
					"bytes":	11796480,
					"bits_per_second":	943595706.5785228,
					"retransmits":	0,
					"snd_cwnd":	8365096,
					"snd_wnd":	8355840,
					"rtt":	71506,
					"rttvar":	72,
					"pmtu":	1500,
					"omitted":	false,
					"sender":	true
				}],
			"sum":	{
				"start":	13.00012,
				"end":	13.100133,
				"seconds":	0.10001300275325775,
				"bytes":	11796480,
				"bits_per_second":	943595706.5785228,
				"retransmits":	0,
				"omitted":	false,
				"sender":	true
			}
		}, {
			"streams":	[{
					"socket":	6,
					"start":	13.100133,
					"end":	13.200144,
					"seconds":	0.10001099854707718,
					"bytes":	11796480,
					"bits_per_second":	943614616.102221,
					"retransmits":	0,
					"snd_cwnd":	8365096,
					"snd_wnd":	8355840,
					"rtt":	71619,
					"rttvar":	22,
					"pmtu":	1500,
					"omitted":	false,
					"sender":	true
				}],
			"sum":	{
				"start":	13.100133,
				"end":	13.200144,
				"seconds":	0.10001099854707718,
				"bytes":	11796480,
				"bits_per_second":	943614616.102221,
				"retransmits":	0,
				"omitted":	false,
				"sender":	true
			}
		}, {
			"streams":	[{
					"socket":	6,
					"start":	13.200144,
					"end":	13.300126,
					"seconds":	0.099982000887393951,
					"bytes":	11796480,
					"bits_per_second":	943888291.51646531,
					"retransmits":	0,
					"snd_cwnd":	8365096,
					"snd_wnd":	8355840,
					"rtt":	71603,
					"rttvar":	18,
					"pmtu":	1500,
					"omitted":	false,
					"sender":	true
				}],
			"sum":	{
				"start":	13.200144,
				"end":	13.300126,
				"seconds":	0.099982000887393951,
				"bytes":	11796480,
				"bits_per_second":	943888291.51646531,
				"retransmits":	0,
				"omitted":	false,
				"sender":	true
			}
		}, {
			"streams":	[{
					"socket":	6,
					"start":	13.300126,
					"end":	13.400105,
					"seconds":	0.0999789983034134,
					"bytes":	11796480,
					"bits_per_second":	943916638.50845,
					"retransmits":	0,
					"snd_cwnd":	8365096,
					"snd_wnd":	8355840,
					"rtt":	71574,
					"rttvar":	32,
					"pmtu":	1500,
					"omitted":	false,
					"sender":	true
				}],
			"sum":	{
				"start":	13.300126,
				"end":	13.400105,
				"seconds":	0.0999789983034134,
				"bytes":	11796480,
				"bits_per_second":	943916638.50845,
				"retransmits":	0,
				"omitted":	false,
				"sender":	true
			}
		}, {
			"streams":	[{
					"socket":	6,
					"start":	13.400105,
					"end":	13.500403,
					"seconds":	0.10029800236225128,
					"bytes":	11796480,
					"bits_per_second":	940914452.704178,
					"retransmits":	0,
					"snd_cwnd":	8365096,
					"snd_wnd":	8355840,
					"rtt":	71207,
					"rttvar":	12,
					"pmtu":	1500,
					"omitted":	false,
					"sender":	true
				}],
			"sum":	{
				"start":	13.400105,
				"end":	13.500403,
				"seconds":	0.10029800236225128,
				"bytes":	11796480,
				"bits_per_second":	940914452.704178,
				"retransmits":	0,
				"omitted":	false,
				"sender":	true
			}
		}, {
			"streams":	[{
					"socket":	6,
					"start":	13.500403,
					"end":	13.600138,
					"seconds":	0.099734999239444733,
					"bytes":	10485760,
					"bits_per_second":	841089694.08628058,
					"retransmits":	0,
					"snd_cwnd":	8365096,
					"snd_wnd":	8355840,
					"rtt":	71344,
					"rttvar":	19,
					"pmtu":	1500,
					"omitted":	false,
					"sender":	true
				}],
			"sum":	{
				"start":	13.500403,
				"end":	13.600138,
				"seconds":	0.099734999239444733,
				"bytes":	10485760,
				"bits_per_second":	841089694.08628058,
				"retransmits":	0,
				"omitted":	false,
				"sender":	true
			}
		}, {
			"streams":	[{
					"socket":	6,
					"start":	13.600138,
					"end":	13.700103,
					"seconds":	0.099964998662471771,
					"bytes":	11796480,
					"bits_per_second":	944048829.71732068,
					"retransmits":	0,
					"snd_cwnd":	8365096,
					"snd_wnd":	8355840,
					"rtt":	71543,
					"rttvar":	27,
					"pmtu":	1500,
					"omitted":	false,
					"sender":	true
				}],
			"sum":	{
				"start":	13.600138,
				"end":	13.700103,
				"seconds":	0.099964998662471771,
				"bytes":	11796480,
				"bits_per_second":	944048829.71732068,
				"retransmits":	0,
				"omitted":	false,
				"sender":	true
			}
		}, {
			"streams":	[{
					"socket":	6,
					"start":	13.700103,
					"end":	13.800121,
					"seconds":	0.10001800209283829,
					"bytes":	11796480,
					"bits_per_second":	943548541.515582,
					"retransmits":	0,
					"snd_cwnd":	8365096,
					"snd_wnd":	8355840,
					"rtt":	71385,
					"rttvar":	42,
					"pmtu":	1500,
					"omitted":	false,
					"sender":	true
				}],
			"sum":	{
				"start":	13.700103,
				"end":	13.800121,
				"seconds":	0.10001800209283829,
				"bytes":	11796480,
				"bits_per_second":	943548541.515582,
				"retransmits":	0,
				"omitted":	false,
				"sender":	true
			}
		}, {
			"streams":	[{
					"socket":	6,
					"start":	13.800121,
					"end":	13.900138,
					"seconds":	0.1000170037150383,
					"bytes":	11796480,
					"bits_per_second":	943557960.09324455,
					"retransmits":	0,
					"snd_cwnd":	8365096,
					"snd_wnd":	8355840,
					"rtt":	71595,
					"rttvar":	38,
					"pmtu":	1500,
					"omitted":	false,
					"sender":	true
				}],
			"sum":	{
				"start":	13.800121,
				"end":	13.900138,
				"seconds":	0.1000170037150383,
				"bytes":	11796480,
				"bits_per_second":	943557960.09324455,
				"retransmits":	0,
				"omitted":	false,
				"sender":	true
			}
		}, {
			"streams":	[{
					"socket":	6,
					"start":	13.900138,
					"end":	14.00013,
					"seconds":	0.099991999566555023,
					"bytes":	11796480,
					"bits_per_second":	943793907.60343552,
					"retransmits":	0,
					"snd_cwnd":	8365096,
					"snd_wnd":	8355840,
					"rtt":	71740,
					"rttvar":	23,
					"pmtu":	1500,
					"omitted":	false,
					"sender":	true
				}],
			"sum":	{
				"start":	13.900138,
				"end":	14.00013,
				"seconds":	0.099991999566555023,
				"bytes":	11796480,
				"bits_per_second":	943793907.60343552,
				"retransmits":	0,
				"omitted":	false,
				"sender":	true
			}
		}, {
			"streams":	[{
					"socket":	6,
					"start":	14.00013,
					"end":	14.100127,
					"seconds":	0.099996998906135559,
					"bytes":	11796480,
					"bits_per_second":	943746722.72499156,
					"retransmits":	0,
					"snd_cwnd":	8365096,
					"snd_wnd":	8355840,
					"rtt":	71348,
					"rttvar":	60,
					"pmtu":	1500,
					"omitted":	false,
					"sender":	true
				}],
			"sum":	{
				"start":	14.00013,
				"end":	14.100127,
				"seconds":	0.099996998906135559,
				"bytes":	11796480,
				"bits_per_second":	943746722.72499156,
				"retransmits":	0,
				"omitted":	false,
				"sender":	true
			}
		}, {
			"streams":	[{
					"socket":	6,
					"start":	14.100127,
					"end":	14.200123,
					"seconds":	0.099996000528335571,
					"bytes":	11796480,
					"bits_per_second":	943756145.259611,
					"retransmits":	0,
					"snd_cwnd":	8365096,
					"snd_wnd":	8355840,
					"rtt":	71664,
					"rttvar":	30,
					"pmtu":	1500,
					"omitted":	false,
					"sender":	true
				}],
			"sum":	{
				"start":	14.100127,
				"end":	14.200123,
				"seconds":	0.099996000528335571,
				"bytes":	11796480,
				"bits_per_second":	943756145.259611,
				"retransmits":	0,
				"omitted":	false,
				"sender":	true
			}
		}, {
			"streams":	[{
					"socket":	6,
					"start":	14.200123,
					"end":	14.300077,
					"seconds":	0.0999540016055107,
					"bytes":	11796480,
					"bits_per_second":	944152695.08126473,
					"retransmits":	0,
					"snd_cwnd":	8365096,
					"snd_wnd":	8355840,
					"rtt":	71527,
					"rttvar":	57,
					"pmtu":	1500,
					"omitted":	false,
					"sender":	true
				}],
			"sum":	{
				"start":	14.200123,
				"end":	14.300077,
				"seconds":	0.0999540016055107,
				"bytes":	11796480,
				"bits_per_second":	944152695.08126473,
				"retransmits":	0,
				"omitted":	false,
				"sender":	true
			}
		}, {
			"streams":	[{
					"socket":	6,
					"start":	14.300077,
					"end":	14.4001,
					"seconds":	0.10002300143241882,
					"bytes":	11796480,
					"bits_per_second":	943501381.16744,
					"retransmits":	0,
					"snd_cwnd":	8365096,
					"snd_wnd":	8355840,
					"rtt":	71202,
					"rttvar":	30,
					"pmtu":	1500,
					"omitted":	false,
					"sender":	true
				}],
			"sum":	{
				"start":	14.300077,
				"end":	14.4001,
				"seconds":	0.10002300143241882,
				"bytes":	11796480,
				"bits_per_second":	943501381.16744,
				"retransmits":	0,
				"omitted":	false,
				"sender":	true
			}
		}, {
			"streams":	[{
					"socket":	6,
					"start":	14.4001,
					"end":	14.500106,
					"seconds":	0.10000599920749664,
					"bytes":	11796480,
					"bits_per_second":	943661787.771285,
					"retransmits":	0,
					"snd_cwnd":	8365096,
					"snd_wnd":	8355840,
					"rtt":	71370,
					"rttvar":	16,
					"pmtu":	1500,
					"omitted":	false,
					"sender":	true
				}],
			"sum":	{
				"start":	14.4001,
				"end":	14.500106,
				"seconds":	0.10000599920749664,
				"bytes":	11796480,
				"bits_per_second":	943661787.771285,
				"retransmits":	0,
				"omitted":	false,
				"sender":	true
			}
		}, {
			"streams":	[{
					"socket":	6,
					"start":	14.500106,
					"end":	14.600117,
					"seconds":	0.10001099854707718,
					"bytes":	10485760,
					"bits_per_second":	838768547.64641857,
					"retransmits":	0,
					"snd_cwnd":	8365096,
					"snd_wnd":	8355840,
					"rtt":	71454,
					"rttvar":	11,
					"pmtu":	1500,
					"omitted":	false,
					"sender":	true
				}],
			"sum":	{
				"start":	14.500106,
				"end":	14.600117,
				"seconds":	0.10001099854707718,
				"bytes":	10485760,
				"bits_per_second":	838768547.64641857,
				"retransmits":	0,
				"omitted":	false,
				"sender":	true
			}
		}, {
			"streams":	[{
					"socket":	6,
					"start":	14.600117,
					"end":	14.700112,
					"seconds":	0.0999950021505356,
					"bytes":	11796480,
					"bits_per_second":	943765567.9823848,
					"retransmits":	0,
					"snd_cwnd":	8365096,
					"snd_wnd":	8355840,
					"rtt":	71543,
					"rttvar":	36,
					"pmtu":	1500,
					"omitted":	false,
					"sender":	true
				}],
			"sum":	{
				"start":	14.600117,
				"end":	14.700112,
				"seconds":	0.0999950021505356,
				"bytes":	11796480,
				"bits_per_second":	943765567.9823848,
				"retransmits":	0,
				"omitted":	false,
				"sender":	true
			}
		}, {
			"streams":	[{
					"socket":	6,
					"start":	14.700112,
					"end":	14.800113,
					"seconds":	0.10000099986791611,
					"bytes":	11796480,
					"bits_per_second":	943708964.156846,
					"retransmits":	0,
					"snd_cwnd":	8365096,
					"snd_wnd":	8355840,
					"rtt":	71557,
					"rttvar":	16,
					"pmtu":	1500,
					"omitted":	false,
					"sender":	true
				}],
			"sum":	{
				"start":	14.700112,
				"end":	14.800113,
				"seconds":	0.10000099986791611,
				"bytes":	11796480,
				"bits_per_second":	943708964.156846,
				"retransmits":	0,
				"omitted":	false,
				"sender":	true
			}
		}, {
			"streams":	[{
					"socket":	6,
					"start":	14.800113,
					"end":	14.900106,
					"seconds":	0.099992997944355,
					"bytes":	11796480,
					"bits_per_second":	943784484.31476045,
					"retransmits":	0,
					"snd_cwnd":	8365096,
					"snd_wnd":	8355840,
					"rtt":	71443,
					"rttvar":	21,
					"pmtu":	1500,
					"omitted":	false,
					"sender":	true
				}],
			"sum":	{
				"start":	14.800113,
				"end":	14.900106,
				"seconds":	0.099992997944355,
				"bytes":	11796480,
				"bits_per_second":	943784484.31476045,
				"retransmits":	0,
				"omitted":	false,
				"sender":	true
			}
		}, {
			"streams":	[{
					"socket":	6,
					"start":	14.900106,
					"end":	15.000131,
					"seconds":	0.1000249981880188,
					"bytes":	11796480,
					"bits_per_second":	943482546.45911157,
					"retransmits":	0,
					"snd_cwnd":	8365096,
					"snd_wnd":	8355840,
					"rtt":	71633,
					"rttvar":	64,
					"pmtu":	1500,
					"omitted":	false,
					"sender":	true
				}],
			"sum":	{
				"start":	14.900106,
				"end":	15.000131,
				"seconds":	0.1000249981880188,
				"bytes":	11796480,
				"bits_per_second":	943482546.45911157,
				"retransmits":	0,
				"omitted":	false,
				"sender":	true
			}
		}],
	"end":	{
		"streams":	[{
				"sender":	{
					"socket":	6,
					"start":	0,
					"end":	15.000131,
					"seconds":	15.000131,
					"bytes":	1684537344,
					"bits_per_second":	898412070.667916,
					"retransmits":	700,
					"max_snd_cwnd":	8770536,
					"max_snd_wnd":	8380928,
					"max_rtt":	102005,
					"min_rtt":	20092,
					"mean_rtt":	68895,
					"sender":	true
				},
				"receiver":	{
					"socket":	6,
					"start":	0,
					"end":	15.072904,
					"seconds":	15.000131,
					"bytes":	1681384296,
					"bits_per_second":	892400984.442016,
					"sender":	true
				}
			}],
		"sum_sent":	{
			"start":	0,
			"end":	15.000131,
			"seconds":	15.000131,
			"bytes":	1684537344,
			"bits_per_second":	898412070.667916,
			"retransmits":	700,
			"sender":	true
		},
		"sum_received":	{
			"start":	0,
			"end":	15.072904,
			"seconds":	15.072904,
			"bytes":	1681384296,
			"bits_per_second":	892400984.442016,
			"sender":	true
		},
		"cpu_utilization_percent":	{
			"host_total":	3.2911347263162383,
			"host_user":	0.15770205613228067,
			"host_system":	3.1334260415405151,
			"remote_total":	5.6555706702021844,
			"remote_user":	0.573166064970453,
			"remote_system":	5.0824046052317318
		},
		"sender_tcp_congestion":	"cubic",
		"receiver_tcp_congestion":	"cubic"
	}
}
